{
  "type": "Feature",
  "properties": {
    "gn:admin1_code":"04",
    "gn:asciiname":"Dolual",
    "gn:country_code":"SS",
    "gn:dem":414,
    "gn:feature_class":"P",
    "gn:feature_code":"PPL",
    "gn:name":"Dolual",
    "gn:population":0,
    "gn:timezone":"Africa/Juba",
    "iso:country":"SS",
    "wof:name":"Dolual",
    "wof:placetype":"locality"
},
  "geometry": {"coordinates":[29.83152,7.07832],"type":"Point"}
}