{
  "type": "Feature",
  "properties": {
    "gn:admin1_code":"08",
    "gn:asciiname":"Mang",
    "gn:country_code":"SS",
    "gn:dem":405,
    "gn:feature_class":"P",
    "gn:feature_code":"PPL",
    "gn:name":"Mang",
    "gn:population":0,
    "gn:timezone":"Africa/Juba",
    "iso:country":"SS",
    "name:ceb_x_preferred":[
        "Mang"
    ],
    "name:deu_x_preferred":[
        "Mang"
    ],
    "name:fra_x_preferred":[
        "Mang"
    ],
    "name:swe_x_preferred":[
        "Mang"
    ],
    "wof:lang_x_official":[
        "eng"
    ],
    "wof:lang_x_spoken":[
        "eng"
    ],
    "wof:name":"Mang",
    "wof:placetype":"locality"
},
  "geometry": {"coordinates":[28.40913,8.98335],"type":"Point"}
}