{
  "type": "Feature",
  "properties": {
    "gn:admin1_code":"01",
    "gn:asciiname":"Kiri",
    "gn:country_code":"SS",
    "gn:dem":954,
    "gn:feature_class":"P",
    "gn:feature_code":"PPL",
    "gn:name":"Kiri",
    "gn:population":0,
    "gn:timezone":"Africa/Juba",
    "iso:country":"SS",
    "name:ceb_x_preferred":[
        "Kiri"
    ],
    "name:deu_x_preferred":[
        "Kiri"
    ],
    "name:est_x_preferred":[
        "Kiri"
    ],
    "name:fas_x_preferred":[
        "\u06a9\u06cc\u0631\u06cc"
    ],
    "name:fin_x_preferred":[
        "Kiri"
    ],
    "name:fra_x_preferred":[
        "Kiri"
    ],
    "name:ind_x_preferred":[
        "Kiri"
    ],
    "name:ron_x_preferred":[
        "Kiri"
    ],
    "name:spa_x_preferred":[
        "Kiri"
    ],
    "name:swe_x_preferred":[
        "Kiri"
    ],
    "name:ukr_x_preferred":[
        "\u041a\u0456\u0440\u0456"
    ],
    "wof:name":"Kiri",
    "wof:placetype":"locality"
},
  "geometry": {"coordinates":[31.63521,3.77034],"type":"Point"}
}