{
  "type": "Feature",
  "properties": {
    "gn:admin1_code":"02",
    "gn:asciiname":"Larema",
    "gn:country_code":"SS",
    "gn:dem":1387,
    "gn:feature_class":"P",
    "gn:feature_code":"PPL",
    "gn:name":"Larema",
    "gn:population":0,
    "gn:timezone":"Africa/Juba",
    "iso:country":"SS",
    "name:fas_x_preferred":[
        "\u0644\u0627\u0631\u0645\u0627"
    ],
    "name:mzn_x_preferred":[
        "\u0644\u0627\u0631\u0645\u0627"
    ],
    "name:urd_x_preferred":[
        "\u0644\u0627\u0631\u06cc\u0645\u0627"
    ],
    "wof:name":"Larema",
    "wof:placetype":"locality"
},
  "geometry": {"coordinates":[33.62068,4.17239],"type":"Point"}
}