{
  "type": "Feature",
  "properties": {
    "gn:admin1_code":"10",
    "gn:asciiname":"Korai Kerjok",
    "gn:country_code":"SS",
    "gn:dem":490,
    "gn:feature_class":"P",
    "gn:feature_code":"PPL",
    "gn:name":"Korai Kerjok",
    "gn:population":0,
    "gn:timezone":"Africa/Juba",
    "iso:country":"SS",
    "wof:name":"Korai Kerjok",
    "wof:placetype":"locality"
},
  "geometry": {"coordinates":[29.91154,6.11585],"type":"Point"}
}