{
  "type": "Feature",
  "properties": {
    "gn:admin1_code":"07",
    "gn:asciiname":"Bil",
    "gn:country_code":"SS",
    "gn:dem":399,
    "gn:feature_class":"P",
    "gn:feature_code":"PPL",
    "gn:name":"Bil",
    "gn:population":0,
    "gn:timezone":"Africa/Juba",
    "iso:country":"SS",
    "wof:name":"Bil",
    "wof:placetype":"locality"
},
  "geometry": {"coordinates":[31.92808,9.31566],"type":"Point"}
}