{
  "type": "Feature",
  "properties": {
    "gn:admin1_code":"04",
    "gn:asciiname":"Jamkuach",
    "gn:country_code":"SS",
    "gn:dem":425,
    "gn:feature_class":"P",
    "gn:feature_code":"PPL",
    "gn:name":"Jamkuach",
    "gn:population":0,
    "gn:timezone":"Africa/Juba",
    "iso:country":"SS",
    "wof:name":"Jamkuach",
    "wof:placetype":"locality"
},
  "geometry": {"coordinates":[30.2882,6.80415],"type":"Point"}
}