{
  "type": "Feature",
  "properties": {
    "gn:admin1_code":"04",
    "gn:asciiname":"Palwal",
    "gn:country_code":"SS",
    "gn:dem":416,
    "gn:feature_class":"P",
    "gn:feature_code":"PPL",
    "gn:name":"Palwal",
    "gn:population":0,
    "gn:timezone":"Africa/Juba",
    "iso:country":"SS",
    "name:ara_x_preferred":[
        "\u0628\u0627\u0644\u0648\u0627\u0644"
    ],
    "name:ben_x_preferred":[
        "\u09aa\u09be\u09b2\u0993\u09af\u09bc\u09be\u09b2"
    ],
    "name:bih_x_preferred":[
        "\u092a\u0932\u0935\u0932"
    ],
    "name:bpy_x_preferred":[
        "\u09aa\u09be\u09b2\u09f1\u09be\u09b2"
    ],
    "name:ceb_x_preferred":[
        "Palwal"
    ],
    "name:deu_x_preferred":[
        "Palwal"
    ],
    "name:fra_x_preferred":[
        "Palwal"
    ],
    "name:hin_x_preferred":[
        "\u092a\u0932\u0935\u0932"
    ],
    "name:ita_x_preferred":[
        "Palwal"
    ],
    "name:mar_x_preferred":[
        "\u092a\u0932\u0935\u0932"
    ],
    "name:mlg_x_preferred":[
        "Palwal"
    ],
    "name:msa_x_preferred":[
        "Palwal"
    ],
    "name:nld_x_preferred":[
        "Palwal"
    ],
    "name:ori_x_preferred":[
        "\u0b2a\u0b32\u0b71\u0b3e\u0b32"
    ],
    "name:pam_x_preferred":[
        "Palwal"
    ],
    "name:rus_x_preferred":[
        "\u041f\u0430\u043b\u0432\u0430\u043b"
    ],
    "name:san_x_preferred":[
        "\u092a\u0932\u0935\u0932"
    ],
    "name:spa_x_preferred":[
        "Palwal"
    ],
    "name:swe_x_preferred":[
        "Palwal"
    ],
    "name:urd_x_preferred":[
        "\u067e\u0644\u0648\u0644"
    ],
    "name:vie_x_preferred":[
        "Palwal"
    ],
    "name:war_x_preferred":[
        "Palwal"
    ],
    "name:zho_x_preferred":[
        "\u5e15\u5c14\u74e6\u5c14"
    ],
    "wof:lang_x_official":[
        "eng"
    ],
    "wof:lang_x_spoken":[
        "eng"
    ],
    "wof:name":"Palwal",
    "wof:placetype":"locality"
},
  "geometry": {"coordinates":[31.04573,6.84749],"type":"Point"}
}