{
  "type": "Feature",
  "properties": {
    "gn:admin1_code":"08",
    "gn:asciiname":"Anong Lual",
    "gn:country_code":"SS",
    "gn:dem":407,
    "gn:feature_class":"P",
    "gn:feature_code":"PPL",
    "gn:name":"Anong Lual",
    "gn:population":0,
    "gn:timezone":"Africa/Juba",
    "iso:country":"SS",
    "wof:name":"Anong Lual",
    "wof:placetype":"locality"
},
  "geometry": {"coordinates":[28.29291,8.66064],"type":"Point"}
}