{
  "type": "Feature",
  "properties": {
    "gn:admin1_code":"10",
    "gn:asciiname":"Dazaki",
    "gn:country_code":"SS",
    "gn:dem":575,
    "gn:feature_class":"P",
    "gn:feature_code":"PPL",
    "gn:name":"Dazaki",
    "gn:population":0,
    "gn:timezone":"Africa/Juba",
    "iso:country":"SS",
    "wof:name":"Dazaki",
    "wof:placetype":"locality"
},
  "geometry": {"coordinates":[28.70549,5.89662],"type":"Point"}
}