{
  "type": "Feature",
  "properties": {
    "gn:admin1_code":"04",
    "gn:asciiname":"Mattok",
    "gn:country_code":"SS",
    "gn:dem":426,
    "gn:feature_class":"P",
    "gn:feature_code":"PPL",
    "gn:name":"Mattok",
    "gn:population":0,
    "gn:timezone":"Africa/Juba",
    "iso:country":"SS",
    "wof:name":"Mattok",
    "wof:placetype":"locality"
},
  "geometry": {"coordinates":[29.70647,6.8035],"type":"Point"}
}