{
  "type": "Feature",
  "properties": {
    "gn:admin1_code":"08",
    "gn:asciiname":"Abar",
    "gn:country_code":"SS",
    "gn:dem":424,
    "gn:feature_class":"P",
    "gn:feature_code":"PPL",
    "gn:name":"Abar",
    "gn:population":0,
    "gn:timezone":"Africa/Juba",
    "iso:country":"SS",
    "wof:name":"Abar",
    "wof:placetype":"locality"
},
  "geometry": {"coordinates":[28.87653,7.48513],"type":"Point"}
}