{
  "type": "Feature",
  "properties": {
    "gn:admin1_code":"07",
    "gn:asciiname":"Dud",
    "gn:country_code":"SS",
    "gn:dem":396,
    "gn:feature_class":"P",
    "gn:feature_code":"PPL",
    "gn:name":"Dud",
    "gn:population":0,
    "gn:timezone":"Africa/Juba",
    "iso:country":"SS",
    "name:pol_x_preferred":[
        "Niewypa\u0142"
    ],
    "wof:name":"Dud",
    "wof:placetype":"locality"
},
  "geometry": {"coordinates":[32.08035,9.24964],"type":"Point"}
}