{
  "type": "Feature",
  "properties": {
    "gn:admin1_code":"09",
    "gn:asciiname":"Doleib",
    "gn:country_code":"SS",
    "gn:dem":583,
    "gn:feature_class":"P",
    "gn:feature_code":"PPL",
    "gn:name":"Doleib",
    "gn:population":0,
    "gn:timezone":"Africa/Juba",
    "iso:country":"SS",
    "name:und_x_variant":[
        "Doleiba",
        "Doleib",
        "Dulayb"
    ],
    "wof:lang_x_official":[
        "eng"
    ],
    "wof:lang_x_spoken":[
        "eng"
    ],
    "wof:name":"Doleib",
    "wof:placetype":"locality"
},
  "geometry": {"coordinates":[26.11374,7.87134],"type":"Point"}
}