{
  "type": "Feature",
  "properties": {
    "gn:admin1_code":"04",
    "gn:asciiname":"Achigor",
    "gn:country_code":"SS",
    "gn:dem":440,
    "gn:feature_class":"P",
    "gn:feature_code":"PPL",
    "gn:name":"Achigor",
    "gn:population":0,
    "gn:timezone":"Africa/Juba",
    "iso:country":"SS",
    "wof:name":"Achigor",
    "wof:placetype":"locality"
},
  "geometry": {"coordinates":[30.47381,6.6927],"type":"Point"}
}