{
  "type": "Feature",
  "properties": {
    "gn:admin1_code":"01",
    "gn:asciiname":"Gado",
    "gn:country_code":"SS",
    "gn:dem":855,
    "gn:feature_class":"P",
    "gn:feature_code":"PPL",
    "gn:name":"Gado",
    "gn:population":0,
    "gn:timezone":"Africa/Juba",
    "iso:country":"SS",
    "name:ceb_x_preferred":[
        "Gado"
    ],
    "name:deu_x_preferred":[
        "Gado"
    ],
    "name:fra_x_preferred":[
        "Gado"
    ],
    "name:nld_x_preferred":[
        "Gado"
    ],
    "name:por_x_preferred":[
        "Gado"
    ],
    "name:swe_x_preferred":[
        "Gado"
    ],
    "wof:name":"Gado",
    "wof:placetype":"locality"
},
  "geometry": {"coordinates":[30.36667000000001,4.13333],"type":"Point"}
}