{
  "type": "Feature",
  "properties": {
    "gn:admin1_code":"10",
    "gn:asciiname":"Senango",
    "gn:country_code":"SS",
    "gn:dem":827,
    "gn:feature_class":"P",
    "gn:feature_code":"PPL",
    "gn:name":"Senango",
    "gn:population":0,
    "gn:timezone":"Africa/Juba",
    "iso:country":"SS",
    "wof:name":"Senango",
    "wof:placetype":"locality"
},
  "geometry": {"coordinates":[29.42924,4.72008],"type":"Point"}
}