{
  "type": "Feature",
  "properties": {
    "gn:admin1_code":"02",
    "gn:asciiname":"Lokila",
    "gn:country_code":"SS",
    "gn:dem":1294,
    "gn:feature_class":"P",
    "gn:feature_code":"PPL",
    "gn:name":"Lokila",
    "gn:population":0,
    "gn:timezone":"Africa/Juba",
    "iso:country":"SS",
    "wof:name":"Lokila",
    "wof:placetype":"locality"
},
  "geometry": {"coordinates":[33.17157,3.88881],"type":"Point"}
}