{
  "type": "Feature",
  "properties": {
    "gn:admin1_code":"01",
    "gn:asciiname":"Faker",
    "gn:country_code":"SS",
    "gn:dem":443,
    "gn:feature_class":"P",
    "gn:feature_code":"PPL",
    "gn:name":"Faker",
    "gn:population":0,
    "gn:timezone":"Africa/Juba",
    "iso:country":"SS",
    "name:deu_x_preferred":[
        "Faker"
    ],
    "name:kor_x_preferred":[
        "\ud398\uc774\ucee4"
    ],
    "name:por_x_preferred":[
        "Faker"
    ],
    "wof:name":"Faker",
    "wof:placetype":"locality"
},
  "geometry": {"coordinates":[31.83666,5.59111],"type":"Point"}
}