{
  "type": "Feature",
  "properties": {
    "gn:admin1_code":"04",
    "gn:asciiname":"Makoi",
    "gn:country_code":"SS",
    "gn:dem":437,
    "gn:feature_class":"P",
    "gn:feature_code":"PPL",
    "gn:name":"Makoi",
    "gn:population":0,
    "gn:timezone":"Africa/Juba",
    "iso:country":"SS",
    "wof:name":"Makoi",
    "wof:placetype":"locality"
},
  "geometry": {"coordinates":[31.00061,6.10391],"type":"Point"}
}