{
  "type": "Feature",
  "properties": {
    "gn:admin1_code":"28",
    "gn:asciiname":"Bariguna",
    "gn:country_code":"SS",
    "gn:dem":702,
    "gn:feature_class":"P",
    "gn:feature_code":"PPL",
    "gn:name":"Bariguna",
    "gn:population":0,
    "gn:timezone":"Africa/Juba",
    "iso:country":"SS",
    "wof:name":"Bariguna",
    "wof:placetype":"locality"
},
  "geometry": {"coordinates":[27.2995,5.27876],"type":"Point"}
}