{
  "type": "Feature",
  "properties": {
    "gn:admin1_code":"03",
    "gn:asciiname":"Neum",
    "gn:country_code":"SS",
    "gn:dem":432,
    "gn:feature_class":"P",
    "gn:feature_code":"PPL",
    "gn:name":"Neum",
    "gn:population":0,
    "gn:timezone":"Africa/Juba",
    "iso:country":"SS",
    "name:und_x_variant":[
        "Gneum",
        "Neum"
    ],
    "wof:name":"Neum",
    "wof:placetype":"locality"
},
  "geometry": {"coordinates":[34.02282,7.35096],"type":"Point"}
}