{
  "type": "Feature",
  "properties": {
    "gn:admin1_code":"03",
    "gn:asciiname":"Neum",
    "gn:country_code":"SS",
    "gn:dem":432,
    "gn:feature_class":"P",
    "gn:feature_code":"PPL",
    "gn:name":"Neum",
    "gn:population":0,
    "gn:timezone":"Africa/Juba",
    "iso:country":"SS",
    "name:bos_x_preferred":[
        "Neum"
    ],
    "name:bul_x_preferred":[
        "\u041d\u0435\u0443\u043c"
    ],
    "name:cat_x_preferred":[
        "Neum"
    ],
    "name:ceb_x_preferred":[
        "Neum"
    ],
    "name:ces_x_preferred":[
        "Neum"
    ],
    "name:dan_x_preferred":[
        "Neum"
    ],
    "name:deu_x_preferred":[
        "Neum"
    ],
    "name:epo_x_preferred":[
        "Neum"
    ],
    "name:est_x_preferred":[
        "Neum"
    ],
    "name:fra_x_preferred":[
        "Neum"
    ],
    "name:heb_x_preferred":[
        "\u05e0\u05d0\u05d5\u05dd"
    ],
    "name:hrv_x_preferred":[
        "Neum"
    ],
    "name:hun_x_preferred":[
        "Neum"
    ],
    "name:hye_x_preferred":[
        "\u0546\u0565\u0578\u0582\u0574"
    ],
    "name:ita_x_preferred":[
        "Neum"
    ],
    "name:jpn_x_preferred":[
        "\u30cd\u30a6\u30e0"
    ],
    "name:lat_x_preferred":[
        "Portus Noumensis"
    ],
    "name:lit_x_preferred":[
        "Neumas"
    ],
    "name:mkd_x_preferred":[
        "\u041d\u0435\u0443\u043c"
    ],
    "name:nld_x_preferred":[
        "Neum"
    ],
    "name:nor_x_preferred":[
        "Neum"
    ],
    "name:pol_x_preferred":[
        "Neum"
    ],
    "name:por_x_preferred":[
        "Neum"
    ],
    "name:ron_x_preferred":[
        "Neum"
    ],
    "name:rus_x_preferred":[
        "\u041d\u0435\u0443\u043c"
    ],
    "name:slk_x_preferred":[
        "Neum"
    ],
    "name:slv_x_preferred":[
        "Neum"
    ],
    "name:spa_x_preferred":[
        "Neum"
    ],
    "name:sqi_x_preferred":[
        "Neumi"
    ],
    "name:srp_x_preferred":[
        "\u041d\u0435\u0443\u043c"
    ],
    "name:swe_x_preferred":[
        "Neum"
    ],
    "name:tur_x_preferred":[
        "Neum"
    ],
    "name:ukr_x_preferred":[
        "\u041d\u0435\u0443\u043c"
    ],
    "name:und_x_variant":[
        "Gneum",
        "Neum"
    ],
    "name:urd_x_preferred":[
        "\u0646\u06cc\u0648\u0645"
    ],
    "name:vie_x_preferred":[
        "Neum"
    ],
    "wof:name":"Neum",
    "wof:placetype":"locality"
},
  "geometry": {"coordinates":[34.02282,7.35096],"type":"Point"}
}