{
  "type": "Feature",
  "properties": {
    "gn:admin1_code":"01",
    "gn:asciiname":"Langabu",
    "gn:country_code":"SS",
    "gn:dem":648,
    "gn:feature_class":"P",
    "gn:feature_code":"PPL",
    "gn:name":"Langabu",
    "gn:population":0,
    "gn:timezone":"Africa/Juba",
    "iso:country":"SS",
    "wof:name":"Langabu",
    "wof:placetype":"locality"
},
  "geometry": {"coordinates":[32.04904000000001,4.56598],"type":"Point"}
}