{
  "type": "Feature",
  "properties": {
    "gn:admin1_code":"02",
    "gn:asciiname":"Ulako",
    "gn:country_code":"SS",
    "gn:dem":557,
    "gn:feature_class":"P",
    "gn:feature_code":"PPL",
    "gn:name":"Ulako",
    "gn:population":0,
    "gn:timezone":"Africa/Juba",
    "iso:country":"SS",
    "wof:name":"Ulako",
    "wof:placetype":"locality"
},
  "geometry": {"coordinates":[31.82704,3.84605],"type":"Point"}
}