{
  "type": "Feature",
  "properties": {
    "gn:admin1_code":"10",
    "gn:asciiname":"Pakeir",
    "gn:country_code":"SS",
    "gn:dem":476,
    "gn:feature_class":"P",
    "gn:feature_code":"PPL",
    "gn:name":"Pakeir",
    "gn:population":0,
    "gn:timezone":"Africa/Juba",
    "iso:country":"SS",
    "wof:name":"Pakeir",
    "wof:placetype":"locality"
},
  "geometry": {"coordinates":[30.13042,6.26062],"type":"Point"}
}