{
  "type": "Feature",
  "properties": {
    "gn:admin1_code":"07",
    "gn:asciiname":"Kushuwa",
    "gn:country_code":"SS",
    "gn:dem":480,
    "gn:feature_class":"P",
    "gn:feature_code":"PPL",
    "gn:name":"Kushuwa",
    "gn:population":0,
    "gn:timezone":"Africa/Juba",
    "iso:country":"SS",
    "wof:name":"Kushuwa",
    "wof:placetype":"locality"
},
  "geometry": {"coordinates":[33.9298,9.20644],"type":"Point"}
}