{
  "type": "Feature",
  "properties": {
    "gn:admin1_code":"01",
    "gn:asciiname":"Jarra",
    "gn:country_code":"SS",
    "gn:dem":493,
    "gn:feature_class":"P",
    "gn:feature_code":"PPL",
    "gn:name":"Jarra",
    "gn:population":0,
    "gn:timezone":"Africa/Juba",
    "iso:country":"SS",
    "name:ceb_x_preferred":[
        "Jarra"
    ],
    "name:spa_x_preferred":[
        "Jarra"
    ],
    "name:swe_x_preferred":[
        "Jarra"
    ],
    "name:und_x_variant":[
        "Jarrah"
    ],
    "wof:name":"Jarra",
    "wof:placetype":"locality"
},
  "geometry": {"coordinates":[30.76652,5.69916],"type":"Point"}
}