{
  "type": "Feature",
  "properties": {
    "gn:admin1_code":"08",
    "gn:asciiname":"Adium",
    "gn:country_code":"SS",
    "gn:dem":415,
    "gn:feature_class":"P",
    "gn:feature_code":"PPL",
    "gn:name":"Adium",
    "gn:population":0,
    "gn:timezone":"Africa/Juba",
    "iso:country":"SS",
    "name:cat_x_preferred":[
        "Adium"
    ],
    "name:deu_x_preferred":[
        "Adium"
    ],
    "name:fin_x_preferred":[
        "Adium"
    ],
    "name:fra_x_preferred":[
        "Adium"
    ],
    "name:ita_x_preferred":[
        "Adium"
    ],
    "name:jpn_x_preferred":[
        "Adium"
    ],
    "name:kor_x_preferred":[
        "Adium"
    ],
    "name:lmo_x_preferred":[
        "Adium"
    ],
    "name:nld_x_preferred":[
        "Adium"
    ],
    "name:nor_x_preferred":[
        "Adium"
    ],
    "name:pol_x_preferred":[
        "Adium"
    ],
    "name:por_x_preferred":[
        "Adium"
    ],
    "name:rus_x_preferred":[
        "Adium"
    ],
    "name:spa_x_preferred":[
        "Adium"
    ],
    "name:swe_x_preferred":[
        "Adium"
    ],
    "name:tha_x_preferred":[
        "\u0e40\u0e2d\u0e40\u0e14\u0e35\u0e22\u0e21"
    ],
    "name:ukr_x_preferred":[
        "Adium"
    ],
    "name:zho_x_preferred":[
        "Adium"
    ],
    "wof:name":"Adium",
    "wof:placetype":"locality"
},
  "geometry": {"coordinates":[28.1734,8.543],"type":"Point"}
}