{
  "type": "Feature",
  "properties": {
    "gn:admin1_code":"09",
    "gn:asciiname":"Ghittan",
    "gn:country_code":"SS",
    "gn:dem":452,
    "gn:feature_class":"P",
    "gn:feature_code":"PPL",
    "gn:name":"Ghittan",
    "gn:population":0,
    "gn:timezone":"Africa/Juba",
    "iso:country":"SS",
    "wof:name":"Ghittan",
    "wof:placetype":"locality"
},
  "geometry": {"coordinates":[27.76184000000001,7.37982],"type":"Point"}
}