{
  "type": "Feature",
  "properties": {
    "gn:admin1_code":"08",
    "gn:asciiname":"Ayen",
    "gn:country_code":"SS",
    "gn:dem":412,
    "gn:feature_class":"P",
    "gn:feature_code":"PPL",
    "gn:name":"Ayen",
    "gn:population":0,
    "gn:timezone":"Africa/Juba",
    "iso:country":"SS",
    "name:bug_x_preferred":[
        "Ayen"
    ],
    "name:cat_x_preferred":[
        "Aient"
    ],
    "name:ceb_x_preferred":[
        "Ayen"
    ],
    "name:deu_x_preferred":[
        "Ayen"
    ],
    "name:epo_x_preferred":[
        "Ayen"
    ],
    "name:eus_x_preferred":[
        "Aient"
    ],
    "name:fra_x_preferred":[
        "Ayen"
    ],
    "name:hun_x_preferred":[
        "Ayen"
    ],
    "name:ind_x_preferred":[
        "Ayen"
    ],
    "name:ita_x_preferred":[
        "Ayen"
    ],
    "name:jpn_x_preferred":[
        "\u30a2\u30e4\u30f3"
    ],
    "name:kaz_x_preferred":[
        "\u0415\u044f\u043d"
    ],
    "name:lat_x_preferred":[
        "Ayen"
    ],
    "name:mlg_x_preferred":[
        "Ayen"
    ],
    "name:msa_x_preferred":[
        "Ayen"
    ],
    "name:nld_x_preferred":[
        "Ayen"
    ],
    "name:oci_x_preferred":[
        "Aient"
    ],
    "name:pol_x_preferred":[
        "Ayen"
    ],
    "name:por_x_preferred":[
        "Ayen"
    ],
    "name:ron_x_preferred":[
        "Ayen"
    ],
    "name:rus_x_preferred":[
        "\u0410\u0439\u0435\u043d"
    ],
    "name:slk_x_preferred":[
        "Ayen"
    ],
    "name:slv_x_preferred":[
        "Ayen"
    ],
    "name:spa_x_preferred":[
        "Ayen"
    ],
    "name:sqi_x_preferred":[
        "Ayen"
    ],
    "name:srp_x_preferred":[
        "\u0410\u0458\u0430\u043d"
    ],
    "name:swe_x_preferred":[
        "Ayen"
    ],
    "name:ukr_x_preferred":[
        "\u0415\u044f\u043d"
    ],
    "name:uzb_x_preferred":[
        "Ayen"
    ],
    "name:vie_x_preferred":[
        "Ayen"
    ],
    "name:vol_x_preferred":[
        "Ayen"
    ],
    "name:war_x_preferred":[
        "Ayen"
    ],
    "wof:name":"Ayen",
    "wof:placetype":"locality"
},
  "geometry": {"coordinates":[28.29526,8.96359],"type":"Point"}
}