{
  "type": "Feature",
  "properties": {
    "gn:admin1_code":"03",
    "gn:asciiname":"Kwoinlo",
    "gn:country_code":"SS",
    "gn:dem":402,
    "gn:feature_class":"P",
    "gn:feature_code":"PPL",
    "gn:name":"Kwoinlo",
    "gn:population":0,
    "gn:timezone":"Africa/Juba",
    "iso:country":"SS",
    "name:fra_x_preferred":[
        "Kwoinlo"
    ],
    "wof:name":"Kwoinlo",
    "wof:placetype":"locality"
},
  "geometry": {"coordinates":[30.77191,9.16613],"type":"Point"}
}