{
  "type": "Feature",
  "properties": {
    "gn:admin1_code":"07",
    "gn:asciiname":"Sheikh Jok",
    "gn:country_code":"SS",
    "gn:dem":395,
    "gn:feature_class":"P",
    "gn:feature_code":"PPL",
    "gn:name":"Sheikh Jok",
    "gn:population":0,
    "gn:timezone":"Africa/Juba",
    "iso:country":"SS",
    "name:und_x_variant":[
        "Shaykh Jok"
    ],
    "wof:name":"Sheikh Jok",
    "wof:placetype":"locality"
},
  "geometry": {"coordinates":[32.63831,10.96389],"type":"Point"}
}