{
  "type": "Feature",
  "properties": {
    "gn:admin1_code":"08",
    "gn:asciiname":"Neshir",
    "gn:country_code":"SS",
    "gn:dem":535,
    "gn:feature_class":"P",
    "gn:feature_code":"PPL",
    "gn:name":"Neshir",
    "gn:population":0,
    "gn:timezone":"Africa/Juba",
    "iso:country":"SS",
    "name:und_x_variant":[
        "Nash\u012br"
    ],
    "wof:name":"Neshir",
    "wof:placetype":"locality"
},
  "geometry": {"coordinates":[28.30197,7.18475],"type":"Point"}
}