{
  "type": "Feature",
  "properties": {
    "gn:admin1_code":"01",
    "gn:asciiname":"Lantoto",
    "gn:country_code":"SS",
    "gn:dem":859,
    "gn:feature_class":"P",
    "gn:feature_code":"PPL",
    "gn:name":"Lantoto",
    "gn:population":0,
    "gn:timezone":"Africa/Juba",
    "iso:country":"SS",
    "wof:name":"Lantoto",
    "wof:placetype":"locality"
},
  "geometry": {"coordinates":[30.00723,4.58869],"type":"Point"}
}