{
  "type": "Feature",
  "properties": {
    "gn:admin1_code":"02",
    "gn:asciiname":"Lonyori",
    "gn:country_code":"SS",
    "gn:dem":907,
    "gn:feature_class":"P",
    "gn:feature_code":"PPL",
    "gn:name":"Lonyori",
    "gn:population":0,
    "gn:timezone":"Africa/Juba",
    "iso:country":"SS",
    "wof:name":"Lonyori",
    "wof:placetype":"locality"
},
  "geometry": {"coordinates":[33.4015,3.8244],"type":"Point"}
}