{
  "type": "Feature",
  "properties": {
    "gn:admin1_code":"01",
    "gn:asciiname":"Queribe",
    "gn:country_code":"SS",
    "gn:dem":907,
    "gn:feature_class":"P",
    "gn:feature_code":"PPL",
    "gn:name":"Queribe",
    "gn:population":0,
    "gn:timezone":"Africa/Juba",
    "iso:country":"SS",
    "wof:name":"Queribe",
    "wof:placetype":"locality"
},
  "geometry": {"coordinates":[30.46664,3.94892],"type":"Point"}
}