{
  "type": "Feature",
  "properties": {
    "gn:admin1_code":"10",
    "gn:asciiname":"Aburra",
    "gn:country_code":"SS",
    "gn:dem":656,
    "gn:feature_class":"P",
    "gn:feature_code":"PPL",
    "gn:name":"Aburra",
    "gn:population":0,
    "gn:timezone":"Africa/Juba",
    "iso:country":"SS",
    "wof:lang_x_official":[
        "eng"
    ],
    "wof:lang_x_spoken":[
        "eng"
    ],
    "wof:name":"Aburra",
    "wof:placetype":"locality"
},
  "geometry": {"coordinates":[30.37237,5.07383],"type":"Point"}
}