{
  "type": "Feature",
  "properties": {
    "gn:admin1_code":"03",
    "gn:asciiname":"Kaiteng",
    "gn:country_code":"SS",
    "gn:dem":400,
    "gn:feature_class":"P",
    "gn:feature_code":"PPL",
    "gn:name":"Kaiteng",
    "gn:population":0,
    "gn:timezone":"Africa/Juba",
    "iso:country":"SS",
    "name:und_x_variant":[
        "Kayteng"
    ],
    "wof:name":"Kaiteng",
    "wof:placetype":"locality"
},
  "geometry": {"coordinates":[30.66817,8.55601],"type":"Point"}
}