{
  "type": "Feature",
  "properties": {
    "gn:admin1_code":"09",
    "gn:asciiname":"Mofigi",
    "gn:country_code":"SS",
    "gn:dem":657,
    "gn:feature_class":"P",
    "gn:feature_code":"PPL",
    "gn:name":"Mofigi",
    "gn:population":0,
    "gn:timezone":"Africa/Juba",
    "iso:country":"SS",
    "wof:name":"Mofigi",
    "wof:placetype":"locality"
},
  "geometry": {"coordinates":[24.47607,9.03741],"type":"Point"}
}