{
  "type": "Feature",
  "properties": {
    "gn:admin1_code":"01",
    "gn:asciiname":"Jimmeza",
    "gn:cc2":"SD",
    "gn:country_code":"SS",
    "gn:dem":441,
    "gn:feature_class":"P",
    "gn:feature_code":"PPL",
    "gn:name":"Jimmeza",
    "gn:population":0,
    "gn:timezone":"Africa/Juba",
    "iso:country":"SS",
    "name:und_x_variant":[
        "Jummayzah",
        "Jimmeza"
    ],
    "wof:name":"Jimmeza",
    "wof:placetype":"locality"
},
  "geometry": {"coordinates":[31.79972,5.68028],"type":"Point"}
}