{
  "type": "Feature",
  "properties": {
    "gn:admin1_code":"32",
    "gn:asciiname":"Turalei",
    "gn:country_code":"SS",
    "gn:dem":405,
    "gn:feature_class":"P",
    "gn:feature_code":"PPL",
    "gn:name":"Turalei",
    "gn:population":0,
    "gn:timezone":"Africa/Juba",
    "iso:country":"SS",
    "name:cat_x_preferred":[
        "Turalei"
    ],
    "name:fra_x_preferred":[
        "Turalei"
    ],
    "name:pol_x_preferred":[
        "Turalei"
    ],
    "wof:name":"Turalei",
    "wof:placetype":"locality"
},
  "geometry": {"coordinates":[28.4308,9.0912],"type":"Point"}
}