{
  "type": "Feature",
  "properties": {
    "gn:admin1_code":"09",
    "gn:asciiname":"Malak",
    "gn:country_code":"SS",
    "gn:dem":524,
    "gn:feature_class":"P",
    "gn:feature_code":"PPL",
    "gn:name":"Malak",
    "gn:population":0,
    "gn:timezone":"Africa/Juba",
    "iso:country":"SS",
    "name:ita_x_preferred":[
        "Malak"
    ],
    "name:msa_x_preferred":[
        "Malak"
    ],
    "name:nor_x_preferred":[
        "Malak"
    ],
    "name:swe_x_preferred":[
        "Malak"
    ],
    "wof:name":"Malak",
    "wof:placetype":"locality"
},
  "geometry": {"coordinates":[27.15,7.81667],"type":"Point"}
}