{
  "type": "Feature",
  "properties": {
    "gn:admin1_code":"07",
    "gn:asciiname":"Gwatan",
    "gn:country_code":"SS",
    "gn:dem":398,
    "gn:feature_class":"P",
    "gn:feature_code":"PPL",
    "gn:name":"Gwatan",
    "gn:population":0,
    "gn:timezone":"Africa/Juba",
    "iso:country":"SS",
    "wof:name":"Gwatan",
    "wof:placetype":"locality"
},
  "geometry": {"coordinates":[32.59694,9.96527],"type":"Point"}
}