{
  "type": "Feature",
  "properties": {
    "gn:admin1_code":"05",
    "gn:asciiname":"Kang Luel",
    "gn:country_code":"SS",
    "gn:dem":444,
    "gn:feature_class":"P",
    "gn:feature_code":"PPL",
    "gn:name":"Kang Luel",
    "gn:population":0,
    "gn:timezone":"Africa/Juba",
    "iso:country":"SS",
    "wof:name":"Kang Luel",
    "wof:placetype":"locality"
},
  "geometry": {"coordinates":[26.9051,9.16293],"type":"Point"}
}