{
  "type": "Feature",
  "properties": {
    "gn:admin1_code":"09",
    "gn:asciiname":"Abdullah Kyango",
    "gn:country_code":"SS",
    "gn:dem":513,
    "gn:feature_class":"P",
    "gn:feature_code":"PPL",
    "gn:name":"Abdullah Kyango",
    "gn:population":0,
    "gn:timezone":"Africa/Juba",
    "iso:country":"SS",
    "name:und_x_variant":[
        "Abduilah Kyango",
        "\u2018Abd All\u0101h Kyango"
    ],
    "wof:name":"Abdullah Kyango",
    "wof:placetype":"locality"
},
  "geometry": {"coordinates":[27.76548,7.63086],"type":"Point"}
}