{
  "type": "Feature",
  "properties": {
    "gn:admin1_code":"01",
    "gn:asciiname":"Gutetian",
    "gn:country_code":"SS",
    "gn:dem":445,
    "gn:feature_class":"P",
    "gn:feature_code":"PPL",
    "gn:name":"Gutetian",
    "gn:population":0,
    "gn:timezone":"Africa/Juba",
    "iso:country":"SS",
    "wof:name":"Gutetian",
    "wof:placetype":"locality"
},
  "geometry": {"coordinates":[31.44989,5.72121],"type":"Point"}
}