{
  "type": "Feature",
  "properties": {
    "gn:admin1_code":"02",
    "gn:asciiname":"Nagichot",
    "gn:country_code":"SS",
    "gn:dem":1969,
    "gn:feature_class":"P",
    "gn:feature_code":"PPL",
    "gn:name":"Nagichot",
    "gn:population":0,
    "gn:timezone":"Africa/Juba",
    "iso:country":"SS",
    "name:und_x_variant":[
        "Nagishot",
        "Naqishot",
        "Nagichot"
    ],
    "wof:name":"Nagichot",
    "wof:placetype":"locality"
},
  "geometry": {"coordinates":[33.56724000000001,4.27085],"type":"Point"}
}