{
  "type": "Feature",
  "properties": {
    "gn:admin1_code":"08",
    "gn:asciiname":"Shum",
    "gn:country_code":"SS",
    "gn:dem":428,
    "gn:feature_class":"P",
    "gn:feature_code":"PPL",
    "gn:name":"Shum",
    "gn:population":0,
    "gn:timezone":"Africa/Juba",
    "iso:country":"SS",
    "name:cat_x_preferred":[
        "Shum"
    ],
    "name:deu_x_preferred":[
        "Shum"
    ],
    "name:heb_x_preferred":[
        "\u05e9\u05d5\u05dd"
    ],
    "wof:name":"Shum",
    "wof:placetype":"locality"
},
  "geometry": {"coordinates":[28.8238,7.39737],"type":"Point"}
}