{
  "type": "Feature",
  "properties": {
    "gn:admin1_code":"04",
    "gn:asciiname":"Alliab",
    "gn:country_code":"SS",
    "gn:dem":455,
    "gn:feature_class":"P",
    "gn:feature_code":"PPL",
    "gn:name":"Alliab",
    "gn:population":0,
    "gn:timezone":"Africa/Juba",
    "iso:country":"SS",
    "wof:name":"Alliab",
    "wof:placetype":"locality"
},
  "geometry": {"coordinates":[29.47309000000001,6.58722],"type":"Point"}
}