{
  "type": "Feature",
  "properties": {
    "gn:admin1_code":"03",
    "gn:asciiname":"Yom",
    "gn:country_code":"SS",
    "gn:dem":397,
    "gn:feature_class":"P",
    "gn:feature_code":"PPL",
    "gn:name":"Yom",
    "gn:population":0,
    "gn:timezone":"Africa/Juba",
    "iso:country":"SS",
    "name:ara_x_preferred":[
        "\u064a\u0648\u0645"
    ],
    "name:ben_x_preferred":[
        "\u0987\u09af\u09bc\u09ae"
    ],
    "name:ell_x_preferred":[
        "\u0393\u03b9\u03bf\u03bc"
    ],
    "name:fas_x_preferred":[
        "\u06cc\u0648\u0648\u0645"
    ],
    "name:hin_x_preferred":[
        "\u092f\u094b\u092e"
    ],
    "name:hun_x_preferred":[
        "Yom"
    ],
    "name:ind_x_preferred":[
        "Yom"
    ],
    "name:pol_x_preferred":[
        "Yom"
    ],
    "name:swe_x_preferred":[
        "Yom"
    ],
    "name:tur_x_preferred":[
        "Yom"
    ],
    "name:ukr_x_preferred":[
        "\u0419\u043e\u043c"
    ],
    "name:urd_x_preferred":[
        "\u06cc\u0648\u0645"
    ],
    "name:zho_cn_x_preferred":[
        "\u6c38\u6cb3"
    ],
    "name:zho_tw_x_preferred":[
        "\u60a0\u59c6\u6cb3"
    ],
    "wof:name":"Yom",
    "wof:placetype":"locality"
},
  "geometry": {"coordinates":[30.78497,9.17763],"type":"Point"}
}