{
  "type": "Feature",
  "properties": {
    "gn:admin1_code":"09",
    "gn:asciiname":"Ghannam",
    "gn:country_code":"SS",
    "gn:dem":593,
    "gn:feature_class":"P",
    "gn:feature_code":"PPL",
    "gn:name":"Ghannam",
    "gn:population":0,
    "gn:timezone":"Africa/Juba",
    "iso:country":"SS",
    "wof:name":"Ghannam",
    "wof:placetype":"locality"
},
  "geometry": {"coordinates":[26.29786,7.68211],"type":"Point"}
}