{
  "type": "Feature",
  "properties": {
    "gn:admin1_code":"07",
    "gn:asciiname":"Um Dilwiz",
    "gn:country_code":"SS",
    "gn:dem":410,
    "gn:feature_class":"P",
    "gn:feature_code":"PPL",
    "gn:name":"Um Dilwiz",
    "gn:population":0,
    "gn:timezone":"Africa/Juba",
    "iso:country":"SS",
    "wof:name":"Um Dilwiz",
    "wof:placetype":"locality"
},
  "geometry": {"coordinates":[33.1092,12.1401],"type":"Point"}
}