{
  "type": "Feature",
  "properties": {
    "gn:admin1_code":"04",
    "gn:asciiname":"Rumlar",
    "gn:country_code":"SS",
    "gn:dem":417,
    "gn:feature_class":"P",
    "gn:feature_code":"PPL",
    "gn:name":"Rumlar",
    "gn:population":0,
    "gn:timezone":"Africa/Juba",
    "iso:country":"SS",
    "wof:name":"Rumlar",
    "wof:placetype":"locality"
},
  "geometry": {"coordinates":[29.57469,6.96852],"type":"Point"}
}