{
  "type": "Feature",
  "properties": {
    "gn:admin1_code":"05",
    "gn:asciiname":"Akwar",
    "gn:country_code":"SS",
    "gn:dem":456,
    "gn:feature_class":"P",
    "gn:feature_code":"PPL",
    "gn:name":"Akwar",
    "gn:population":0,
    "gn:timezone":"Africa/Juba",
    "iso:country":"SS",
    "wof:name":"Akwar",
    "wof:placetype":"locality"
},
  "geometry": {"coordinates":[26.72356,9.1006],"type":"Point"}
}