{
  "type": "Feature",
  "properties": {
    "gn:admin1_code":"08",
    "gn:asciiname":"Amul",
    "gn:country_code":"SS",
    "gn:dem":413,
    "gn:feature_class":"P",
    "gn:feature_code":"PPL",
    "gn:name":"Amul",
    "gn:population":0,
    "gn:timezone":"Africa/Juba",
    "iso:country":"SS",
    "wof:name":"Amul",
    "wof:placetype":"locality"
},
  "geometry": {"coordinates":[28.47747,8.60652],"type":"Point"}
}