{
  "type": "Feature",
  "properties": {
    "gn:admin1_code":"08",
    "gn:asciiname":"Amul",
    "gn:country_code":"SS",
    "gn:dem":413,
    "gn:feature_class":"P",
    "gn:feature_code":"PPL",
    "gn:name":"Amul",
    "gn:population":0,
    "gn:timezone":"Africa/Juba",
    "iso:country":"SS",
    "name:asm_x_preferred":[
        "\u0986\u09ae\u09c1\u09b2"
    ],
    "name:fra_x_preferred":[
        "Amul"
    ],
    "name:guj_x_preferred":[
        "\u0a85\u0aae\u0ac2\u0ab2"
    ],
    "name:hin_x_preferred":[
        "\u0905\u092e\u0942\u0932"
    ],
    "name:kan_x_preferred":[
        "\u0c85\u0cae\u0cc1\u0cb2\u0ccd"
    ],
    "name:mal_x_preferred":[
        "\u0d05\u0d2e\u0d42\u0d7d"
    ],
    "name:tam_x_preferred":[
        "\u0b85\u0bae\u0bc1\u0bb2\u0bcd"
    ],
    "name:tel_x_preferred":[
        "\u0c05\u0c2e\u0c42\u0c32\u0c4d"
    ],
    "wof:name":"Amul",
    "wof:placetype":"locality"
},
  "geometry": {"coordinates":[28.47747,8.60652],"type":"Point"}
}