{
  "type": "Feature",
  "properties": {
    "gn:admin1_code":"01",
    "gn:asciiname":"Kanza",
    "gn:country_code":"SS",
    "gn:dem":827,
    "gn:feature_class":"P",
    "gn:feature_code":"PPL",
    "gn:name":"Kanza",
    "gn:population":0,
    "gn:timezone":"Africa/Juba",
    "iso:country":"SS",
    "wof:name":"Kanza",
    "wof:placetype":"locality"
},
  "geometry": {"coordinates":[30.09994,4.53543],"type":"Point"}
}