{
  "type": "Feature",
  "properties": {
    "gn:admin1_code":"06",
    "gn:asciiname":"Thar Cheng",
    "gn:country_code":"SS",
    "gn:dem":394,
    "gn:feature_class":"P",
    "gn:feature_code":"PPL",
    "gn:name":"Thar Cheng",
    "gn:population":0,
    "gn:timezone":"Africa/Juba",
    "iso:country":"SS",
    "name:und_x_variant":[
        "Thar Jain",
        "Thar Cheng"
    ],
    "wof:lang_x_official":[
        "eng"
    ],
    "wof:lang_x_spoken":[
        "eng"
    ],
    "wof:name":"Thar Cheng",
    "wof:placetype":"locality"
},
  "geometry": {"coordinates":[30.22058,8.2229],"type":"Point"}
}