{
  "type": "Feature",
  "properties": {
    "gn:admin1_code":"03",
    "gn:asciiname":"Payom",
    "gn:country_code":"SS",
    "gn:dem":418,
    "gn:feature_class":"P",
    "gn:feature_code":"PPL",
    "gn:name":"Payom",
    "gn:population":0,
    "gn:timezone":"Africa/Juba",
    "iso:country":"SS",
    "wof:name":"Payom",
    "wof:placetype":"locality"
},
  "geometry": {"coordinates":[31.3385,6.86897],"type":"Point"}
}