{
  "type": "Feature",
  "properties": {
    "gn:admin1_code":"09",
    "gn:asciiname":"Girish",
    "gn:country_code":"SS",
    "gn:dem":469,
    "gn:feature_class":"P",
    "gn:feature_code":"PPL",
    "gn:name":"Girish",
    "gn:population":0,
    "gn:timezone":"Africa/Juba",
    "iso:country":"SS",
    "wof:name":"Girish",
    "wof:placetype":"locality"
},
  "geometry": {"coordinates":[27.77769,7.40269],"type":"Point"}
}