{
  "type": "Feature",
  "properties": {
    "gn:admin1_code":"01",
    "gn:asciiname":"Mankole",
    "gn:country_code":"SS",
    "gn:dem":767,
    "gn:feature_class":"P",
    "gn:feature_code":"PPL",
    "gn:name":"Mankole",
    "gn:population":0,
    "gn:timezone":"Africa/Juba",
    "iso:country":"SS",
    "name:eng_x_preferred":[
        "Mankole"
    ],
    "wof:name":"Mankole",
    "wof:placetype":"locality"
},
  "geometry": {"coordinates":[30.94049,4.63634],"type":"Point"}
}