{
  "type": "Feature",
  "properties": {
    "gn:admin1_code":"08",
    "gn:asciiname":"Lit Tok",
    "gn:country_code":"SS",
    "gn:dem":424,
    "gn:feature_class":"P",
    "gn:feature_code":"PPL",
    "gn:name":"Lit Tok",
    "gn:population":0,
    "gn:timezone":"Africa/Juba",
    "iso:country":"SS",
    "wof:name":"Lit Tok",
    "wof:placetype":"locality"
},
  "geometry": {"coordinates":[28.01911,8.18339],"type":"Point"}
}