{
  "type": "Feature",
  "properties": {
    "gn:admin1_code":"01",
    "gn:asciiname":"Tali Post",
    "gn:country_code":"SS",
    "gn:dem":454,
    "gn:feature_class":"P",
    "gn:feature_code":"PPL",
    "gn:name":"Tali Post",
    "gn:population":0,
    "gn:timezone":"Africa/Juba",
    "iso:country":"SS",
    "name:und_x_variant":[
        "Gell River Post",
        "Tali",
        "Tali Post"
    ],
    "wof:name":"Tali Post",
    "wof:placetype":"locality"
},
  "geometry": {"coordinates":[30.77865,5.88922],"type":"Point"}
}