{
  "type": "Feature",
  "properties": {
    "gn:admin1_code":"03",
    "gn:asciiname":"Pathai",
    "gn:country_code":"SS",
    "gn:dem":410,
    "gn:feature_class":"P",
    "gn:feature_code":"PPL",
    "gn:name":"Pathai",
    "gn:population":0,
    "gn:timezone":"Africa/Juba",
    "iso:country":"SS",
    "name:und_x_variant":[
        "Fathay",
        "Fathai"
    ],
    "wof:name":"Pathai",
    "wof:placetype":"locality"
},
  "geometry": {"coordinates":[31.83553,8.07148],"type":"Point"}
}