{
  "type": "Feature",
  "properties": {
    "iso:country":"SS",
    "name:ara_x_preferred":[
        "\u064a\u064a\u0631\u0648\u0644"
    ],
    "name:bul_x_preferred":[
        "\u0418\u0439\u0440\u043e\u043b"
    ],
    "name:ceb_x_preferred":[
        "Yirol"
    ],
    "name:eng_x_preferred":[
        "Yirol"
    ],
    "name:fra_x_preferred":[
        "Yirol"
    ],
    "name:ita_x_preferred":[
        "Yirol"
    ],
    "name:jpn_x_preferred":[
        "\u30a4\u30ed\u30eb"
    ],
    "name:nld_x_preferred":[
        "Yirol"
    ],
    "name:pol_x_preferred":[
        "Yirol"
    ],
    "name:rus_x_preferred":[
        "\u0419\u0438\u0440\u043e\u043b\u044c"
    ],
    "name:srp_x_preferred":[
        "\u0408\u0438\u0440\u043e\u043b"
    ],
    "name:swe_x_preferred":[
        "Yirol"
    ],
    "name:urd_x_preferred":[
        "\u06cc\u0627\u0631\u0648\u0644"
    ],
    "name:zho_x_preferred":[
        "\u4f0a\u7f85\u52d2"
    ],
    "qs:gn_country":"SS",
    "qs:gn_fcode":"PPL",
    "qs:gn_pop":0,
    "qs:name":"Yirol",
    "qs:name_adm0":"The Republic of South Sudan",
    "qs:name_adm1":"Lakes",
    "qs:photos":33,
    "qs:photos_1k":7,
    "qs:photos_9k":1,
    "qs:photos_9r":2,
    "qs:photos_all":33,
    "qs:photos_sr":2,
    "qs:placetype":"Town",
    "qs:pop_sr":"4",
    "qs:woe_adm0":56558055,
    "wd:wordcount":328,
    "wof:name":"Yirol",
    "wof:placetype":"locality"
},
  "geometry": {"coordinates":[30.49758,6.55097],"type":"Point"}
}