{
  "type": "Feature",
  "properties": {
    "gn:admin1_code":"02",
    "gn:asciiname":"Lumo",
    "gn:country_code":"SS",
    "gn:dem":596,
    "gn:feature_class":"P",
    "gn:feature_code":"PPL",
    "gn:name":"Lumo",
    "gn:population":0,
    "gn:timezone":"Africa/Juba",
    "iso:country":"SS",
    "wof:name":"Lumo",
    "wof:placetype":"locality"
},
  "geometry": {"coordinates":[32.50794,4.42829],"type":"Point"}
}