{
  "type": "Feature",
  "properties": {
    "gn:admin1_code":"07",
    "gn:asciiname":"Bilaiwal",
    "gn:country_code":"SS",
    "gn:dem":402,
    "gn:feature_class":"P",
    "gn:feature_code":"PPL",
    "gn:name":"Bilaiwal",
    "gn:population":0,
    "gn:timezone":"Africa/Juba",
    "iso:country":"SS",
    "wof:name":"Bilaiwal",
    "wof:placetype":"locality"
},
  "geometry": {"coordinates":[32.31672,9.10769],"type":"Point"}
}