{
  "type": "Feature",
  "properties": {
    "gn:admin1_code":"05",
    "gn:asciiname":"Nyor",
    "gn:country_code":"SS",
    "gn:dem":448,
    "gn:feature_class":"P",
    "gn:feature_code":"PPL",
    "gn:name":"Nyor",
    "gn:population":0,
    "gn:timezone":"Africa/Juba",
    "iso:country":"SS",
    "wof:name":"Nyor",
    "wof:placetype":"locality"
},
  "geometry": {"coordinates":[26.86071,9.14732],"type":"Point"}
}