{
  "type": "Feature",
  "properties": {
    "gn:admin1_code":"08",
    "gn:asciiname":"Bale",
    "gn:country_code":"SS",
    "gn:dem":416,
    "gn:feature_class":"P",
    "gn:feature_code":"PPL",
    "gn:name":"Bale",
    "gn:population":0,
    "gn:timezone":"Africa/Juba",
    "iso:country":"SS",
    "wof:name":"Bale",
    "wof:placetype":"locality"
},
  "geometry": {"coordinates":[28.01691,8.88938],"type":"Point"}
}