{
  "type": "Feature",
  "properties": {
    "gn:admin1_code":"07",
    "gn:asciiname":"Daga Post",
    "gn:country_code":"SS",
    "gn:dem":491,
    "gn:feature_class":"P",
    "gn:feature_code":"PPL",
    "gn:name":"Daga Post",
    "gn:population":0,
    "gn:timezone":"Africa/Juba",
    "iso:country":"SS",
    "name:und_x_variant":[
        "Daqa Post",
        "Daga River Post",
        "Daga Post"
    ],
    "wof:name":"Daga Post",
    "wof:placetype":"locality"
},
  "geometry": {"coordinates":[33.96107,9.20128],"type":"Point"}
}