{
  "type": "Feature",
  "properties": {
    "gn:admin1_code":"08",
    "gn:asciiname":"Akwaich",
    "gn:country_code":"SS",
    "gn:dem":404,
    "gn:feature_class":"P",
    "gn:feature_code":"PPL",
    "gn:name":"Akwaich",
    "gn:population":0,
    "gn:timezone":"Africa/Juba",
    "iso:country":"SS",
    "wof:name":"Akwaich",
    "wof:placetype":"locality"
},
  "geometry": {"coordinates":[28.47188,8.86593],"type":"Point"}
}