{
  "type": "Feature",
  "properties": {
    "gn:admin1_code":"09",
    "gn:asciiname":"Rabeh",
    "gn:country_code":"SS",
    "gn:dem":574,
    "gn:feature_class":"P",
    "gn:feature_code":"PPL",
    "gn:name":"Rabeh",
    "gn:population":0,
    "gn:timezone":"Africa/Juba",
    "iso:country":"SS",
    "name:fas_x_preferred":[
        "\u0631\u0639\u0628\u0647"
    ],
    "wof:lang_x_official":[
        "eng"
    ],
    "wof:lang_x_spoken":[
        "eng"
    ],
    "wof:name":"Rabeh",
    "wof:placetype":"locality"
},
  "geometry": {"coordinates":[25.70907,8.55647],"type":"Point"}
}