{
  "type": "Feature",
  "properties": {
    "gn:admin1_code":"06",
    "gn:asciiname":"Mowein",
    "gn:country_code":"SS",
    "gn:dem":403,
    "gn:feature_class":"P",
    "gn:feature_code":"PPL",
    "gn:name":"Mowein",
    "gn:population":0,
    "gn:timezone":"Africa/Juba",
    "iso:country":"SS",
    "wof:name":"Mowein",
    "wof:placetype":"locality"
},
  "geometry": {"coordinates":[28.41596,9.14016],"type":"Point"}
}