{
  "type": "Feature",
  "properties": {
    "gn:admin1_code":"07",
    "gn:asciiname":"Wunyat",
    "gn:country_code":"SS",
    "gn:dem":390,
    "gn:feature_class":"P",
    "gn:feature_code":"PPL",
    "gn:name":"Wunyat",
    "gn:population":0,
    "gn:timezone":"Africa/Juba",
    "iso:country":"SS",
    "wof:name":"Wunyat",
    "wof:placetype":"locality"
},
  "geometry": {"coordinates":[32.55693,10.60788],"type":"Point"}
}