{
  "type": "Feature",
  "properties": {
    "gn:admin1_code":"02",
    "gn:asciiname":"Ngoboli",
    "gn:country_code":"SS",
    "gn:dem":537,
    "gn:feature_class":"P",
    "gn:feature_code":"PPL",
    "gn:name":"Ngoboli",
    "gn:population":0,
    "gn:timezone":"Africa/Juba",
    "iso:country":"SS",
    "wof:lang_x_official":[
        "eng"
    ],
    "wof:lang_x_spoken":[
        "eng"
    ],
    "wof:name":"Ngoboli",
    "wof:placetype":"locality"
},
  "geometry": {"coordinates":[32.6006,4.90996],"type":"Point"}
}