{
  "type": "Feature",
  "properties": {
    "gn:admin1_code":"01",
    "gn:asciiname":"Girim",
    "gn:country_code":"SS",
    "gn:dem":919,
    "gn:feature_class":"P",
    "gn:feature_code":"PPL",
    "gn:name":"Girim",
    "gn:population":0,
    "gn:timezone":"Africa/Juba",
    "iso:country":"SS",
    "wof:name":"Girim",
    "wof:placetype":"locality"
},
  "geometry": {"coordinates":[31.04779000000001,4.21533],"type":"Point"}
}