{
  "type": "Feature",
  "properties": {
    "gn:admin1_code":"03",
    "gn:asciiname":"Chindura",
    "gn:country_code":"SS",
    "gn:dem":420,
    "gn:feature_class":"P",
    "gn:feature_code":"PPL",
    "gn:name":"Chindura",
    "gn:population":0,
    "gn:timezone":"Africa/Juba",
    "iso:country":"SS",
    "wof:name":"Chindura",
    "wof:placetype":"locality"
},
  "geometry": {"coordinates":[33.02987,6.91],"type":"Point"}
}