{
  "type": "Feature",
  "properties": {
    "gn:admin1_code":"10",
    "gn:asciiname":"Dabai",
    "gn:country_code":"SS",
    "gn:dem":518,
    "gn:feature_class":"P",
    "gn:feature_code":"PPL",
    "gn:name":"Dabai",
    "gn:population":0,
    "gn:timezone":"Africa/Juba",
    "iso:country":"SS",
    "wof:name":"Dabai",
    "wof:placetype":"locality"
},
  "geometry": {"coordinates":[29.97564,5.81699],"type":"Point"}
}