{
  "type": "Feature",
  "properties": {
    "gn:admin1_code":"06",
    "gn:asciiname":"Legnyang",
    "gn:country_code":"SS",
    "gn:dem":410,
    "gn:feature_class":"P",
    "gn:feature_code":"PPL",
    "gn:name":"Legnyang",
    "gn:population":0,
    "gn:timezone":"Africa/Juba",
    "iso:country":"SS",
    "wof:name":"Legnyang",
    "wof:placetype":"locality"
},
  "geometry": {"coordinates":[30.05139,9.91371],"type":"Point"}
}