{
  "type": "Feature",
  "properties": {
    "gn:admin1_code":"01",
    "gn:asciiname":"Nyaing",
    "gn:country_code":"SS",
    "gn:dem":628,
    "gn:feature_class":"P",
    "gn:feature_code":"PPL",
    "gn:name":"Nyaing",
    "gn:population":0,
    "gn:timezone":"Africa/Juba",
    "iso:country":"SS",
    "wof:name":"Nyaing",
    "wof:placetype":"locality"
},
  "geometry": {"coordinates":[31.62574,4.29466],"type":"Point"}
}