{
  "type": "Feature",
  "properties": {
    "gn:admin1_code":"04",
    "gn:asciiname":"Delbeng",
    "gn:country_code":"SS",
    "gn:dem":407,
    "gn:feature_class":"P",
    "gn:feature_code":"PPL",
    "gn:name":"Delbeng",
    "gn:population":0,
    "gn:timezone":"Africa/Juba",
    "iso:country":"SS",
    "wof:name":"Delbeng",
    "wof:placetype":"locality"
},
  "geometry": {"coordinates":[29.83122,7.46037],"type":"Point"}
}