{
  "type": "Feature",
  "properties": {
    "gn:admin1_code":"07",
    "gn:asciiname":"Sheikh Bade",
    "gn:country_code":"SS",
    "gn:dem":445,
    "gn:feature_class":"P",
    "gn:feature_code":"PPL",
    "gn:name":"Sheikh Bade",
    "gn:population":0,
    "gn:timezone":"Africa/Juba",
    "iso:country":"SS",
    "name:eng_x_preferred":[
        "Sheikh Bade"
    ],
    "name:und_x_variant":[
        "Shaykh Bade"
    ],
    "wof:name":"Sheikh Bade",
    "wof:placetype":"locality"
},
  "geometry": {"coordinates":[33.54336,10.24403],"type":"Point"}
}