{
  "type": "Feature",
  "properties": {
    "gn:admin1_code":"05",
    "gn:asciiname":"Ashwek",
    "gn:country_code":"SS",
    "gn:dem":406,
    "gn:feature_class":"P",
    "gn:feature_code":"PPL",
    "gn:name":"Ashwek",
    "gn:population":0,
    "gn:timezone":"Africa/Juba",
    "iso:country":"SS",
    "wof:name":"Ashwek",
    "wof:placetype":"locality"
},
  "geometry": {"coordinates":[28.19611,9.03725],"type":"Point"}
}