{
  "type": "Feature",
  "properties": {
    "gn:admin1_code":"07",
    "gn:asciiname":"Cham Thoni Jul",
    "gn:country_code":"SS",
    "gn:dem":409,
    "gn:feature_class":"P",
    "gn:feature_code":"PPL",
    "gn:name":"Cham Thoni Jul",
    "gn:population":0,
    "gn:timezone":"Africa/Juba",
    "iso:country":"SS",
    "wof:name":"Cham Thoni Jul",
    "wof:placetype":"locality"
},
  "geometry": {"coordinates":[33.53100999999999,8.48437],"type":"Point"}
}