{
  "type": "Feature",
  "properties": {
    "gn:admin1_code":"05",
    "gn:asciiname":"Niankwel",
    "gn:country_code":"SS",
    "gn:dem":429,
    "gn:feature_class":"P",
    "gn:feature_code":"PPL",
    "gn:name":"Niankwel",
    "gn:population":0,
    "gn:timezone":"Africa/Juba",
    "iso:country":"SS",
    "wof:name":"Niankwel",
    "wof:placetype":"locality"
},
  "geometry": {"coordinates":[27.23745,8.99166],"type":"Point"}
}