{
  "type": "Feature",
  "properties": {
    "gn:admin1_code":"09",
    "gn:asciiname":"Ngairanvor",
    "gn:country_code":"SS",
    "gn:dem":618,
    "gn:feature_class":"P",
    "gn:feature_code":"PPL",
    "gn:name":"Ngairanvor",
    "gn:population":0,
    "gn:timezone":"Africa/Juba",
    "iso:country":"SS",
    "wof:name":"Ngairanvor",
    "wof:placetype":"locality"
},
  "geometry": {"coordinates":[26.33077,7.67372],"type":"Point"}
}