{
  "type": "Feature",
  "properties": {
    "gn:admin1_code":"10",
    "gn:asciiname":"Mokkei",
    "gn:country_code":"SS",
    "gn:dem":495,
    "gn:feature_class":"P",
    "gn:feature_code":"PPL",
    "gn:name":"Mokkei",
    "gn:population":0,
    "gn:timezone":"Africa/Juba",
    "iso:country":"SS",
    "wof:name":"Mokkei",
    "wof:placetype":"locality"
},
  "geometry": {"coordinates":[29.96337,6.09215],"type":"Point"}
}