{
  "type": "Feature",
  "properties": {
    "gn:admin1_code":"28",
    "gn:asciiname":"Kaya",
    "gn:country_code":"SS",
    "gn:dem":1135,
    "gn:feature_class":"P",
    "gn:feature_code":"PPL",
    "gn:name":"Kaya",
    "gn:population":0,
    "gn:timezone":"Africa/Juba",
    "iso:country":"SS",
    "wof:name":"Kaya",
    "wof:placetype":"locality"
},
  "geometry": {"coordinates":[30.88,3.55],"type":"Point"}
}