{
  "type": "Feature",
  "properties": {
    "gn:admin1_code":"01",
    "gn:asciiname":"Marlango",
    "gn:country_code":"SS",
    "gn:dem":492,
    "gn:feature_class":"P",
    "gn:feature_code":"PPL",
    "gn:name":"Marlango",
    "gn:population":0,
    "gn:timezone":"Africa/Juba",
    "iso:country":"SS",
    "name:bcl_x_preferred":[
        "Marlango"
    ],
    "name:cat_x_preferred":[
        "Marlango"
    ],
    "name:deu_x_preferred":[
        "Marlango"
    ],
    "name:glg_x_preferred":[
        "Marlango"
    ],
    "name:ita_x_preferred":[
        "Marlango"
    ],
    "name:rus_x_preferred":[
        "Marlango"
    ],
    "name:spa_x_preferred":[
        "Marlango"
    ],
    "name:ukr_x_preferred":[
        "Marlango"
    ],
    "name:und_x_variant":[
        "Kobo"
    ],
    "wof:name":"Marlango",
    "wof:placetype":"locality"
},
  "geometry": {"coordinates":[30.55992,5.86775],"type":"Point"}
}