{
  "type": "Feature",
  "properties": {
    "gn:admin1_code":"03",
    "gn:asciiname":"Malek",
    "gn:country_code":"SS",
    "gn:dem":432,
    "gn:feature_class":"P",
    "gn:feature_code":"PPL",
    "gn:name":"Malek",
    "gn:population":0,
    "gn:timezone":"Africa/Juba",
    "iso:country":"SS",
    "name:ceb_x_preferred":[
        "Malek"
    ],
    "name:deu_x_preferred":[
        "Malek"
    ],
    "name:fra_x_preferred":[
        "Malek"
    ],
    "name:nds_x_preferred":[
        "Malek"
    ],
    "name:pol_x_preferred":[
        "Malek"
    ],
    "name:spa_x_preferred":[
        "Malek"
    ],
    "name:swe_x_preferred":[
        "Malek"
    ],
    "name:und_x_variant":[
        "Mal\u012bk"
    ],
    "wof:lang_x_official":[
        "eng"
    ],
    "wof:lang_x_spoken":[
        "eng"
    ],
    "wof:name":"Malek",
    "wof:placetype":"locality"
},
  "geometry": {"coordinates":[31.59975,6.0694],"type":"Point"}
}