{
  "type": "Feature",
  "properties": {
    "gn:admin1_code":"07",
    "gn:asciiname":"Cholei",
    "gn:country_code":"SS",
    "gn:dem":428,
    "gn:feature_class":"P",
    "gn:feature_code":"PPL",
    "gn:name":"Cholei",
    "gn:population":0,
    "gn:timezone":"Africa/Juba",
    "iso:country":"SS",
    "wof:name":"Cholei",
    "wof:placetype":"locality"
},
  "geometry": {"coordinates":[33.42001,10.24141],"type":"Point"}
}