{
  "type": "Feature",
  "properties": {
    "gn:admin1_code":"01",
    "gn:asciiname":"Kuio",
    "gn:country_code":"SS",
    "gn:dem":558,
    "gn:feature_class":"P",
    "gn:feature_code":"PPL",
    "gn:name":"Kuio",
    "gn:population":0,
    "gn:timezone":"Africa/Juba",
    "iso:country":"SS",
    "wof:name":"Kuio",
    "wof:placetype":"locality"
},
  "geometry": {"coordinates":[31.72062,3.95429],"type":"Point"}
}