{
  "type": "Feature",
  "properties": {
    "gn:admin1_code":"02",
    "gn:asciiname":"Idong",
    "gn:country_code":"SS",
    "gn:dem":659,
    "gn:feature_class":"P",
    "gn:feature_code":"PPL",
    "gn:name":"Idong",
    "gn:population":0,
    "gn:timezone":"Africa/Juba",
    "iso:country":"SS",
    "wof:name":"Idong",
    "wof:placetype":"locality"
},
  "geometry": {"coordinates":[33.56985,4.79853],"type":"Point"}
}