{
  "type": "Feature",
  "properties": {
    "gn:admin1_code":"04",
    "gn:asciiname":"Lang",
    "gn:country_code":"SS",
    "gn:dem":422,
    "gn:feature_class":"P",
    "gn:feature_code":"PPL",
    "gn:name":"Lang",
    "gn:population":0,
    "gn:timezone":"Africa/Juba",
    "iso:country":"SS",
    "name:ara_x_preferred":[
        "\u0644\u0627\u0646\u063a"
    ],
    "name:cat_x_preferred":[
        "Lang"
    ],
    "name:ceb_x_preferred":[
        "Lang"
    ],
    "name:ces_x_preferred":[
        "Lang"
    ],
    "name:csb_x_preferred":[
        "Lang Czes\u0142aw"
    ],
    "name:deu_x_preferred":[
        "Lang"
    ],
    "name:fin_x_preferred":[
        "Lang"
    ],
    "name:fra_x_preferred":[
        "Lang"
    ],
    "name:hat_x_preferred":[
        "Lang"
    ],
    "name:heb_x_preferred":[
        "\u05dc\u05d0\u05e0\u05d2"
    ],
    "name:ita_x_preferred":[
        "Lang"
    ],
    "name:jpn_x_preferred":[
        "\u30e9\u30f3\u30b0"
    ],
    "name:nld_x_preferred":[
        "Lang"
    ],
    "name:pol_x_preferred":[
        "Lang"
    ],
    "name:por_x_preferred":[
        "Lang"
    ],
    "name:ron_x_preferred":[
        "Lang"
    ],
    "name:rus_x_preferred":[
        "Lang"
    ],
    "name:slk_x_preferred":[
        "Lang"
    ],
    "name:spa_x_preferred":[
        "Lang"
    ],
    "name:swe_x_preferred":[
        "Lang"
    ],
    "wof:name":"Lang",
    "wof:placetype":"locality"
},
  "geometry": {"coordinates":[29.99561,6.88015],"type":"Point"}
}