{
  "type": "Feature",
  "properties": {
    "gn:admin1_code":"09",
    "gn:asciiname":"Abuge",
    "gn:country_code":"SS",
    "gn:dem":542,
    "gn:feature_class":"P",
    "gn:feature_code":"PPL",
    "gn:name":"Abug\u00e9",
    "gn:population":0,
    "gn:timezone":"Africa/Juba",
    "iso:country":"SS",
    "wof:name":"Abuge",
    "wof:placetype":"locality"
},
  "geometry": {"coordinates":[25.73673,8.87282],"type":"Point"}
}