{
  "type": "Feature",
  "properties": {
    "gn:admin1_code":"08",
    "gn:asciiname":"Dang",
    "gn:country_code":"SS",
    "gn:dem":413,
    "gn:feature_class":"P",
    "gn:feature_code":"PPL",
    "gn:name":"Dang",
    "gn:population":0,
    "gn:timezone":"Africa/Juba",
    "iso:country":"SS",
    "name:ceb_x_preferred":[
        "Dang"
    ],
    "name:deu_x_preferred":[
        "Dang"
    ],
    "name:fra_x_preferred":[
        "Dang"
    ],
    "name:nld_x_preferred":[
        "Dang"
    ],
    "name:swe_x_preferred":[
        "Dang"
    ],
    "name:tam_x_preferred":[
        "\u0b9f\u0bbe\u0b99\u0bcd \u0bae\u0bbe\u0bb5\u0b9f\u0bcd\u0b9f\u0bae\u0bcd"
    ],
    "name:und_x_variant":[
        "Dong"
    ],
    "wof:lang_x_official":[
        "eng"
    ],
    "wof:lang_x_spoken":[
        "eng"
    ],
    "wof:name":"Dang",
    "wof:placetype":"locality"
},
  "geometry": {"coordinates":[28.13775,8.74321],"type":"Point"}
}