{
  "type": "Feature",
  "properties": {
    "gn:admin1_code":"05",
    "gn:asciiname":"Malwal",
    "gn:country_code":"SS",
    "gn:dem":429,
    "gn:feature_class":"P",
    "gn:feature_code":"PPL",
    "gn:name":"Malwal",
    "gn:population":0,
    "gn:timezone":"Africa/Juba",
    "iso:country":"SS",
    "name:und_x_variant":[
        "Malwal Dit"
    ],
    "wof:name":"Malwal",
    "wof:placetype":"locality"
},
  "geometry": {"coordinates":[27.32436,9.07759],"type":"Point"}
}