{
  "type": "Feature",
  "properties": {
    "gn:admin1_code":"08",
    "gn:asciiname":"Dumbil",
    "gn:country_code":"SS",
    "gn:dem":406,
    "gn:feature_class":"P",
    "gn:feature_code":"PPL",
    "gn:name":"Dumbil",
    "gn:population":0,
    "gn:timezone":"Africa/Juba",
    "iso:country":"SS",
    "wof:name":"Dumbil",
    "wof:placetype":"locality"
},
  "geometry": {"coordinates":[28.58402,8.37053],"type":"Point"}
}