{
  "type": "Feature",
  "properties": {
    "gn:admin1_code":"01",
    "gn:asciiname":"Akasu",
    "gn:country_code":"SS",
    "gn:dem":959,
    "gn:feature_class":"P",
    "gn:feature_code":"PPL",
    "gn:name":"Akasu",
    "gn:population":0,
    "gn:timezone":"Africa/Juba",
    "iso:country":"SS",
    "wof:name":"Akasu",
    "wof:placetype":"locality"
},
  "geometry": {"coordinates":[30.74204000000001,3.92555],"type":"Point"}
}