{
  "type": "Feature",
  "properties": {
    "gn:admin1_code":"08",
    "gn:asciiname":"Fankot",
    "gn:country_code":"SS",
    "gn:dem":426,
    "gn:feature_class":"P",
    "gn:feature_code":"PPL",
    "gn:name":"Fankot",
    "gn:population":0,
    "gn:timezone":"Africa/Juba",
    "iso:country":"SS",
    "wof:name":"Fankot",
    "wof:placetype":"locality"
},
  "geometry": {"coordinates":[28.84402,7.35757],"type":"Point"}
}