{
  "type": "Feature",
  "properties": {
    "gn:admin1_code":"01",
    "gn:asciiname":"Nyori",
    "gn:country_code":"SS",
    "gn:dem":887,
    "gn:feature_class":"P",
    "gn:feature_code":"PPL",
    "gn:name":"Nyori",
    "gn:population":0,
    "gn:timezone":"Africa/Juba",
    "iso:country":"SS",
    "wof:name":"Nyori",
    "wof:placetype":"locality"
},
  "geometry": {"coordinates":[30.42133,3.94013],"type":"Point"}
}