{
  "type": "Feature",
  "properties": {
    "gn:admin1_code":"03",
    "gn:asciiname":"Kavolla",
    "gn:country_code":"SS",
    "gn:dem":419,
    "gn:feature_class":"P",
    "gn:feature_code":"PPL",
    "gn:name":"Kavolla",
    "gn:population":0,
    "gn:timezone":"Africa/Juba",
    "iso:country":"SS",
    "wof:name":"Kavolla",
    "wof:placetype":"locality"
},
  "geometry": {"coordinates":[33.65922,6.70146],"type":"Point"}
}