{
  "type": "Feature",
  "properties": {
    "gn:admin1_code":"04",
    "gn:asciiname":"Chuei Nyijang",
    "gn:country_code":"SS",
    "gn:dem":428,
    "gn:feature_class":"P",
    "gn:feature_code":"PPL",
    "gn:name":"Chuei Nyijang",
    "gn:population":0,
    "gn:timezone":"Africa/Juba",
    "iso:country":"SS",
    "wof:name":"Chuei Nyijang",
    "wof:placetype":"locality"
},
  "geometry": {"coordinates":[30.22329,6.75011],"type":"Point"}
}