{
  "type": "Feature",
  "properties": {
    "gn:admin1_code":"04",
    "gn:asciiname":"Abui",
    "gn:country_code":"SS",
    "gn:dem":422,
    "gn:feature_class":"P",
    "gn:feature_code":"PPL",
    "gn:name":"Abui",
    "gn:population":0,
    "gn:timezone":"Africa/Juba",
    "iso:country":"SS",
    "wof:name":"Abui",
    "wof:placetype":"locality"
},
  "geometry": {"coordinates":[30.21413,6.83831],"type":"Point"}
}