{
  "type": "Feature",
  "properties": {
    "gn:admin1_code":"10",
    "gn:asciiname":"Birshi",
    "gn:country_code":"SS",
    "gn:dem":623,
    "gn:feature_class":"P",
    "gn:feature_code":"PPL",
    "gn:name":"Birshi",
    "gn:population":0,
    "gn:timezone":"Africa/Juba",
    "iso:country":"SS",
    "wof:name":"Birshi",
    "wof:placetype":"locality"
},
  "geometry": {"coordinates":[28.79231,5.78178],"type":"Point"}
}