{
  "type": "Feature",
  "properties": {
    "gn:admin1_code":"05",
    "gn:asciiname":"Gordem",
    "gn:country_code":"SS",
    "gn:dem":424,
    "gn:feature_class":"P",
    "gn:feature_code":"PPL",
    "gn:name":"Gordem",
    "gn:population":0,
    "gn:timezone":"Africa/Juba",
    "iso:country":"SS",
    "wof:name":"Gordem",
    "wof:placetype":"locality"
},
  "geometry": {"coordinates":[27.59483,8.9895],"type":"Point"}
}