{
  "type": "Feature",
  "properties": {
    "gn:admin1_code":"04",
    "gn:asciiname":"Dokweri",
    "gn:country_code":"SS",
    "gn:dem":457,
    "gn:feature_class":"P",
    "gn:feature_code":"PPL",
    "gn:name":"Dokweri",
    "gn:population":0,
    "gn:timezone":"Africa/Juba",
    "iso:country":"SS",
    "wof:name":"Dokweri",
    "wof:placetype":"locality"
},
  "geometry": {"coordinates":[30.23852,6.14049],"type":"Point"}
}