{
  "type": "Feature",
  "properties": {
    "gn:admin1_code":"01",
    "gn:asciiname":"Langile",
    "gn:country_code":"SS",
    "gn:dem":745,
    "gn:feature_class":"P",
    "gn:feature_code":"PPL",
    "gn:name":"Langile",
    "gn:population":0,
    "gn:timezone":"Africa/Juba",
    "iso:country":"SS",
    "wof:name":"Langile",
    "wof:placetype":"locality"
},
  "geometry": {"coordinates":[31.73186,3.87997],"type":"Point"}
}