{
  "type": "Feature",
  "properties": {
    "gn:admin1_code":"04",
    "gn:asciiname":"Ajak",
    "gn:country_code":"SS",
    "gn:dem":414,
    "gn:feature_class":"P",
    "gn:feature_code":"PPL",
    "gn:name":"Ajak",
    "gn:population":0,
    "gn:timezone":"Africa/Juba",
    "iso:country":"SS",
    "wof:name":"Ajak",
    "wof:placetype":"locality"
},
  "geometry": {"coordinates":[29.72278,7.11667],"type":"Point"}
}