{
  "type": "Feature",
  "properties": {
    "gn:admin1_code":"05",
    "gn:asciiname":"Kwol",
    "gn:country_code":"SS",
    "gn:dem":440,
    "gn:feature_class":"P",
    "gn:feature_code":"PPL",
    "gn:name":"Kwol",
    "gn:population":0,
    "gn:timezone":"Africa/Juba",
    "iso:country":"SS",
    "wof:name":"Kwol",
    "wof:placetype":"locality"
},
  "geometry": {"coordinates":[26.9749,9.17816],"type":"Point"}
}