{
  "type": "Feature",
  "properties": {
    "gn:admin1_code":"08",
    "gn:asciiname":"Malwal",
    "gn:country_code":"SS",
    "gn:dem":410,
    "gn:feature_class":"P",
    "gn:feature_code":"PPL",
    "gn:name":"Malwal",
    "gn:population":0,
    "gn:timezone":"Africa/Juba",
    "iso:country":"SS",
    "wof:name":"Malwal",
    "wof:placetype":"locality"
},
  "geometry": {"coordinates":[28.26384,8.67949],"type":"Point"}
}