{
  "type": "Feature",
  "properties": {
    "gn:admin1_code":"07",
    "gn:asciiname":"Nila",
    "gn:country_code":"SS",
    "gn:dem":470,
    "gn:feature_class":"P",
    "gn:feature_code":"PPL",
    "gn:name":"Nila",
    "gn:population":0,
    "gn:timezone":"Africa/Juba",
    "iso:country":"SS",
    "name:ceb_x_preferred":[
        "Nila"
    ],
    "name:deu_x_preferred":[
        "Nila"
    ],
    "name:eng_x_preferred":[
        "Nila"
    ],
    "name:ind_x_preferred":[
        "Nila"
    ],
    "name:jav_x_preferred":[
        "Nila"
    ],
    "name:rus_x_preferred":[
        "\u041d\u0438\u043b\u0430"
    ],
    "name:slk_x_preferred":[
        "Nila"
    ],
    "name:swe_x_preferred":[
        "Nila"
    ],
    "wof:lang_x_official":[
        "eng"
    ],
    "wof:lang_x_spoken":[
        "eng"
    ],
    "wof:name":"Nila",
    "wof:placetype":"locality"
},
  "geometry": {"coordinates":[33.82486,10.10794],"type":"Point"}
}