{
  "type": "Feature",
  "properties": {
    "gn:admin1_code":"03",
    "gn:asciiname":"Fakwar",
    "gn:country_code":"SS",
    "gn:dem":416,
    "gn:feature_class":"P",
    "gn:feature_code":"PPL",
    "gn:name":"Fakwar",
    "gn:population":0,
    "gn:timezone":"Africa/Juba",
    "iso:country":"SS",
    "wof:name":"Fakwar",
    "wof:placetype":"locality"
},
  "geometry": {"coordinates":[31.37316,7.11707],"type":"Point"}
}