{
  "type": "Feature",
  "properties": {
    "gn:admin1_code":"02",
    "gn:asciiname":"Longilayo",
    "gn:country_code":"SS",
    "gn:dem":824,
    "gn:feature_class":"P",
    "gn:feature_code":"PPL",
    "gn:name":"Longilayo",
    "gn:population":0,
    "gn:timezone":"Africa/Juba",
    "iso:country":"SS",
    "wof:name":"Longilayo",
    "wof:placetype":"locality"
},
  "geometry": {"coordinates":[32.67225,4.87541],"type":"Point"}
}