{
  "type": "Feature",
  "properties": {
    "gn:admin1_code":"08",
    "gn:asciiname":"Rab Akon",
    "gn:country_code":"SS",
    "gn:dem":412,
    "gn:feature_class":"P",
    "gn:feature_code":"PPL",
    "gn:name":"Rab Akon",
    "gn:population":0,
    "gn:timezone":"Africa/Juba",
    "iso:country":"SS",
    "wof:name":"Rab Akon",
    "wof:placetype":"locality"
},
  "geometry": {"coordinates":[28.23361,8.65174],"type":"Point"}
}