{
  "type": "Feature",
  "properties": {
    "gn:admin1_code":"05",
    "gn:asciiname":"Fan Bea",
    "gn:country_code":"SS",
    "gn:dem":406,
    "gn:feature_class":"P",
    "gn:feature_code":"PPL",
    "gn:name":"Fan Bea",
    "gn:population":0,
    "gn:timezone":"Africa/Juba",
    "iso:country":"SS",
    "wof:name":"Fan Bea",
    "wof:placetype":"locality"
},
  "geometry": {"coordinates":[28.16477,9.06686],"type":"Point"}
}