{
  "type": "Feature",
  "properties": {
    "gn:admin1_code":"07",
    "gn:asciiname":"Wunawol",
    "gn:country_code":"SS",
    "gn:dem":391,
    "gn:feature_class":"P",
    "gn:feature_code":"PPL",
    "gn:name":"Wunawol",
    "gn:population":0,
    "gn:timezone":"Africa/Juba",
    "iso:country":"SS",
    "name:und_x_variant":[
        "Wunangwi",
        "Wunawol"
    ],
    "wof:name":"Wunawol",
    "wof:placetype":"locality"
},
  "geometry": {"coordinates":[32.59681,10.81654],"type":"Point"}
}