{
  "type": "Feature",
  "properties": {
    "gn:admin1_code":"06",
    "gn:asciiname":"Ahmed `Arabi",
    "gn:country_code":"SS",
    "gn:dem":397,
    "gn:feature_class":"P",
    "gn:feature_code":"PPL",
    "gn:name":"Ahmed \u2018Arabi",
    "gn:population":0,
    "gn:timezone":"Africa/Juba",
    "iso:country":"SS",
    "name:und_x_variant":[
        "Ahmed \u2018Arabi",
        "A\u1e29mad \u2018Arab\u012b"
    ],
    "wof:name":"Ahmed `Arabi",
    "wof:placetype":"locality"
},
  "geometry": {"coordinates":[29.81506,9.17116],"type":"Point"}
}