{
  "type": "Feature",
  "properties": {
    "gn:admin1_code":"08",
    "gn:asciiname":"Malau",
    "gn:country_code":"SS",
    "gn:dem":472,
    "gn:feature_class":"P",
    "gn:feature_code":"PPL",
    "gn:name":"Malau",
    "gn:population":0,
    "gn:timezone":"Africa/Juba",
    "iso:country":"SS",
    "wof:name":"Malau",
    "wof:placetype":"locality"
},
  "geometry": {"coordinates":[27.79209,8.29885],"type":"Point"}
}