{
  "type": "Feature",
  "properties": {
    "gn:admin1_code":"03",
    "gn:asciiname":"Konkyau",
    "gn:country_code":"SS",
    "gn:dem":405,
    "gn:feature_class":"P",
    "gn:feature_code":"PPL",
    "gn:name":"Konkyau",
    "gn:population":0,
    "gn:timezone":"Africa/Juba",
    "iso:country":"SS",
    "wof:name":"Konkyau",
    "wof:placetype":"locality"
},
  "geometry": {"coordinates":[32.31463,8.31755],"type":"Point"}
}