{
  "type": "Feature",
  "properties": {
    "gn:admin1_code":"03",
    "gn:asciiname":"Jungshol",
    "gn:country_code":"SS",
    "gn:dem":405,
    "gn:feature_class":"P",
    "gn:feature_code":"PPL",
    "gn:name":"Jungshol",
    "gn:population":0,
    "gn:timezone":"Africa/Juba",
    "iso:country":"SS",
    "wof:name":"Jungshol",
    "wof:placetype":"locality"
},
  "geometry": {"coordinates":[30.83054000000001,8.11033],"type":"Point"}
}