{
  "type": "Feature",
  "properties": {
    "gn:admin1_code":"03",
    "gn:asciiname":"Mudi",
    "gn:country_code":"SS",
    "gn:dem":401,
    "gn:feature_class":"P",
    "gn:feature_code":"PPL",
    "gn:name":"Mudi",
    "gn:population":0,
    "gn:timezone":"Africa/Juba",
    "iso:country":"SS",
    "wof:name":"Mudi",
    "wof:placetype":"locality"
},
  "geometry": {"coordinates":[30.88355,9.29653],"type":"Point"}
}