{
  "type": "Feature",
  "properties": {
    "gn:admin1_code":"07",
    "gn:asciiname":"Ogra",
    "gn:country_code":"SS",
    "gn:dem":400,
    "gn:feature_class":"P",
    "gn:feature_code":"PPL",
    "gn:name":"Ogra",
    "gn:population":0,
    "gn:timezone":"Africa/Juba",
    "iso:country":"SS",
    "name:ceb_x_preferred":[
        "Comuna Ogra"
    ],
    "name:deu_x_preferred":[
        "Ogra"
    ],
    "name:epo_x_preferred":[
        "Ogra"
    ],
    "name:fra_x_preferred":[
        "Ogra"
    ],
    "name:ita_x_preferred":[
        "Ogra"
    ],
    "name:msa_x_preferred":[
        "Ogra"
    ],
    "name:nld_x_preferred":[
        "Ogra"
    ],
    "name:por_x_preferred":[
        "Ogra"
    ],
    "name:ron_x_preferred":[
        "Comuna Ogra"
    ],
    "name:srp_x_preferred":[
        "\u041e\u043f\u0448\u0442\u0438\u043d\u0430 \u041e\u0433\u0440\u0430"
    ],
    "name:ukr_x_preferred":[
        "\u041e\u0433\u0440\u0430"
    ],
    "name:vie_x_preferred":[
        "Ogra"
    ],
    "name:vol_x_preferred":[
        "Ogra"
    ],
    "name:zho_x_preferred":[
        "\u5967\u683c\u62c9\u9109"
    ],
    "wof:name":"Ogra",
    "wof:placetype":"locality"
},
  "geometry": {"coordinates":[32.9382,11.4136],"type":"Point"}
}