{
  "type": "Feature",
  "properties": {
    "gn:admin1_code":"07",
    "gn:asciiname":"Ogra",
    "gn:country_code":"SS",
    "gn:dem":400,
    "gn:feature_class":"P",
    "gn:feature_code":"PPL",
    "gn:name":"Ogra",
    "gn:population":0,
    "gn:timezone":"Africa/Juba",
    "iso:country":"SS",
    "wof:name":"Ogra",
    "wof:placetype":"locality"
},
  "geometry": {"coordinates":[32.9382,11.4136],"type":"Point"}
}