{
  "type": "Feature",
  "properties": {
    "gn:admin1_code":"09",
    "gn:asciiname":"`Angareb",
    "gn:country_code":"SS",
    "gn:dem":556,
    "gn:feature_class":"P",
    "gn:feature_code":"PPL",
    "gn:name":"\u2018Angareb",
    "gn:population":0,
    "gn:timezone":"Africa/Juba",
    "iso:country":"SS",
    "wof:name":"`Angareb",
    "wof:placetype":"locality"
},
  "geometry": {"coordinates":[24.32657,9.31745],"type":"Point"}
}