{
  "type": "Feature",
  "properties": {
    "gn:admin1_code":"09",
    "gn:asciiname":"Murgan",
    "gn:country_code":"SS",
    "gn:dem":458,
    "gn:feature_class":"P",
    "gn:feature_code":"PPL",
    "gn:name":"Murgan",
    "gn:population":0,
    "gn:timezone":"Africa/Juba",
    "iso:country":"SS",
    "name:und_x_variant":[
        "Murj\u0101n"
    ],
    "wof:name":"Murgan",
    "wof:placetype":"locality"
},
  "geometry": {"coordinates":[28.15612,7.64372],"type":"Point"}
}