{
  "type": "Feature",
  "properties": {
    "gn:admin1_code":"09",
    "gn:asciiname":"Minamba",
    "gn:country_code":"SS",
    "gn:dem":723,
    "gn:feature_class":"P",
    "gn:feature_code":"PPL",
    "gn:name":"Minamba",
    "gn:population":0,
    "gn:timezone":"Africa/Juba",
    "iso:country":"SS",
    "wof:name":"Minamba",
    "wof:placetype":"locality"
},
  "geometry": {"coordinates":[25.18495,8.46505],"type":"Point"}
}