{
  "type": "Feature",
  "properties": {
    "gn:admin1_code":"09",
    "gn:asciiname":"Zaid",
    "gn:country_code":"SS",
    "gn:dem":476,
    "gn:feature_class":"P",
    "gn:feature_code":"PPL",
    "gn:name":"Zaid",
    "gn:population":0,
    "gn:timezone":"Africa/Juba",
    "iso:country":"SS",
    "wof:name":"Zaid",
    "wof:placetype":"locality"
},
  "geometry": {"coordinates":[27.38047000000001,8.11477],"type":"Point"}
}