{
  "type": "Feature",
  "properties": {
    "gn:admin1_code":"01",
    "gn:asciiname":"Nyigo",
    "gn:country_code":"SS",
    "gn:dem":810,
    "gn:feature_class":"P",
    "gn:feature_code":"PPL",
    "gn:name":"Nyigo",
    "gn:population":0,
    "gn:timezone":"Africa/Juba",
    "iso:country":"SS",
    "wof:name":"Nyigo",
    "wof:placetype":"locality"
},
  "geometry": {"coordinates":[30.67556,4.23389],"type":"Point"}
}