{
  "type": "Feature",
  "properties": {
    "gn:admin1_code":"01",
    "gn:asciiname":"Yugalla",
    "gn:country_code":"SS",
    "gn:dem":1039,
    "gn:feature_class":"P",
    "gn:feature_code":"PPL",
    "gn:name":"Yugalla",
    "gn:population":0,
    "gn:timezone":"Africa/Juba",
    "iso:country":"SS",
    "wof:name":"Yugalla",
    "wof:placetype":"locality"
},
  "geometry": {"coordinates":[30.89955,3.78935],"type":"Point"}
}