{
  "type": "Feature",
  "properties": {
    "gn:admin1_code":"07",
    "gn:asciiname":"Thakjuk",
    "gn:country_code":"SS",
    "gn:dem":404,
    "gn:feature_class":"P",
    "gn:feature_code":"PPL",
    "gn:name":"Thakjuk",
    "gn:population":0,
    "gn:timezone":"Africa/Juba",
    "iso:country":"SS",
    "wof:name":"Thakjuk",
    "wof:placetype":"locality"
},
  "geometry": {"coordinates":[33.07236,8.45457],"type":"Point"}
}