{
  "type": "Feature",
  "properties": {
    "gn:admin1_code":"05",
    "gn:asciiname":"Kway",
    "gn:country_code":"SS",
    "gn:dem":405,
    "gn:feature_class":"P",
    "gn:feature_code":"PPL",
    "gn:name":"Kway",
    "gn:population":0,
    "gn:timezone":"Africa/Juba",
    "iso:country":"SS",
    "wof:name":"Kway",
    "wof:placetype":"locality"
},
  "geometry": {"coordinates":[28.1647,9.02682],"type":"Point"}
}