{
  "type": "Feature",
  "properties": {
    "gn:admin1_code":"01",
    "gn:asciiname":"Indura",
    "gn:country_code":"SS",
    "gn:dem":477,
    "gn:feature_class":"P",
    "gn:feature_code":"PPL",
    "gn:name":"Indura",
    "gn:population":0,
    "gn:timezone":"Africa/Juba",
    "iso:country":"SS",
    "wof:name":"Indura",
    "wof:placetype":"locality"
},
  "geometry": {"coordinates":[31.46862,4.91824],"type":"Point"}
}