{
  "type": "Feature",
  "properties": {
    "gn:admin1_code":"10",
    "gn:asciiname":"Wandi",
    "gn:country_code":"SS",
    "gn:dem":526,
    "gn:feature_class":"P",
    "gn:feature_code":"PPL",
    "gn:name":"Wandi",
    "gn:population":0,
    "gn:timezone":"Africa/Juba",
    "iso:country":"SS",
    "name:ceb_x_preferred":[
        "Wandi"
    ],
    "name:swe_x_preferred":[
        "Wandi"
    ],
    "wof:name":"Wandi",
    "wof:placetype":"locality"
},
  "geometry": {"coordinates":[30.64101,5.49195],"type":"Point"}
}