{
  "type": "Feature",
  "properties": {
    "gn:admin1_code":"07",
    "gn:asciiname":"Nun",
    "gn:country_code":"SS",
    "gn:dem":395,
    "gn:feature_class":"P",
    "gn:feature_code":"PPL",
    "gn:name":"N\u016bn",
    "gn:population":0,
    "gn:timezone":"Africa/Juba",
    "iso:country":"SS",
    "name:ara_x_preferred":[
        "\u0631\u0627\u0647\u0628\u0629"
    ],
    "name:ast_x_preferred":[
        "Monxa"
    ],
    "name:bod_x_preferred":[
        "\u0f56\u0f59\u0f74\u0f53\u0f0b\u0f58\u0f0d"
    ],
    "name:bre_x_preferred":[
        "Leanez"
    ],
    "name:cat_x_preferred":[
        "Monja"
    ],
    "name:ces_x_preferred":[
        "\u0158eholnice"
    ],
    "name:cym_x_preferred":[
        "Lleian"
    ],
    "name:dan_x_preferred":[
        "Nonne"
    ],
    "name:deu_x_preferred":[
        "Nonne"
    ],
    "name:epo_x_preferred":[
        "Mona\u0125ino"
    ],
    "name:est_x_preferred":[
        "Nunn"
    ],
    "name:eus_x_preferred":[
        "Moja"
    ],
    "name:fas_x_preferred":[
        "\u0631\u0627\u0647\u0628\u0647"
    ],
    "name:fin_x_preferred":[
        "Nunna"
    ],
    "name:fra_x_preferred":[
        "Religieuse"
    ],
    "name:gle_x_preferred":[
        "Bean rialta"
    ],
    "name:hun_x_preferred":[
        "Ap\u00e1ca"
    ],
    "name:ina_x_preferred":[
        "Monacha"
    ],
    "name:ind_x_preferred":[
        "Biarawati"
    ],
    "name:isl_x_preferred":[
        "Nunna"
    ],
    "name:ita_x_preferred":[
        "Monaca"
    ],
    "name:kat_x_preferred":[
        "\u10db\u10dd\u10dc\u10d0\u10d6\u10dd\u10dc\u10d8"
    ],
    "name:kor_x_preferred":[
        "\uc218\ub3c4\uc790"
    ],
    "name:lat_x_preferred":[
        "Soror"
    ],
    "name:lim_x_preferred":[
        "Zuuster"
    ],
    "name:lin_x_preferred":[
        "Mam\u025b\u0301lo"
    ],
    "name:nld_x_preferred":[
        "Zuster"
    ],
    "name:nno_x_preferred":[
        "Nonne"
    ],
    "name:nor_x_preferred":[
        "Nonne"
    ],
    "name:pdc_x_preferred":[
        "Glooschderfraa"
    ],
    "name:pol_x_preferred":[
        "Zakonnica"
    ],
    "name:por_x_preferred":[
        "Monja"
    ],
    "name:ron_x_preferred":[
        "Maic\u0103"
    ],
    "name:sco_x_preferred":[
        "Nun"
    ],
    "name:slk_x_preferred":[
        "Mn\u00ed\u0161ka"
    ],
    "name:sna_x_preferred":[
        "Mbonga"
    ],
    "name:spa_x_preferred":[
        "Monja"
    ],
    "name:swa_x_preferred":[
        "Sista"
    ],
    "name:swe_x_preferred":[
        "Nunna"
    ],
    "name:tam_x_preferred":[
        "\u0b85\u0bb0\u0bc1\u0b9f\u0bcd\u0b9a\u0b95\u0bcb\u0ba4\u0bb0\u0bbf"
    ],
    "name:tha_x_preferred":[
        "\u0e19\u0e31\u0e01\u0e1e\u0e23\u0e15\u0e2b\u0e0d\u0e34\u0e07"
    ],
    "name:urd_x_preferred":[
        "\u0631\u0627\u06c1\u0628\u06c1"
    ],
    "name:vie_x_preferred":[
        "N\u1eef tu"
    ],
    "wof:name":"Nun",
    "wof:placetype":"locality"
},
  "geometry": {"coordinates":[32.19123,10.41122],"type":"Point"}
}