{
  "type": "Feature",
  "properties": {
    "gn:admin1_code":"01",
    "gn:asciiname":"Lukudu",
    "gn:country_code":"SS",
    "gn:dem":928,
    "gn:feature_class":"P",
    "gn:feature_code":"PPL",
    "gn:name":"Lukudu",
    "gn:population":0,
    "gn:timezone":"Africa/Juba",
    "iso:country":"SS",
    "wof:name":"Lukudu",
    "wof:placetype":"locality"
},
  "geometry": {"coordinates":[30.99305,4.15663],"type":"Point"}
}