{
  "type": "Feature",
  "properties": {
    "gn:admin1_code":"09",
    "gn:asciiname":"Duniaka",
    "gn:country_code":"SS",
    "gn:dem":472,
    "gn:feature_class":"P",
    "gn:feature_code":"PPL",
    "gn:name":"Duniaka",
    "gn:population":0,
    "gn:timezone":"Africa/Juba",
    "iso:country":"SS",
    "wof:name":"Duniaka",
    "wof:placetype":"locality"
},
  "geometry": {"coordinates":[27.89887,7.46319],"type":"Point"}
}