{
  "type": "Feature",
  "properties": {
    "gn:admin1_code":"09",
    "gn:asciiname":"Umm Chalandu",
    "gn:country_code":"SS",
    "gn:dem":507,
    "gn:feature_class":"P",
    "gn:feature_code":"PPL",
    "gn:name":"Umm Chalandu",
    "gn:population":0,
    "gn:timezone":"Africa/Juba",
    "iso:country":"SS",
    "wof:lang_x_official":[
        "eng"
    ],
    "wof:lang_x_spoken":[
        "eng"
    ],
    "wof:name":"Umm Chalandu",
    "wof:placetype":"locality"
},
  "geometry": {"coordinates":[25.87497,8.7222],"type":"Point"}
}