{
  "type": "Feature",
  "properties": {
    "gn:admin1_code":"01",
    "gn:asciiname":"Abegi",
    "gn:country_code":"SS",
    "gn:dem":869,
    "gn:feature_class":"P",
    "gn:feature_code":"PPL",
    "gn:name":"Abegi",
    "gn:population":0,
    "gn:timezone":"Africa/Juba",
    "iso:country":"SS",
    "wof:name":"Abegi",
    "wof:placetype":"locality"
},
  "geometry": {"coordinates":[30.56749000000001,4.01348],"type":"Point"}
}