{
  "type": "Feature",
  "properties": {
    "gn:admin1_code":"05",
    "gn:asciiname":"Ayai Diop",
    "gn:country_code":"SS",
    "gn:dem":426,
    "gn:feature_class":"P",
    "gn:feature_code":"PPL",
    "gn:name":"Ayai Diop",
    "gn:population":0,
    "gn:timezone":"Africa/Juba",
    "iso:country":"SS",
    "wof:name":"Ayai Diop",
    "wof:placetype":"locality"
},
  "geometry": {"coordinates":[27.38922,9.04773],"type":"Point"}
}