{
  "type": "Feature",
  "properties": {
    "gn:admin1_code":"09",
    "gn:asciiname":"Fadai",
    "gn:country_code":"SS",
    "gn:dem":480,
    "gn:feature_class":"P",
    "gn:feature_code":"PPL",
    "gn:name":"Fadai",
    "gn:population":0,
    "gn:timezone":"Africa/Juba",
    "iso:country":"SS",
    "wof:name":"Fadai",
    "wof:placetype":"locality"
},
  "geometry": {"coordinates":[28.07734,7.06557],"type":"Point"}
}