{
  "type": "Feature",
  "properties": {
    "gn:admin1_code":"01",
    "gn:asciiname":"Kendi",
    "gn:country_code":"SS",
    "gn:dem":1157,
    "gn:feature_class":"P",
    "gn:feature_code":"PPL",
    "gn:name":"Kendi",
    "gn:population":0,
    "gn:timezone":"Africa/Juba",
    "iso:country":"SS",
    "wof:name":"Kendi",
    "wof:placetype":"locality"
},
  "geometry": {"coordinates":[30.64249,3.68746],"type":"Point"}
}