{
  "type": "Feature",
  "properties": {
    "gn:admin1_code":"03",
    "gn:asciiname":"Pochala",
    "gn:country_code":"SS",
    "gn:dem":442,
    "gn:feature_class":"P",
    "gn:feature_code":"PPL",
    "gn:name":"Pochala",
    "gn:population":0,
    "gn:timezone":"Africa/Juba",
    "iso:country":"SS",
    "name:und_x_variant":[
        "Bashala",
        "Pachalla",
        "Pachala",
        "Pochala"
    ],
    "wof:lang_x_official":[
        "eng"
    ],
    "wof:lang_x_spoken":[
        "eng"
    ],
    "wof:name":"Pochala",
    "wof:placetype":"locality"
},
  "geometry": {"coordinates":[34.09963,7.18795],"type":"Point"}
}