{
  "type": "Feature",
  "properties": {
    "gn:admin1_code":"01",
    "gn:asciiname":"Shamba",
    "gn:country_code":"SS",
    "gn:dem":903,
    "gn:feature_class":"P",
    "gn:feature_code":"PPL",
    "gn:name":"Shamba",
    "gn:population":0,
    "gn:timezone":"Africa/Juba",
    "iso:country":"SS",
    "name:ceb_x_preferred":[
        "Shamba"
    ],
    "name:swe_x_preferred":[
        "Shamba"
    ],
    "wof:name":"Shamba",
    "wof:placetype":"locality"
},
  "geometry": {"coordinates":[31.13862,4.37955],"type":"Point"}
}