{
  "type": "Feature",
  "properties": {
    "gn:admin1_code":"04",
    "gn:asciiname":"Agany",
    "gn:country_code":"SS",
    "gn:dem":415,
    "gn:feature_class":"P",
    "gn:feature_code":"PPL",
    "gn:name":"Agany",
    "gn:population":0,
    "gn:timezone":"Africa/Juba",
    "iso:country":"SS",
    "wof:name":"Agany",
    "wof:placetype":"locality"
},
  "geometry": {"coordinates":[30.95294,6.85414],"type":"Point"}
}