{
  "type": "Feature",
  "properties": {
    "gn:admin1_code":"08",
    "gn:asciiname":"Fan Ajuk",
    "gn:country_code":"SS",
    "gn:dem":411,
    "gn:feature_class":"P",
    "gn:feature_code":"PPL",
    "gn:name":"Fan Ajuk",
    "gn:population":0,
    "gn:timezone":"Africa/Juba",
    "iso:country":"SS",
    "wof:lang_x_official":[
        "eng"
    ],
    "wof:lang_x_spoken":[
        "eng"
    ],
    "wof:name":"Fan Ajuk",
    "wof:placetype":"locality"
},
  "geometry": {"coordinates":[28.2256,8.83971],"type":"Point"}
}