{
  "type": "Feature",
  "properties": {
    "gn:admin1_code":"03",
    "gn:asciiname":"Tiltil",
    "gn:country_code":"SS",
    "gn:dem":401,
    "gn:feature_class":"P",
    "gn:feature_code":"PPL",
    "gn:name":"Tiltil",
    "gn:population":0,
    "gn:timezone":"Africa/Juba",
    "iso:country":"SS",
    "name:ceb_x_preferred":[
        "Tiltil"
    ],
    "name:eus_x_preferred":[
        "Tiltil"
    ],
    "name:fas_x_preferred":[
        "\u062a\u06cc\u0644\u062a\u06cc\u0644"
    ],
    "name:fra_x_preferred":[
        "Tiltil"
    ],
    "name:ita_x_preferred":[
        "Tiltil"
    ],
    "name:mwl_x_preferred":[
        "Tiltil"
    ],
    "name:nld_x_preferred":[
        "Tiltil"
    ],
    "name:por_x_preferred":[
        "Tiltil"
    ],
    "name:ron_x_preferred":[
        "Tiltil"
    ],
    "name:rus_x_preferred":[
        "\u0422\u0438\u043b\u044c\u0442\u0438\u043b\u044c"
    ],
    "name:spa_x_preferred":[
        "Til Til"
    ],
    "name:swe_x_preferred":[
        "Tiltil"
    ],
    "name:zho_x_preferred":[
        "\u8482\u723e\u8482\u723e"
    ],
    "wof:name":"Tiltil",
    "wof:placetype":"locality"
},
  "geometry": {"coordinates":[30.63286,9.2795],"type":"Point"}
}