{
  "type": "Feature",
  "properties": {
    "gn:admin1_code":"02",
    "gn:asciiname":"Patibe",
    "gn:country_code":"SS",
    "gn:dem":749,
    "gn:feature_class":"P",
    "gn:feature_code":"PPL",
    "gn:name":"Patibe",
    "gn:population":0,
    "gn:timezone":"Africa/Juba",
    "iso:country":"SS",
    "wof:name":"Patibe",
    "wof:placetype":"locality"
},
  "geometry": {"coordinates":[31.99878,3.88338],"type":"Point"}
}