{
  "type": "Feature",
  "properties": {
    "gn:admin1_code":"03",
    "gn:asciiname":"Buingfiort",
    "gn:country_code":"SS",
    "gn:dem":401,
    "gn:feature_class":"P",
    "gn:feature_code":"PPL",
    "gn:name":"Buingfiort",
    "gn:population":0,
    "gn:timezone":"Africa/Juba",
    "iso:country":"SS",
    "name:und_x_variant":[
        "Bungfiort",
        "Buingfiort"
    ],
    "wof:name":"Buingfiort",
    "wof:placetype":"locality"
},
  "geometry": {"coordinates":[31.70227,9.16292],"type":"Point"}
}