{
  "type": "Feature",
  "properties": {
    "gn:admin1_code":"10",
    "gn:asciiname":"Or",
    "gn:country_code":"SS",
    "gn:dem":477,
    "gn:feature_class":"P",
    "gn:feature_code":"PPL",
    "gn:name":"Or",
    "gn:population":0,
    "gn:timezone":"Africa/Juba",
    "iso:country":"SS",
    "name:ara_x_preferred":[
        "\u0623\u0648"
    ],
    "name:cat_x_preferred":[
        "Or"
    ],
    "name:fra_x_preferred":[
        "Or"
    ],
    "name:swe_x_preferred":[
        "Or"
    ],
    "name:ukr_x_preferred":[
        "\u0410\u0431\u043e"
    ],
    "wof:name":"Or",
    "wof:placetype":"locality"
},
  "geometry": {"coordinates":[30.14614000000001,6.22485],"type":"Point"}
}