{
  "type": "Feature",
  "properties": {
    "gn:admin1_code":"10",
    "gn:asciiname":"Or",
    "gn:country_code":"SS",
    "gn:dem":477,
    "gn:feature_class":"P",
    "gn:feature_code":"PPL",
    "gn:name":"Or",
    "gn:population":0,
    "gn:timezone":"Africa/Juba",
    "iso:country":"SS",
    "wof:name":"Or",
    "wof:placetype":"locality"
},
  "geometry": {"coordinates":[30.14614000000001,6.22485],"type":"Point"}
}