{
  "type": "Feature",
  "properties": {
    "gn:admin1_code":"05",
    "gn:asciiname":"Aran",
    "gn:country_code":"SS",
    "gn:dem":442,
    "gn:feature_class":"P",
    "gn:feature_code":"PPL",
    "gn:name":"Aran",
    "gn:population":0,
    "gn:timezone":"Africa/Juba",
    "iso:country":"SS",
    "wof:name":"Aran",
    "wof:placetype":"locality"
},
  "geometry": {"coordinates":[26.93967,9.1347],"type":"Point"}
}