{
  "type": "Feature",
  "properties": {
    "gn:admin1_code":"05",
    "gn:asciiname":"Aran",
    "gn:country_code":"SS",
    "gn:dem":442,
    "gn:feature_class":"P",
    "gn:feature_code":"PPL",
    "gn:name":"Aran",
    "gn:population":0,
    "gn:timezone":"Africa/Juba",
    "iso:country":"SS",
    "name:aze_x_preferred":[
        "Aran"
    ],
    "name:bel_x_preferred":[
        "\u0410\u0440\u0430\u043d"
    ],
    "name:bre_x_preferred":[
        "Aran"
    ],
    "name:cat_x_preferred":[
        "Aran"
    ],
    "name:ceb_x_preferred":[
        "Aran"
    ],
    "name:ces_x_preferred":[
        "Aran"
    ],
    "name:cym_x_preferred":[
        "Aran"
    ],
    "name:deu_x_preferred":[
        "Aran"
    ],
    "name:eus_x_preferred":[
        "Aran"
    ],
    "name:fas_x_preferred":[
        "\u0627\u0631\u0627\u0646"
    ],
    "name:fra_x_preferred":[
        "Aran"
    ],
    "name:hye_x_preferred":[
        "\u0531\u0580\u0561\u0576"
    ],
    "name:ita_x_preferred":[
        "Aran"
    ],
    "name:kat_x_preferred":[
        "\u10d0\u10e0\u10d0\u10dc\u10d8"
    ],
    "name:lit_x_preferred":[
        "Aranas"
    ],
    "name:rus_x_preferred":[
        "\u0410\u0440\u0430\u043d"
    ],
    "name:srp_x_preferred":[
        "\u0410\u0440\u0430\u043d"
    ],
    "name:swe_x_preferred":[
        "Aran"
    ],
    "wof:lang_x_official":[
        "eng"
    ],
    "wof:lang_x_spoken":[
        "eng"
    ],
    "wof:name":"Aran",
    "wof:placetype":"locality"
},
  "geometry": {"coordinates":[26.93967,9.1347],"type":"Point"}
}