{
  "type": "Feature",
  "properties": {
    "gn:admin1_code":"01",
    "gn:asciiname":"Loago",
    "gn:country_code":"SS",
    "gn:dem":655,
    "gn:feature_class":"P",
    "gn:feature_code":"PPL",
    "gn:name":"Loago",
    "gn:population":0,
    "gn:timezone":"Africa/Juba",
    "iso:country":"SS",
    "wof:name":"Loago",
    "wof:placetype":"locality"
},
  "geometry": {"coordinates":[31.28459,4.5102],"type":"Point"}
}