{
  "type": "Feature",
  "properties": {
    "gn:admin1_code":"01",
    "gn:asciiname":"Shiromba",
    "gn:country_code":"SS",
    "gn:dem":866,
    "gn:feature_class":"P",
    "gn:feature_code":"PPL",
    "gn:name":"Shiromba",
    "gn:population":0,
    "gn:timezone":"Africa/Juba",
    "iso:country":"SS",
    "wof:name":"Shiromba",
    "wof:placetype":"locality"
},
  "geometry": {"coordinates":[30.98184,4.58395],"type":"Point"}
}