{
  "type": "Feature",
  "properties": {
    "gn:admin1_code":"04",
    "gn:asciiname":"Dirjay",
    "gn:country_code":"SS",
    "gn:dem":456,
    "gn:feature_class":"P",
    "gn:feature_code":"PPL",
    "gn:name":"Dirjay",
    "gn:population":0,
    "gn:timezone":"Africa/Juba",
    "iso:country":"SS",
    "wof:name":"Dirjay",
    "wof:placetype":"locality"
},
  "geometry": {"coordinates":[30.61528,6.50194],"type":"Point"}
}