{
  "type": "Feature",
  "properties": {
    "gn:admin1_code":"08",
    "gn:asciiname":"Dilkwoi",
    "gn:country_code":"SS",
    "gn:dem":427,
    "gn:feature_class":"P",
    "gn:feature_code":"PPL",
    "gn:name":"Dilkwoi",
    "gn:population":0,
    "gn:timezone":"Africa/Juba",
    "iso:country":"SS",
    "wof:name":"Dilkwoi",
    "wof:placetype":"locality"
},
  "geometry": {"coordinates":[28.83052,7.4827],"type":"Point"}
}