{
  "type": "Feature",
  "properties": {
    "gn:admin1_code":"10",
    "gn:asciiname":"Niaba",
    "gn:country_code":"SS",
    "gn:dem":659,
    "gn:feature_class":"P",
    "gn:feature_code":"PPL",
    "gn:name":"Niaba",
    "gn:population":0,
    "gn:timezone":"Africa/Juba",
    "iso:country":"SS",
    "wof:name":"Niaba",
    "wof:placetype":"locality"
},
  "geometry": {"coordinates":[30.30342000000001,5.05977],"type":"Point"}
}