{
  "type": "Feature",
  "properties": {
    "gn:admin1_code":"03",
    "gn:asciiname":"Nyod",
    "gn:country_code":"SS",
    "gn:dem":403,
    "gn:feature_class":"P",
    "gn:feature_code":"PPL",
    "gn:name":"Nyod",
    "gn:population":0,
    "gn:timezone":"Africa/Juba",
    "iso:country":"SS",
    "wof:name":"Nyod",
    "wof:placetype":"locality"
},
  "geometry": {"coordinates":[30.69435,8.62732],"type":"Point"}
}