{
  "type": "Feature",
  "properties": {
    "gn:admin1_code":"09",
    "gn:asciiname":"Tabangiya",
    "gn:country_code":"SS",
    "gn:dem":570,
    "gn:feature_class":"P",
    "gn:feature_code":"PPL",
    "gn:name":"Tabangiya",
    "gn:population":0,
    "gn:timezone":"Africa/Juba",
    "iso:country":"SS",
    "wof:name":"Tabangiya",
    "wof:placetype":"locality"
},
  "geometry": {"coordinates":[26.16202,7.75898],"type":"Point"}
}