{
  "type": "Feature",
  "properties": {
    "gn:admin1_code":"06",
    "gn:asciiname":"Nerboar",
    "gn:country_code":"SS",
    "gn:dem":395,
    "gn:feature_class":"P",
    "gn:feature_code":"PPL",
    "gn:name":"Nerboar",
    "gn:population":0,
    "gn:timezone":"Africa/Juba",
    "iso:country":"SS",
    "wof:name":"Nerboar",
    "wof:placetype":"locality"
},
  "geometry": {"coordinates":[29.86397,8.3219],"type":"Point"}
}