{
  "type": "Feature",
  "properties": {
    "gn:admin1_code":"07",
    "gn:asciiname":"Lelo",
    "gn:country_code":"SS",
    "gn:dem":395,
    "gn:feature_class":"P",
    "gn:feature_code":"PPL",
    "gn:name":"Lelo",
    "gn:population":0,
    "gn:timezone":"Africa/Juba",
    "iso:country":"SS",
    "wof:name":"Lelo",
    "wof:placetype":"locality"
},
  "geometry": {"coordinates":[31.61718,9.5474],"type":"Point"}
}