{
  "type": "Feature",
  "properties": {
    "gn:admin1_code":"07",
    "gn:asciiname":"Dirdimma",
    "gn:country_code":"SS",
    "gn:dem":456,
    "gn:feature_class":"P",
    "gn:feature_code":"PPL",
    "gn:name":"Dirdimma",
    "gn:population":0,
    "gn:timezone":"Africa/Juba",
    "iso:country":"SS",
    "wof:name":"Dirdimma",
    "wof:placetype":"locality"
},
  "geometry": {"coordinates":[33.59494,10.2758],"type":"Point"}
}