{
  "type": "Feature",
  "properties": {
    "gn:admin1_code":"02",
    "gn:asciiname":"Mutaram",
    "gn:country_code":"SS",
    "gn:dem":552,
    "gn:feature_class":"P",
    "gn:feature_code":"PPL",
    "gn:name":"Mutaram",
    "gn:population":0,
    "gn:timezone":"Africa/Juba",
    "iso:country":"SS",
    "wof:lang_x_official":[
        "eng"
    ],
    "wof:lang_x_spoken":[
        "eng"
    ],
    "wof:name":"Mutaram",
    "wof:placetype":"locality"
},
  "geometry": {"coordinates":[32.46098,4.57703],"type":"Point"}
}