{
  "type": "Feature",
  "properties": {
    "gn:admin1_code":"05",
    "gn:asciiname":"Rual",
    "gn:country_code":"SS",
    "gn:dem":413,
    "gn:feature_class":"P",
    "gn:feature_code":"PPL",
    "gn:name":"Rual",
    "gn:population":0,
    "gn:timezone":"Africa/Juba",
    "iso:country":"SS",
    "wof:name":"Rual",
    "wof:placetype":"locality"
},
  "geometry": {"coordinates":[27.8884,9.01792],"type":"Point"}
}