{
  "type": "Feature",
  "properties": {
    "gn:admin1_code":"07",
    "gn:asciiname":"Kusdonga",
    "gn:country_code":"SS",
    "gn:dem":438,
    "gn:feature_class":"P",
    "gn:feature_code":"PPL",
    "gn:name":"Kusdonga",
    "gn:population":0,
    "gn:timezone":"Africa/Juba",
    "iso:country":"SS",
    "wof:name":"Kusdonga",
    "wof:placetype":"locality"
},
  "geometry": {"coordinates":[33.73990999999999,9.28258],"type":"Point"}
}