{
  "type": "Feature",
  "properties": {
    "gn:admin1_code":"02",
    "gn:asciiname":"Luarogh",
    "gn:country_code":"SS",
    "gn:dem":544,
    "gn:feature_class":"P",
    "gn:feature_code":"PPL",
    "gn:name":"Luarogh",
    "gn:population":0,
    "gn:timezone":"Africa/Juba",
    "iso:country":"SS",
    "wof:name":"Luarogh",
    "wof:placetype":"locality"
},
  "geometry": {"coordinates":[33.73752,5.06804],"type":"Point"}
}