{
  "type": "Feature",
  "properties": {
    "gn:admin1_code":"02",
    "gn:asciiname":"Teiranging",
    "gn:country_code":"SS",
    "gn:dem":987,
    "gn:feature_class":"P",
    "gn:feature_code":"PPL",
    "gn:name":"Teiranging",
    "gn:population":0,
    "gn:timezone":"Africa/Juba",
    "iso:country":"SS",
    "wof:name":"Teiranging",
    "wof:placetype":"locality"
},
  "geometry": {"coordinates":[32.72212,4.27794],"type":"Point"}
}