{
  "type": "Feature",
  "properties": {
    "gn:admin1_code":"09",
    "gn:asciiname":"Kanaga",
    "gn:country_code":"SS",
    "gn:dem":530,
    "gn:feature_class":"P",
    "gn:feature_code":"PPL",
    "gn:name":"Kanaga",
    "gn:population":0,
    "gn:timezone":"Africa/Juba",
    "iso:country":"SS",
    "name:ceb_x_preferred":[
        "Kanaga"
    ],
    "name:fra_x_preferred":[
        "Kanaga"
    ],
    "name:swe_x_preferred":[
        "Kanaga"
    ],
    "wof:name":"Kanaga",
    "wof:placetype":"locality"
},
  "geometry": {"coordinates":[27.86517000000001,7.24455],"type":"Point"}
}