{
  "type": "Feature",
  "properties": {
    "gn:admin1_code":"03",
    "gn:asciiname":"Nabaka",
    "gn:country_code":"SS",
    "gn:dem":423,
    "gn:feature_class":"P",
    "gn:feature_code":"PPL",
    "gn:name":"Nabaka",
    "gn:population":0,
    "gn:timezone":"Africa/Juba",
    "iso:country":"SS",
    "wof:name":"Nabaka",
    "wof:placetype":"locality"
},
  "geometry": {"coordinates":[33.16385,6.76487],"type":"Point"}
}