{
  "type": "Feature",
  "properties": {
    "gn:admin1_code":"04",
    "gn:asciiname":"Lualadol",
    "gn:country_code":"SS",
    "gn:dem":423,
    "gn:feature_class":"P",
    "gn:feature_code":"PPL",
    "gn:name":"Lualadol",
    "gn:population":0,
    "gn:timezone":"Africa/Juba",
    "iso:country":"SS",
    "wof:name":"Lualadol",
    "wof:placetype":"locality"
},
  "geometry": {"coordinates":[29.84762000000001,6.93615],"type":"Point"}
}