{
  "type": "Feature",
  "properties": {
    "gn:admin1_code":"04",
    "gn:asciiname":"Kulnyiragok",
    "gn:country_code":"SS",
    "gn:dem":428,
    "gn:feature_class":"P",
    "gn:feature_code":"PPL",
    "gn:name":"Kulnyiragok",
    "gn:population":0,
    "gn:timezone":"Africa/Juba",
    "iso:country":"SS",
    "wof:name":"Kulnyiragok",
    "wof:placetype":"locality"
},
  "geometry": {"coordinates":[30.36337,6.79207],"type":"Point"}
}