{
  "type": "Feature",
  "properties": {
    "gn:admin1_code":"07",
    "gn:asciiname":"Bwell",
    "gn:country_code":"SS",
    "gn:dem":397,
    "gn:feature_class":"P",
    "gn:feature_code":"PPL",
    "gn:name":"Bwell",
    "gn:population":0,
    "gn:timezone":"Africa/Juba",
    "iso:country":"SS",
    "wof:name":"Bwell",
    "wof:placetype":"locality"
},
  "geometry": {"coordinates":[32.18333,9.19204],"type":"Point"}
}