{
  "type": "Feature",
  "properties": {
    "gn:admin1_code":"07",
    "gn:asciiname":"Majak",
    "gn:country_code":"SS",
    "gn:dem":414,
    "gn:feature_class":"P",
    "gn:feature_code":"PPL",
    "gn:name":"Majak",
    "gn:population":0,
    "gn:timezone":"Africa/Juba",
    "iso:country":"SS",
    "name:aze_x_preferred":[
        "Mayak"
    ],
    "name:bul_x_preferred":[
        "\u041c\u0430\u044f\u043a"
    ],
    "name:ceb_x_preferred":[
        "Majak"
    ],
    "name:deu_x_preferred":[
        "Majak"
    ],
    "name:pol_x_preferred":[
        "Majak"
    ],
    "name:rus_x_preferred":[
        "\u041c\u0430\u044f\u043a"
    ],
    "name:srp_x_preferred":[
        "\u041c\u0430\u0458\u0430\u043a"
    ],
    "name:swe_x_preferred":[
        "Majak"
    ],
    "name:ukr_x_preferred":[
        "\u041c\u0430\u044f\u043a"
    ],
    "wof:lang_x_official":[
        "eng"
    ],
    "wof:lang_x_spoken":[
        "eng"
    ],
    "wof:name":"Majak",
    "wof:placetype":"locality"
},
  "geometry": {"coordinates":[33.7981,8.43113],"type":"Point"}
}