{
  "type": "Feature",
  "properties": {
    "gn:admin1_code":"04",
    "gn:asciiname":"Dolinom",
    "gn:country_code":"SS",
    "gn:dem":428,
    "gn:feature_class":"P",
    "gn:feature_code":"PPL",
    "gn:name":"Dolinom",
    "gn:population":0,
    "gn:timezone":"Africa/Juba",
    "iso:country":"SS",
    "wof:name":"Dolinom",
    "wof:placetype":"locality"
},
  "geometry": {"coordinates":[31.33562,6.09302],"type":"Point"}
}