{
  "type": "Feature",
  "properties": {
    "gn:admin1_code":"07",
    "gn:asciiname":"Pachucha",
    "gn:country_code":"SS",
    "gn:dem":403,
    "gn:feature_class":"P",
    "gn:feature_code":"PPL",
    "gn:name":"Pachucha",
    "gn:population":0,
    "gn:timezone":"Africa/Juba",
    "iso:country":"SS",
    "wof:name":"Pachucha",
    "wof:placetype":"locality"
},
  "geometry": {"coordinates":[32.9502,11.3756],"type":"Point"}
}