{
  "type": "Feature",
  "properties": {
    "gn:admin1_code":"04",
    "gn:asciiname":"Makwet",
    "gn:country_code":"SS",
    "gn:dem":439,
    "gn:feature_class":"P",
    "gn:feature_code":"PPL",
    "gn:name":"Makwet",
    "gn:population":0,
    "gn:timezone":"Africa/Juba",
    "iso:country":"SS",
    "name:und_x_variant":[
        "Akot"
    ],
    "wof:name":"Makwet",
    "wof:placetype":"locality"
},
  "geometry": {"coordinates":[30.93074,6.16134],"type":"Point"}
}