{
  "type": "Feature",
  "properties": {
    "gn:admin1_code":"02",
    "gn:asciiname":"Kidepo",
    "gn:country_code":"SS",
    "gn:dem":801,
    "gn:feature_class":"P",
    "gn:feature_code":"PPL",
    "gn:name":"Kidepo",
    "gn:population":0,
    "gn:timezone":"Africa/Juba",
    "iso:country":"SS",
    "wof:name":"Kidepo",
    "wof:placetype":"locality"
},
  "geometry": {"coordinates":[33.25838,4.09591],"type":"Point"}
}