{
  "type": "Feature",
  "properties": {
    "gn:admin1_code":"01",
    "gn:asciiname":"Nunyarri",
    "gn:country_code":"SS",
    "gn:dem":1001,
    "gn:feature_class":"P",
    "gn:feature_code":"PPL",
    "gn:name":"Nunyarri",
    "gn:population":0,
    "gn:timezone":"Africa/Juba",
    "iso:country":"SS",
    "wof:name":"Nunyarri",
    "wof:placetype":"locality"
},
  "geometry": {"coordinates":[30.92757000000001,3.83119],"type":"Point"}
}