{
  "type": "Feature",
  "properties": {
    "gn:admin1_code":"01",
    "gn:asciiname":"Baka",
    "gn:country_code":"SS",
    "gn:dem":832,
    "gn:feature_class":"P",
    "gn:feature_code":"PPL",
    "gn:name":"Baka",
    "gn:population":0,
    "gn:timezone":"Africa/Juba",
    "iso:country":"SS",
    "wof:name":"Baka",
    "wof:placetype":"locality"
},
  "geometry": {"coordinates":[30.09204,4.55232],"type":"Point"}
}