{
  "type": "Feature",
  "properties": {
    "gn:admin1_code":"01",
    "gn:asciiname":"Mongalla",
    "gn:country_code":"SS",
    "gn:dem":450,
    "gn:feature_class":"P",
    "gn:feature_code":"PPL",
    "gn:name":"Mongalla",
    "gn:population":0,
    "gn:timezone":"Africa/Juba",
    "iso:country":"SS",
    "name:deu_x_preferred":[
        "Mangalla"
    ],
    "name:nld_x_preferred":[
        "Mangalla"
    ],
    "name:rus_x_preferred":[
        "\u041c\u043e\u043d\u0433\u0430\u043b\u043b\u0430"
    ],
    "name:und_x_variant":[
        "Manqalah",
        "Monqala",
        "Mongala",
        "Mongalla"
    ],
    "name:zho_x_preferred":[
        "\u8499\u52a0\u62c9"
    ],
    "wof:lang_x_official":[
        "eng"
    ],
    "wof:lang_x_spoken":[
        "eng"
    ],
    "wof:name":"Mongalla",
    "wof:placetype":"locality"
},
  "geometry": {"coordinates":[31.76877,5.19945],"type":"Point"}
}