{
  "type": "Feature",
  "properties": {
    "gn:admin1_code":"01",
    "gn:asciiname":"Mongalla",
    "gn:country_code":"SS",
    "gn:dem":450,
    "gn:feature_class":"P",
    "gn:feature_code":"PPL",
    "gn:name":"Mongalla",
    "gn:population":0,
    "gn:timezone":"Africa/Juba",
    "iso:country":"SS",
    "name:und_x_variant":[
        "Manqalah",
        "Monqala",
        "Mongala",
        "Mongalla"
    ],
    "wof:name":"Mongalla",
    "wof:placetype":"locality"
},
  "geometry": {"coordinates":[31.76877,5.19945],"type":"Point"}
}