{
  "type": "Feature",
  "properties": {
    "gn:admin1_code":"03",
    "gn:asciiname":"Kwal Tiu",
    "gn:country_code":"SS",
    "gn:dem":434,
    "gn:feature_class":"P",
    "gn:feature_code":"PPL",
    "gn:name":"Kwal Tiu",
    "gn:population":0,
    "gn:timezone":"Africa/Juba",
    "iso:country":"SS",
    "wof:name":"Kwal Tiu",
    "wof:placetype":"locality"
},
  "geometry": {"coordinates":[31.81199,6.17785],"type":"Point"}
}