{
  "type": "Feature",
  "properties": {
    "gn:admin1_code":"07",
    "gn:asciiname":"Fekang",
    "gn:country_code":"SS",
    "gn:dem":398,
    "gn:feature_class":"P",
    "gn:feature_code":"PPL",
    "gn:name":"Fekang",
    "gn:population":0,
    "gn:timezone":"Africa/Juba",
    "iso:country":"SS",
    "name:und_x_variant":[
        "Fakang",
        "Fekang"
    ],
    "wof:name":"Fekang",
    "wof:placetype":"locality"
},
  "geometry": {"coordinates":[31.46497,9.3658],"type":"Point"}
}