{
  "type": "Feature",
  "properties": {
    "gn:admin1_code":"06",
    "gn:asciiname":"Nareor",
    "gn:country_code":"SS",
    "gn:dem":394,
    "gn:feature_class":"P",
    "gn:feature_code":"PPL",
    "gn:name":"Nareor",
    "gn:population":0,
    "gn:timezone":"Africa/Juba",
    "iso:country":"SS",
    "wof:name":"Nareor",
    "wof:placetype":"locality"
},
  "geometry": {"coordinates":[29.22837,9.1105],"type":"Point"}
}