{
  "type": "Feature",
  "properties": {
    "gn:admin1_code":"01",
    "gn:asciiname":"Kemiru",
    "gn:country_code":"SS",
    "gn:dem":823,
    "gn:feature_class":"P",
    "gn:feature_code":"PPL",
    "gn:name":"Kemiru",
    "gn:population":0,
    "gn:timezone":"Africa/Juba",
    "iso:country":"SS",
    "wof:name":"Kemiru",
    "wof:placetype":"locality"
},
  "geometry": {"coordinates":[30.49861,4.17194],"type":"Point"}
}