{
  "type": "Feature",
  "properties": {
    "gn:admin1_code":"02",
    "gn:asciiname":"Nagongitela",
    "gn:country_code":"SS",
    "gn:dem":552,
    "gn:feature_class":"P",
    "gn:feature_code":"PPL",
    "gn:name":"Nagongitela",
    "gn:population":0,
    "gn:timezone":"Africa/Juba",
    "iso:country":"SS",
    "wof:name":"Nagongitela",
    "wof:placetype":"locality"
},
  "geometry": {"coordinates":[33.73471,5.05268],"type":"Point"}
}