{
  "type": "Feature",
  "properties": {
    "gn:admin1_code":"05",
    "gn:asciiname":"Fet",
    "gn:country_code":"SS",
    "gn:dem":409,
    "gn:feature_class":"P",
    "gn:feature_code":"PPL",
    "gn:name":"Fet",
    "gn:population":0,
    "gn:timezone":"Africa/Juba",
    "iso:country":"SS",
    "wof:name":"Fet",
    "wof:placetype":"locality"
},
  "geometry": {"coordinates":[28.03515,9.20783],"type":"Point"}
}