{
  "type": "Feature",
  "properties": {
    "gn:admin1_code":"05",
    "gn:asciiname":"Fet",
    "gn:country_code":"SS",
    "gn:dem":409,
    "gn:feature_class":"P",
    "gn:feature_code":"PPL",
    "gn:name":"Fet",
    "gn:population":0,
    "gn:timezone":"Africa/Juba",
    "iso:country":"SS",
    "name:ara_x_preferred":[
        "\u0641\u064a\u062a"
    ],
    "name:bpy_x_preferred":[
        "\u09ab\u09c7\u099f"
    ],
    "name:cat_x_preferred":[
        "Fet"
    ],
    "name:ceb_x_preferred":[
        "Fet"
    ],
    "name:che_x_preferred":[
        "\u0424\u0435\u0442"
    ],
    "name:dan_x_preferred":[
        "Fet"
    ],
    "name:deu_x_preferred":[
        "Fet"
    ],
    "name:epo_x_preferred":[
        "Fet"
    ],
    "name:eus_x_preferred":[
        "Fet"
    ],
    "name:fin_x_preferred":[
        "Fet"
    ],
    "name:fra_x_preferred":[
        "Fet"
    ],
    "name:glg_x_preferred":[
        "Fet"
    ],
    "name:hun_x_preferred":[
        "Fet k\u00f6zs\u00e9g"
    ],
    "name:hye_x_preferred":[
        "\u0556\u0565\u0569\u056b \u0570\u0561\u0574\u0561\u0575\u0576\u0584"
    ],
    "name:ita_x_preferred":[
        "Fet"
    ],
    "name:jav_x_preferred":[
        "Fet"
    ],
    "name:lat_x_preferred":[
        "Fet"
    ],
    "name:lim_x_preferred":[
        "Fet"
    ],
    "name:msa_x_preferred":[
        "Fet"
    ],
    "name:nds_x_preferred":[
        "Kommun Fet"
    ],
    "name:nld_x_preferred":[
        "Fet"
    ],
    "name:nno_x_preferred":[
        "Fet kommune"
    ],
    "name:nor_x_preferred":[
        "Fet"
    ],
    "name:pol_x_preferred":[
        "Fet"
    ],
    "name:por_x_preferred":[
        "Fet"
    ],
    "name:ron_x_preferred":[
        "Fet"
    ],
    "name:rus_x_preferred":[
        "\u0424\u0435\u0442"
    ],
    "name:slv_x_preferred":[
        "Fet"
    ],
    "name:sme_x_preferred":[
        "Fet"
    ],
    "name:swe_x_preferred":[
        "Fets kommun"
    ],
    "name:vie_x_preferred":[
        "Fet"
    ],
    "name:war_x_preferred":[
        "Fet"
    ],
    "name:zho_x_preferred":[
        "\u8cbb\u7279"
    ],
    "wof:name":"Fet",
    "wof:placetype":"locality"
},
  "geometry": {"coordinates":[28.03515,9.20783],"type":"Point"}
}