{
  "type": "Feature",
  "properties": {
    "gn:admin1_code":"06",
    "gn:asciiname":"Fatung",
    "gn:country_code":"SS",
    "gn:dem":392,
    "gn:feature_class":"P",
    "gn:feature_code":"PPL",
    "gn:name":"Fatung",
    "gn:population":0,
    "gn:timezone":"Africa/Juba",
    "iso:country":"SS",
    "wof:name":"Fatung",
    "wof:placetype":"locality"
},
  "geometry": {"coordinates":[29.22193,9.05988],"type":"Point"}
}