{
  "type": "Feature",
  "properties": {
    "gn:admin1_code":"09",
    "gn:asciiname":"El Eidham",
    "gn:country_code":"SS",
    "gn:dem":454,
    "gn:feature_class":"P",
    "gn:feature_code":"PPL",
    "gn:name":"El Eidham",
    "gn:population":0,
    "gn:timezone":"Africa/Juba",
    "iso:country":"SS",
    "wof:name":"El Eidham",
    "wof:placetype":"locality"
},
  "geometry": {"coordinates":[25.55695,10.34728],"type":"Point"}
}