{
  "type": "Feature",
  "properties": {
    "gn:admin1_code":"01",
    "gn:asciiname":"Jala",
    "gn:country_code":"SS",
    "gn:dem":855,
    "gn:feature_class":"P",
    "gn:feature_code":"PPL",
    "gn:name":"Jala",
    "gn:population":0,
    "gn:timezone":"Africa/Juba",
    "iso:country":"SS",
    "name:ceb_x_preferred":[
        "Jala"
    ],
    "name:fra_x_preferred":[
        "Jala"
    ],
    "name:hrv_x_preferred":[
        "Jala"
    ],
    "name:srp_x_preferred":[
        "Jala"
    ],
    "name:swe_x_preferred":[
        "Jala"
    ],
    "wof:name":"Jala",
    "wof:placetype":"locality"
},
  "geometry": {"coordinates":[31.17093,4.40624],"type":"Point"}
}