{
  "type": "Feature",
  "properties": {
    "gn:admin1_code":"01",
    "gn:asciiname":"Kabengere",
    "gn:country_code":"SS",
    "gn:dem":900,
    "gn:feature_class":"P",
    "gn:feature_code":"PPL",
    "gn:name":"Kabengere",
    "gn:population":0,
    "gn:timezone":"Africa/Juba",
    "iso:country":"SS",
    "wof:name":"Kabengere",
    "wof:placetype":"locality"
},
  "geometry": {"coordinates":[30.6366,3.87238],"type":"Point"}
}