{
  "type": "Feature",
  "properties": {
    "gn:admin1_code":"08",
    "gn:asciiname":"Agurawel",
    "gn:country_code":"SS",
    "gn:dem":416,
    "gn:feature_class":"P",
    "gn:feature_code":"PPL",
    "gn:name":"Agurawel",
    "gn:population":0,
    "gn:timezone":"Africa/Juba",
    "iso:country":"SS",
    "wof:name":"Agurawel",
    "wof:placetype":"locality"
},
  "geometry": {"coordinates":[28.24049,8.3618],"type":"Point"}
}