{
  "type": "Feature",
  "properties": {
    "gn:admin1_code":"05",
    "gn:asciiname":"Unading",
    "gn:country_code":"SS",
    "gn:dem":422,
    "gn:feature_class":"P",
    "gn:feature_code":"PPL",
    "gn:name":"Unading",
    "gn:population":0,
    "gn:timezone":"Africa/Juba",
    "iso:country":"SS",
    "wof:name":"Unading",
    "wof:placetype":"locality"
},
  "geometry": {"coordinates":[27.43396,8.8725],"type":"Point"}
}