{
  "type": "Feature",
  "properties": {
    "gn:admin1_code":"09",
    "gn:asciiname":"Barud Mbaiyra",
    "gn:country_code":"SS",
    "gn:dem":636,
    "gn:feature_class":"P",
    "gn:feature_code":"PPL",
    "gn:name":"Barud Mbaiyra",
    "gn:population":0,
    "gn:timezone":"Africa/Juba",
    "iso:country":"SS",
    "name:und_x_variant":[
        "Barud Mbaiya"
    ],
    "wof:lang_x_official":[
        "eng"
    ],
    "wof:lang_x_spoken":[
        "eng"
    ],
    "wof:name":"Barud Mbaiyra",
    "wof:placetype":"locality"
},
  "geometry": {"coordinates":[26.07288,7.98005],"type":"Point"}
}