{
  "type": "Feature",
  "properties": {
    "gn:admin1_code":"07",
    "gn:asciiname":"Alel",
    "gn:country_code":"SS",
    "gn:dem":396,
    "gn:feature_class":"P",
    "gn:feature_code":"PPL",
    "gn:name":"Alel",
    "gn:population":0,
    "gn:timezone":"Africa/Juba",
    "iso:country":"SS",
    "wof:name":"Alel",
    "wof:placetype":"locality"
},
  "geometry": {"coordinates":[31.64125,9.44367],"type":"Point"}
}