{
  "type": "Feature",
  "properties": {
    "gn:admin1_code":"01",
    "gn:asciiname":"Bush",
    "gn:country_code":"SS",
    "gn:dem":442,
    "gn:feature_class":"P",
    "gn:feature_code":"PPL",
    "gn:name":"Bush",
    "gn:population":0,
    "gn:timezone":"Africa/Juba",
    "iso:country":"SS",
    "name:ara_x_preferred":[
        "\u0628\u0648\u0634"
    ],
    "name:bel_x_preferred":[
        "\u0411\u0443\u0448"
    ],
    "name:bul_x_preferred":[
        "\u0411\u0443\u0448"
    ],
    "name:cat_x_preferred":[
        "Bush"
    ],
    "name:ceb_x_preferred":[
        "Bush"
    ],
    "name:ces_x_preferred":[
        "Bush"
    ],
    "name:deu_x_preferred":[
        "Bush"
    ],
    "name:est_x_preferred":[
        "Bush"
    ],
    "name:fin_x_preferred":[
        "Bush"
    ],
    "name:fra_x_preferred":[
        "Bush"
    ],
    "name:gle_x_preferred":[
        "Sceach"
    ],
    "name:heb_x_preferred":[
        "\u05d1\u05d5\u05e9"
    ],
    "name:hun_x_preferred":[
        "Bush"
    ],
    "name:hye_x_preferred":[
        "\u0532\u0578\u0582\u0577"
    ],
    "name:isl_x_preferred":[
        "Bush"
    ],
    "name:ita_x_preferred":[
        "Bush"
    ],
    "name:jpn_x_preferred":[
        "\u30d6\u30c3\u30b7\u30e5"
    ],
    "name:kaz_x_preferred":[
        "\u0411\u0443\u0448"
    ],
    "name:lav_x_preferred":[
        "Bush"
    ],
    "name:nld_x_preferred":[
        "Bush"
    ],
    "name:nor_x_preferred":[
        "Bush"
    ],
    "name:pol_x_preferred":[
        "Bush"
    ],
    "name:por_x_preferred":[
        "Bush"
    ],
    "name:ron_x_preferred":[
        "Bush"
    ],
    "name:rus_x_preferred":[
        "\u0411\u0443\u0448"
    ],
    "name:slk_x_preferred":[
        "Bush"
    ],
    "name:spa_x_preferred":[
        "Bush"
    ],
    "name:srp_x_preferred":[
        "\u0411\u0443\u0448"
    ],
    "name:swe_x_preferred":[
        "Bush"
    ],
    "name:tur_x_preferred":[
        "Bush"
    ],
    "name:ukr_x_preferred":[
        "\u0411\u0443\u0448"
    ],
    "wof:name":"Bush",
    "wof:placetype":"locality"
},
  "geometry": {"coordinates":[31.82701,5.66904],"type":"Point"}
}