{
  "type": "Feature",
  "properties": {
    "gn:admin1_code":"01",
    "gn:asciiname":"Bush",
    "gn:country_code":"SS",
    "gn:dem":442,
    "gn:feature_class":"P",
    "gn:feature_code":"PPL",
    "gn:name":"Bush",
    "gn:population":0,
    "gn:timezone":"Africa/Juba",
    "iso:country":"SS",
    "wof:name":"Bush",
    "wof:placetype":"locality"
},
  "geometry": {"coordinates":[31.82701,5.66904],"type":"Point"}
}