{
  "type": "Feature",
  "properties": {
    "gn:admin1_code":"04",
    "gn:asciiname":"Mayenwell",
    "gn:country_code":"SS",
    "gn:dem":427,
    "gn:feature_class":"P",
    "gn:feature_code":"PPL",
    "gn:name":"Mayenwell",
    "gn:population":0,
    "gn:timezone":"Africa/Juba",
    "iso:country":"SS",
    "wof:name":"Mayenwell",
    "wof:placetype":"locality"
},
  "geometry": {"coordinates":[29.43902000000001,6.84386],"type":"Point"}
}