{
  "type": "Feature",
  "properties": {
    "gn:admin1_code":"04",
    "gn:asciiname":"Abi Rij",
    "gn:country_code":"SS",
    "gn:dem":414,
    "gn:feature_class":"P",
    "gn:feature_code":"PPL",
    "gn:name":"Abi Rij",
    "gn:population":0,
    "gn:timezone":"Africa/Juba",
    "iso:country":"SS",
    "name:und_x_variant":[
        "Abiriu",
        "Abi Rij"
    ],
    "wof:name":"Abi Rij",
    "wof:placetype":"locality"
},
  "geometry": {"coordinates":[29.45341,6.96044],"type":"Point"}
}