{
  "type": "Feature",
  "properties": {
    "gn:admin1_code":"07",
    "gn:asciiname":"Fullu",
    "gn:country_code":"SS",
    "gn:dem":452,
    "gn:feature_class":"P",
    "gn:feature_code":"PPL",
    "gn:name":"Fullu",
    "gn:population":0,
    "gn:timezone":"Africa/Juba",
    "iso:country":"SS",
    "wof:name":"Fullu",
    "wof:placetype":"locality"
},
  "geometry": {"coordinates":[33.80654000000001,9.2283],"type":"Point"}
}