{
  "type": "Feature",
  "properties": {
    "gn:admin1_code":"07",
    "gn:asciiname":"Obwi",
    "gn:country_code":"SS",
    "gn:dem":394,
    "gn:feature_class":"P",
    "gn:feature_code":"PPL",
    "gn:name":"Obwi",
    "gn:population":0,
    "gn:timezone":"Africa/Juba",
    "iso:country":"SS",
    "wof:name":"Obwi",
    "wof:placetype":"locality"
},
  "geometry": {"coordinates":[32.24287,10.24885],"type":"Point"}
}