{
  "type": "Feature",
  "properties": {
    "gn:admin1_code":"07",
    "gn:asciiname":"Dinka Degeis",
    "gn:country_code":"SS",
    "gn:dem":409,
    "gn:feature_class":"P",
    "gn:feature_code":"PPL",
    "gn:name":"Dinka Degeis",
    "gn:population":0,
    "gn:timezone":"Africa/Juba",
    "iso:country":"SS",
    "name:und_x_variant":[
        "Ban Gieng Win",
        "Dinka Degeis"
    ],
    "wof:lang_x_official":[
        "eng"
    ],
    "wof:lang_x_spoken":[
        "eng"
    ],
    "wof:name":"Dinka Degeis",
    "wof:placetype":"locality"
},
  "geometry": {"coordinates":[33.20215,10.27355],"type":"Point"}
}