{
  "type": "Feature",
  "properties": {
    "gn:admin1_code":"08",
    "gn:asciiname":"Wun Rog",
    "gn:country_code":"SS",
    "gn:dem":407,
    "gn:feature_class":"P",
    "gn:feature_code":"PPL",
    "gn:name":"Wun Rog",
    "gn:population":0,
    "gn:timezone":"Africa/Juba",
    "iso:country":"SS",
    "name:eng_x_preferred":[
        "Wunrock"
    ],
    "name:und_x_variant":[
        "Wun Roj",
        "Wun Rog"
    ],
    "wof:lang_x_official":[
        "eng"
    ],
    "wof:lang_x_spoken":[
        "eng"
    ],
    "wof:name":"Wun Rog",
    "wof:placetype":"locality"
},
  "geometry": {"coordinates":[28.3026,8.98977],"type":"Point"}
}