{
  "type": "Feature",
  "properties": {
    "gn:admin1_code":"01",
    "gn:asciiname":"Dari",
    "gn:country_code":"SS",
    "gn:dem":484,
    "gn:feature_class":"P",
    "gn:feature_code":"PPL",
    "gn:name":"Dari",
    "gn:population":0,
    "gn:timezone":"Africa/Juba",
    "iso:country":"SS",
    "name:ceb_x_preferred":[
        "Dari"
    ],
    "name:deu_x_preferred":[
        "Dari"
    ],
    "name:ell_x_preferred":[
        "\u039d\u03c4\u03b1\u03c1\u03af"
    ],
    "name:fas_x_preferred":[
        "\u062f\u0631\u06cc"
    ],
    "name:ind_x_preferred":[
        "Dari"
    ],
    "name:ita_x_preferred":[
        "Dari"
    ],
    "name:jpn_x_preferred":[
        "\u30c0\u30ea\u30fc\u8a9e"
    ],
    "name:kur_x_preferred":[
        "Der\u00ee"
    ],
    "name:slk_x_preferred":[
        "Dar\u00edj\u010dina"
    ],
    "name:spa_x_preferred":[
        "Dari"
    ],
    "name:sun_x_preferred":[
        "Dari"
    ],
    "name:swe_x_preferred":[
        "Dari"
    ],
    "name:und_x_variant":[
        "Dorri"
    ],
    "name:vie_x_preferred":[
        "Dari"
    ],
    "wof:name":"Dari",
    "wof:placetype":"locality"
},
  "geometry": {"coordinates":[30.76155,6.00086],"type":"Point"}
}