{
  "type": "Feature",
  "properties": {
    "gn:admin1_code":"01",
    "gn:asciiname":"Dari",
    "gn:country_code":"SS",
    "gn:dem":484,
    "gn:feature_class":"P",
    "gn:feature_code":"PPL",
    "gn:name":"Dari",
    "gn:population":0,
    "gn:timezone":"Africa/Juba",
    "iso:country":"SS",
    "name:und_x_variant":[
        "Dorri",
        "Dari"
    ],
    "wof:name":"Dari",
    "wof:placetype":"locality"
},
  "geometry": {"coordinates":[30.76155,6.00086],"type":"Point"}
}