{
  "type": "Feature",
  "properties": {
    "gn:admin1_code":"03",
    "gn:asciiname":"Nikowa",
    "gn:country_code":"SS",
    "gn:dem":412,
    "gn:feature_class":"P",
    "gn:feature_code":"PPL",
    "gn:name":"Nikowa",
    "gn:population":0,
    "gn:timezone":"Africa/Juba",
    "iso:country":"SS",
    "wof:lang_x_official":[
        "eng"
    ],
    "wof:lang_x_spoken":[
        "eng"
    ],
    "wof:name":"Nikowa",
    "wof:placetype":"locality"
},
  "geometry": {"coordinates":[33.03167,7.78709],"type":"Point"}
}