{
  "type": "Feature",
  "properties": {
    "gn:admin1_code":"04",
    "gn:asciiname":"Panebei",
    "gn:country_code":"SS",
    "gn:dem":456,
    "gn:feature_class":"P",
    "gn:feature_code":"PPL",
    "gn:name":"Panebei",
    "gn:population":0,
    "gn:timezone":"Africa/Juba",
    "iso:country":"SS",
    "wof:name":"Panebei",
    "wof:placetype":"locality"
},
  "geometry": {"coordinates":[29.86283,6.45264],"type":"Point"}
}