{
  "type": "Feature",
  "properties": {
    "gn:admin1_code":"07",
    "gn:asciiname":"Derib Jungara",
    "gn:country_code":"SS",
    "gn:dem":426,
    "gn:feature_class":"P",
    "gn:feature_code":"PPL",
    "gn:name":"Derib Jungara",
    "gn:population":0,
    "gn:timezone":"Africa/Juba",
    "iso:country":"SS",
    "name:und_x_variant":[
        "Ban Gurrum",
        "Derib Jungara"
    ],
    "wof:name":"Derib Jungara",
    "wof:placetype":"locality"
},
  "geometry": {"coordinates":[33.34399000000001,10.32984],"type":"Point"}
}