{
  "type": "Feature",
  "properties": {
    "gn:admin1_code":"09",
    "gn:asciiname":"Umm Tugulgul",
    "gn:country_code":"SS",
    "gn:dem":629,
    "gn:feature_class":"P",
    "gn:feature_code":"PPL",
    "gn:name":"Umm Tugulgul",
    "gn:population":0,
    "gn:timezone":"Africa/Juba",
    "iso:country":"SS",
    "wof:name":"Umm Tugulgul",
    "wof:placetype":"locality"
},
  "geometry": {"coordinates":[25.94656,8.13993],"type":"Point"}
}