{
  "type": "Feature",
  "properties": {
    "gn:admin1_code":"10",
    "gn:asciiname":"Verikoka",
    "gn:country_code":"SS",
    "gn:dem":557,
    "gn:feature_class":"P",
    "gn:feature_code":"PPL",
    "gn:name":"Verikoka",
    "gn:population":0,
    "gn:timezone":"Africa/Juba",
    "iso:country":"SS",
    "wof:lang_x_official":[
        "eng"
    ],
    "wof:lang_x_spoken":[
        "eng"
    ],
    "wof:name":"Verikoka",
    "wof:placetype":"locality"
},
  "geometry": {"coordinates":[30.8487,5.14365],"type":"Point"}
}