{
  "type": "Feature",
  "properties": {
    "gn:admin1_code":"02",
    "gn:asciiname":"Paja",
    "gn:country_code":"SS",
    "gn:dem":859,
    "gn:feature_class":"P",
    "gn:feature_code":"PPL",
    "gn:name":"Paja",
    "gn:population":0,
    "gn:timezone":"Africa/Juba",
    "iso:country":"SS",
    "name:fas_x_preferred":[
        "\u067e\u0627\u062c\u0627"
    ],
    "name:glk_x_preferred":[
        "\u067e\u0627\u062c\u0627"
    ],
    "name:mzn_x_preferred":[
        "\u067e\u0627\u062c\u0627"
    ],
    "wof:name":"Paja",
    "wof:placetype":"locality"
},
  "geometry": {"coordinates":[32.04461,3.96556],"type":"Point"}
}