{
  "type": "Feature",
  "properties": {
    "gn:admin1_code":"01",
    "gn:asciiname":"Jada",
    "gn:country_code":"SS",
    "gn:dem":479,
    "gn:feature_class":"P",
    "gn:feature_code":"PPL",
    "gn:name":"Jada",
    "gn:population":0,
    "gn:timezone":"Africa/Juba",
    "iso:country":"SS",
    "wof:name":"Jada",
    "wof:placetype":"locality"
},
  "geometry": {"coordinates":[31.67447,4.83672],"type":"Point"}
}