{
  "type": "Feature",
  "properties": {
    "gn:admin1_code":"05",
    "gn:asciiname":"Makwoich",
    "gn:country_code":"SS",
    "gn:dem":429,
    "gn:feature_class":"P",
    "gn:feature_code":"PPL",
    "gn:name":"Makwoich",
    "gn:population":0,
    "gn:timezone":"Africa/Juba",
    "iso:country":"SS",
    "wof:name":"Makwoich",
    "wof:placetype":"locality"
},
  "geometry": {"coordinates":[27.23581,8.9644],"type":"Point"}
}