{
  "type": "Feature",
  "properties": {
    "gn:admin1_code":"04",
    "gn:asciiname":"Nyaliet",
    "gn:country_code":"SS",
    "gn:dem":430,
    "gn:feature_class":"P",
    "gn:feature_code":"PPL",
    "gn:name":"Nyaliet",
    "gn:population":0,
    "gn:timezone":"Africa/Juba",
    "iso:country":"SS",
    "name:und_x_variant":[
        "Nyaliot"
    ],
    "wof:name":"Nyaliet",
    "wof:placetype":"locality"
},
  "geometry": {"coordinates":[30.52234,6.59677],"type":"Point"}
}