{
  "type": "Feature",
  "properties": {
    "gn:admin1_code":"06",
    "gn:asciiname":"Akait",
    "gn:country_code":"SS",
    "gn:dem":398,
    "gn:feature_class":"P",
    "gn:feature_code":"PPL",
    "gn:name":"Akait",
    "gn:population":0,
    "gn:timezone":"Africa/Juba",
    "iso:country":"SS",
    "wof:name":"Akait",
    "wof:placetype":"locality"
},
  "geometry": {"coordinates":[29.61843,9.2351],"type":"Point"}
}