{
  "type": "Feature",
  "properties": {
    "gn:admin1_code":"02",
    "gn:asciiname":"Lokila",
    "gn:country_code":"SS",
    "gn:dem":598,
    "gn:feature_class":"P",
    "gn:feature_code":"PPL",
    "gn:name":"Lokila",
    "gn:population":0,
    "gn:timezone":"Africa/Juba",
    "iso:country":"SS",
    "wof:name":"Lokila",
    "wof:placetype":"locality"
},
  "geometry": {"coordinates":[32.22470999999999,4.54864],"type":"Point"}
}