{
  "type": "Feature",
  "properties": {
    "gn:admin1_code":"01",
    "gn:asciiname":"Pogu",
    "gn:country_code":"SS",
    "gn:dem":1085,
    "gn:feature_class":"P",
    "gn:feature_code":"PPL",
    "gn:name":"Pogu",
    "gn:population":0,
    "gn:timezone":"Africa/Juba",
    "iso:country":"SS",
    "wof:name":"Pogu",
    "wof:placetype":"locality"
},
  "geometry": {"coordinates":[30.61083,3.77776],"type":"Point"}
}