{
  "type": "Feature",
  "properties": {
    "gn:admin1_code":"08",
    "gn:asciiname":"Fan Agork",
    "gn:country_code":"SS",
    "gn:dem":400,
    "gn:feature_class":"P",
    "gn:feature_code":"PPL",
    "gn:name":"Fan Agork",
    "gn:population":0,
    "gn:timezone":"Africa/Juba",
    "iso:country":"SS",
    "wof:name":"Fan Agork",
    "wof:placetype":"locality"
},
  "geometry": {"coordinates":[28.63333,9.08333],"type":"Point"}
}