{
  "type": "Feature",
  "properties": {
    "gn:admin1_code":"02",
    "gn:asciiname":"Agoro",
    "gn:country_code":"SS",
    "gn:dem":795,
    "gn:feature_class":"P",
    "gn:feature_code":"PPL",
    "gn:name":"Agoro",
    "gn:population":0,
    "gn:timezone":"Africa/Juba",
    "iso:country":"SS",
    "wof:name":"Agoro",
    "wof:placetype":"locality"
},
  "geometry": {"coordinates":[32.23477,4.15197],"type":"Point"}
}