{
  "type": "Feature",
  "properties": {
    "gn:admin1_code":"08",
    "gn:asciiname":"Kwok",
    "gn:country_code":"SS",
    "gn:dem":400,
    "gn:feature_class":"P",
    "gn:feature_code":"PPL",
    "gn:name":"Kwok",
    "gn:population":0,
    "gn:timezone":"Africa/Juba",
    "iso:country":"SS",
    "wof:name":"Kwok",
    "wof:placetype":"locality"
},
  "geometry": {"coordinates":[29.47068,8.07604],"type":"Point"}
}