{
  "type": "Feature",
  "properties": {
    "gn:admin1_code":"08",
    "gn:asciiname":"Madud Avom",
    "gn:country_code":"SS",
    "gn:dem":469,
    "gn:feature_class":"P",
    "gn:feature_code":"PPL",
    "gn:name":"Madud Avom",
    "gn:population":0,
    "gn:timezone":"Africa/Juba",
    "iso:country":"SS",
    "wof:name":"Madud Avom",
    "wof:placetype":"locality"
},
  "geometry": {"coordinates":[27.80429,8.22571],"type":"Point"}
}