{
  "type": "Feature",
  "properties": {
    "gn:admin1_code":"10",
    "gn:asciiname":"Bufi",
    "gn:country_code":"SS",
    "gn:dem":481,
    "gn:feature_class":"P",
    "gn:feature_code":"PPL",
    "gn:name":"Bufi",
    "gn:population":0,
    "gn:timezone":"Africa/Juba",
    "iso:country":"SS",
    "name:deu_x_preferred":[
        "Bufi"
    ],
    "name:ita_x_preferred":[
        "Bufi"
    ],
    "wof:lang_x_official":[
        "eng"
    ],
    "wof:lang_x_spoken":[
        "eng"
    ],
    "wof:name":"Bufi",
    "wof:placetype":"locality"
},
  "geometry": {"coordinates":[30.29822,5.90194],"type":"Point"}
}