{
  "type": "Feature",
  "properties": {
    "gn:admin1_code":"07",
    "gn:asciiname":"Mutt",
    "gn:country_code":"SS",
    "gn:dem":396,
    "gn:feature_class":"P",
    "gn:feature_code":"PPL",
    "gn:name":"Mutt",
    "gn:population":0,
    "gn:timezone":"Africa/Juba",
    "iso:country":"SS",
    "wof:name":"Mutt",
    "wof:placetype":"locality"
},
  "geometry": {"coordinates":[32.14802,10.44965],"type":"Point"}
}