{
  "type": "Feature",
  "properties": {
    "gn:admin1_code":"08",
    "gn:asciiname":"Fan Dung",
    "gn:country_code":"SS",
    "gn:dem":417,
    "gn:feature_class":"P",
    "gn:feature_code":"PPL",
    "gn:name":"Fan Dung",
    "gn:population":0,
    "gn:timezone":"Africa/Juba",
    "iso:country":"SS",
    "wof:name":"Fan Dung",
    "wof:placetype":"locality"
},
  "geometry": {"coordinates":[27.80582,8.74707],"type":"Point"}
}