{
  "type": "Feature",
  "properties": {
    "gn:admin1_code":"03",
    "gn:asciiname":"Wang Tar",
    "gn:country_code":"SS",
    "gn:dem":399,
    "gn:feature_class":"P",
    "gn:feature_code":"PPL",
    "gn:name":"Wang Tar",
    "gn:population":0,
    "gn:timezone":"Africa/Juba",
    "iso:country":"SS",
    "wof:name":"Wang Tar",
    "wof:placetype":"locality"
},
  "geometry": {"coordinates":[30.98924,9.43118],"type":"Point"}
}