{
  "type": "Feature",
  "properties": {
    "gn:admin1_code":"03",
    "gn:asciiname":"Wangledid",
    "gn:country_code":"SS",
    "gn:dem":412,
    "gn:feature_class":"P",
    "gn:feature_code":"PPL",
    "gn:name":"Wangledid",
    "gn:population":0,
    "gn:timezone":"Africa/Juba",
    "iso:country":"SS",
    "wof:name":"Wangledid",
    "wof:placetype":"locality"
},
  "geometry": {"coordinates":[32.33962,7.98001],"type":"Point"}
}