{
  "type": "Feature",
  "properties": {
    "gn:admin1_code":"01",
    "gn:asciiname":"Jungu",
    "gn:country_code":"SS",
    "gn:dem":952,
    "gn:feature_class":"P",
    "gn:feature_code":"PPL",
    "gn:name":"Jungu",
    "gn:population":0,
    "gn:timezone":"Africa/Juba",
    "iso:country":"SS",
    "wof:name":"Jungu",
    "wof:placetype":"locality"
},
  "geometry": {"coordinates":[31.04300000000001,4.30175],"type":"Point"}
}