{
  "type": "Feature",
  "properties": {
    "gn:admin1_code":"03",
    "gn:asciiname":"Tep Jor",
    "gn:country_code":"SS",
    "gn:dem":404,
    "gn:feature_class":"P",
    "gn:feature_code":"PPL",
    "gn:name":"Tep Jor",
    "gn:population":0,
    "gn:timezone":"Africa/Juba",
    "iso:country":"SS",
    "wof:name":"Tep Jor",
    "wof:placetype":"locality"
},
  "geometry": {"coordinates":[32.38633,8.33763],"type":"Point"}
}