{
  "type": "Feature",
  "properties": {
    "gn:admin1_code":"08",
    "gn:asciiname":"Jerajup",
    "gn:country_code":"SS",
    "gn:dem":425,
    "gn:feature_class":"P",
    "gn:feature_code":"PPL",
    "gn:name":"Jerajup",
    "gn:population":0,
    "gn:timezone":"Africa/Juba",
    "iso:country":"SS",
    "wof:name":"Jerajup",
    "wof:placetype":"locality"
},
  "geometry": {"coordinates":[27.74116,8.58638],"type":"Point"}
}