{
  "type": "Feature",
  "properties": {
    "gn:admin1_code":"03",
    "gn:asciiname":"Ushini",
    "gn:country_code":"SS",
    "gn:dem":419,
    "gn:feature_class":"P",
    "gn:feature_code":"PPL",
    "gn:name":"Ushini",
    "gn:population":0,
    "gn:timezone":"Africa/Juba",
    "iso:country":"SS",
    "wof:name":"Ushini",
    "wof:placetype":"locality"
},
  "geometry": {"coordinates":[33.55783,7.68477],"type":"Point"}
}