{
  "type": "Feature",
  "properties": {
    "gn:admin1_code":"04",
    "gn:asciiname":"Anyei",
    "gn:country_code":"SS",
    "gn:dem":429,
    "gn:feature_class":"P",
    "gn:feature_code":"PPL",
    "gn:name":"Anyei",
    "gn:population":0,
    "gn:timezone":"Africa/Juba",
    "iso:country":"SS",
    "wof:name":"Anyei",
    "wof:placetype":"locality"
},
  "geometry": {"coordinates":[31.01176,6.60809],"type":"Point"}
}