{
  "type": "Feature",
  "properties": {
    "gn:admin1_code":"08",
    "gn:asciiname":"N'gork Aliang",
    "gn:country_code":"SS",
    "gn:dem":414,
    "gn:feature_class":"P",
    "gn:feature_code":"PPL",
    "gn:name":"N\u2019gork Aliang",
    "gn:population":0,
    "gn:timezone":"Africa/Juba",
    "iso:country":"SS",
    "wof:name":"N'gork Aliang",
    "wof:placetype":"locality"
},
  "geometry": {"coordinates":[27.97569,8.66684],"type":"Point"}
}