{
  "type": "Feature",
  "properties": {
    "gn:admin1_code":"05",
    "gn:asciiname":"Apeir",
    "gn:country_code":"SS",
    "gn:dem":421,
    "gn:feature_class":"P",
    "gn:feature_code":"PPL",
    "gn:name":"Apeir",
    "gn:population":0,
    "gn:timezone":"Africa/Juba",
    "iso:country":"SS",
    "wof:name":"Apeir",
    "wof:placetype":"locality"
},
  "geometry": {"coordinates":[27.67907,8.98452],"type":"Point"}
}