{
  "type": "Feature",
  "properties": {
    "gn:admin1_code":"02",
    "gn:asciiname":"Kikirik",
    "gn:country_code":"SS",
    "gn:dem":819,
    "gn:feature_class":"P",
    "gn:feature_code":"PPL",
    "gn:name":"Kikirik",
    "gn:population":0,
    "gn:timezone":"Africa/Juba",
    "iso:country":"SS",
    "wof:name":"Kikirik",
    "wof:placetype":"locality"
},
  "geometry": {"coordinates":[33.06636,4.13387],"type":"Point"}
}