{
  "type": "Feature",
  "properties": {
    "gn:admin1_code":"10",
    "gn:asciiname":"Dhiau",
    "gn:country_code":"SS",
    "gn:dem":467,
    "gn:feature_class":"P",
    "gn:feature_code":"PPL",
    "gn:name":"Dhiau",
    "gn:population":0,
    "gn:timezone":"Africa/Juba",
    "iso:country":"SS",
    "wof:name":"Dhiau",
    "wof:placetype":"locality"
},
  "geometry": {"coordinates":[30.19233,6.11467],"type":"Point"}
}