{
  "type": "Feature",
  "properties": {
    "gn:admin1_code":"07",
    "gn:asciiname":"Nyintok",
    "gn:country_code":"SS",
    "gn:dem":401,
    "gn:feature_class":"P",
    "gn:feature_code":"PPL",
    "gn:name":"Nyintok",
    "gn:population":0,
    "gn:timezone":"Africa/Juba",
    "iso:country":"SS",
    "name:und_x_variant":[
        "Nintok"
    ],
    "wof:name":"Nyintok",
    "wof:placetype":"locality"
},
  "geometry": {"coordinates":[32.66192,8.64656],"type":"Point"}
}