{
  "type": "Feature",
  "properties": {
    "gn:admin1_code":"04",
    "gn:asciiname":"Golmayen",
    "gn:country_code":"SS",
    "gn:dem":423,
    "gn:feature_class":"P",
    "gn:feature_code":"PPL",
    "gn:name":"Golmayen",
    "gn:population":0,
    "gn:timezone":"Africa/Juba",
    "iso:country":"SS",
    "wof:name":"Golmayen",
    "wof:placetype":"locality"
},
  "geometry": {"coordinates":[29.80486,6.92077],"type":"Point"}
}