{
  "type": "Feature",
  "properties": {
    "gn:admin1_code":"04",
    "gn:asciiname":"Akeu",
    "gn:country_code":"SS",
    "gn:dem":433,
    "gn:feature_class":"P",
    "gn:feature_code":"PPL",
    "gn:name":"Akeu",
    "gn:population":0,
    "gn:timezone":"Africa/Juba",
    "iso:country":"SS",
    "wof:name":"Akeu",
    "wof:placetype":"locality"
},
  "geometry": {"coordinates":[30.61373,6.26634],"type":"Point"}
}