{
  "type": "Feature",
  "properties": {
    "gn:admin1_code":"01",
    "gn:asciiname":"Loga",
    "gn:country_code":"SS",
    "gn:dem":904,
    "gn:feature_class":"P",
    "gn:feature_code":"PPL",
    "gn:name":"Loga",
    "gn:population":0,
    "gn:timezone":"Africa/Juba",
    "iso:country":"SS",
    "wof:name":"Loga",
    "wof:placetype":"locality"
},
  "geometry": {"coordinates":[31.20694,4.09167],"type":"Point"}
}