{
  "type": "Feature",
  "properties": {
    "gn:admin1_code":"04",
    "gn:asciiname":"Raag",
    "gn:country_code":"SS",
    "gn:dem":429,
    "gn:feature_class":"P",
    "gn:feature_code":"PPL",
    "gn:name":"Raag",
    "gn:population":0,
    "gn:timezone":"Africa/Juba",
    "iso:country":"SS",
    "wof:name":"Raag",
    "wof:placetype":"locality"
},
  "geometry": {"coordinates":[29.96404,6.79446],"type":"Point"}
}