{
  "type": "Feature",
  "properties": {
    "gn:admin1_code":"01",
    "gn:asciiname":"Reien",
    "gn:country_code":"SS",
    "gn:dem":468,
    "gn:feature_class":"P",
    "gn:feature_code":"PPL",
    "gn:name":"Reien",
    "gn:population":0,
    "gn:timezone":"Africa/Juba",
    "iso:country":"SS",
    "name:und_x_variant":[
        "Rein",
        "Reien"
    ],
    "wof:name":"Reien",
    "wof:placetype":"locality"
},
  "geometry": {"coordinates":[30.52041,6.0595],"type":"Point"}
}