{
  "type": "Feature",
  "properties": {
    "gn:admin1_code":"05",
    "gn:asciiname":"Ashaki",
    "gn:country_code":"SS",
    "gn:dem":487,
    "gn:feature_class":"P",
    "gn:feature_code":"PPL",
    "gn:name":"Ashaki",
    "gn:population":0,
    "gn:timezone":"Africa/Juba",
    "iso:country":"SS",
    "name:und_x_variant":[
        "Ashasi",
        "Ashaki"
    ],
    "wof:name":"Ashaki",
    "wof:placetype":"locality"
},
  "geometry": {"coordinates":[26.20843,8.7351],"type":"Point"}
}