{
  "type": "Feature",
  "properties": {
    "gn:admin1_code":"10",
    "gn:asciiname":"Dodo",
    "gn:country_code":"SS",
    "gn:dem":685,
    "gn:feature_class":"P",
    "gn:feature_code":"PPL",
    "gn:name":"Dodo",
    "gn:population":0,
    "gn:timezone":"Africa/Juba",
    "iso:country":"SS",
    "wof:name":"Dodo",
    "wof:placetype":"locality"
},
  "geometry": {"coordinates":[29.93556,5.09889],"type":"Point"}
}