{
  "type": "Feature",
  "properties": {
    "gn:admin1_code":"10",
    "gn:asciiname":"Baragu",
    "gn:country_code":"SS",
    "gn:dem":712,
    "gn:feature_class":"P",
    "gn:feature_code":"PPL",
    "gn:name":"Baragu",
    "gn:population":0,
    "gn:timezone":"Africa/Juba",
    "iso:country":"SS",
    "wof:name":"Baragu",
    "wof:placetype":"locality"
},
  "geometry": {"coordinates":[27.68865,4.98325],"type":"Point"}
}