{
  "type": "Feature",
  "properties": {
    "gn:admin1_code":"10",
    "gn:asciiname":"Naramha",
    "gn:country_code":"SS",
    "gn:dem":593,
    "gn:feature_class":"P",
    "gn:feature_code":"PPL",
    "gn:name":"Naramha",
    "gn:population":0,
    "gn:timezone":"Africa/Juba",
    "iso:country":"SS",
    "name:und_x_variant":[
        "Naramoa",
        "Naramha"
    ],
    "wof:name":"Naramha",
    "wof:placetype":"locality"
},
  "geometry": {"coordinates":[30.68263,5.15033],"type":"Point"}
}