{
  "type": "Feature",
  "properties": {
    "gn:admin1_code":"07",
    "gn:asciiname":"Kanshur",
    "gn:country_code":"SS",
    "gn:dem":413,
    "gn:feature_class":"P",
    "gn:feature_code":"PPL",
    "gn:name":"Kanshur",
    "gn:population":0,
    "gn:timezone":"Africa/Juba",
    "iso:country":"SS",
    "wof:name":"Kanshur",
    "wof:placetype":"locality"
},
  "geometry": {"coordinates":[33.2816,10.03497],"type":"Point"}
}