{
  "type": "Feature",
  "properties": {
    "gn:admin1_code":"06",
    "gn:asciiname":"Dor Akoich",
    "gn:country_code":"SS",
    "gn:dem":395,
    "gn:feature_class":"P",
    "gn:feature_code":"PPL",
    "gn:name":"Dor Akoich",
    "gn:population":0,
    "gn:timezone":"Africa/Juba",
    "iso:country":"SS",
    "name:und_x_variant":[
        "Dor Kich"
    ],
    "wof:name":"Dor Akoich",
    "wof:placetype":"locality"
},
  "geometry": {"coordinates":[29.88126,8.85383],"type":"Point"}
}