{
  "type": "Feature",
  "properties": {
    "gn:admin1_code":"03",
    "gn:asciiname":"Ayom",
    "gn:country_code":"SS",
    "gn:dem":411,
    "gn:feature_class":"P",
    "gn:feature_code":"PPL",
    "gn:name":"Ayom",
    "gn:population":0,
    "gn:timezone":"Africa/Juba",
    "iso:country":"SS",
    "wof:name":"Ayom",
    "wof:placetype":"locality"
},
  "geometry": {"coordinates":[31.8595,7.69718],"type":"Point"}
}