{
  "type": "Feature",
  "properties": {
    "gn:admin1_code":"01",
    "gn:asciiname":"Kuja",
    "gn:country_code":"SS",
    "gn:dem":550,
    "gn:feature_class":"P",
    "gn:feature_code":"PPL",
    "gn:name":"Kuja",
    "gn:population":0,
    "gn:timezone":"Africa/Juba",
    "iso:country":"SS",
    "wof:name":"Kuja",
    "wof:placetype":"locality"
},
  "geometry": {"coordinates":[31.59464,4.58144],"type":"Point"}
}