{
  "type": "Feature",
  "properties": {
    "gn:admin1_code":"07",
    "gn:asciiname":"Pwot",
    "gn:country_code":"SS",
    "gn:dem":397,
    "gn:feature_class":"P",
    "gn:feature_code":"PPL",
    "gn:name":"Pwot",
    "gn:population":0,
    "gn:timezone":"Africa/Juba",
    "iso:country":"SS",
    "wof:name":"Pwot",
    "wof:placetype":"locality"
},
  "geometry": {"coordinates":[31.67044000000001,9.61093],"type":"Point"}
}