{
  "type": "Feature",
  "properties": {
    "gn:admin1_code":"10",
    "gn:asciiname":"Zumbu",
    "gn:country_code":"SS",
    "gn:dem":672,
    "gn:feature_class":"P",
    "gn:feature_code":"PPL",
    "gn:name":"Zumbu",
    "gn:population":0,
    "gn:timezone":"Africa/Juba",
    "iso:country":"SS",
    "wof:name":"Zumbu",
    "wof:placetype":"locality"
},
  "geometry": {"coordinates":[29.17,5.14944],"type":"Point"}
}