{
  "type": "Feature",
  "properties": {
    "gn:admin1_code":"08",
    "gn:asciiname":"Monok",
    "gn:country_code":"SS",
    "gn:dem":409,
    "gn:feature_class":"P",
    "gn:feature_code":"PPL",
    "gn:name":"Monok",
    "gn:population":0,
    "gn:timezone":"Africa/Juba",
    "iso:country":"SS",
    "name:bar_x_preferred":[
        "Monok"
    ],
    "name:ceb_x_preferred":[
        "Monok"
    ],
    "name:deu_x_preferred":[
        "Monok"
    ],
    "name:epo_x_preferred":[
        "Monok"
    ],
    "name:fas_x_preferred":[
        "\u0645\u0648\u0646\u0648\u06a9"
    ],
    "name:fra_x_preferred":[
        "Monok"
    ],
    "name:heb_x_preferred":[
        "\u05de\u05d5\u05e0\u05d5\u05e7"
    ],
    "name:hun_x_preferred":[
        "Monok"
    ],
    "name:ita_x_preferred":[
        "Monok"
    ],
    "name:jpn_x_preferred":[
        "\u30e2\u30ce\u30af"
    ],
    "name:msa_x_preferred":[
        "Monok"
    ],
    "name:nld_x_preferred":[
        "Monok"
    ],
    "name:pol_x_preferred":[
        "Monok"
    ],
    "name:ron_x_preferred":[
        "Monok"
    ],
    "name:slk_x_preferred":[
        "Monok"
    ],
    "name:slv_x_preferred":[
        "Monok"
    ],
    "name:vie_x_preferred":[
        "Monok"
    ],
    "name:zho_x_preferred":[
        "\u83ab\u8bfa\u514b"
    ],
    "wof:name":"Monok",
    "wof:placetype":"locality"
},
  "geometry": {"coordinates":[28.32065,8.65836],"type":"Point"}
}