{
  "type": "Feature",
  "properties": {
    "gn:admin1_code":"10",
    "gn:asciiname":"Mandi",
    "gn:country_code":"SS",
    "gn:dem":651,
    "gn:feature_class":"P",
    "gn:feature_code":"PPL",
    "gn:name":"Mandi",
    "gn:population":0,
    "gn:timezone":"Africa/Juba",
    "iso:country":"SS",
    "wof:name":"Mandi",
    "wof:placetype":"locality"
},
  "geometry": {"coordinates":[30.21455,5.14066],"type":"Point"}
}