{
  "type": "Feature",
  "properties": {
    "gn:admin1_code":"03",
    "gn:asciiname":"Chwegh",
    "gn:country_code":"SS",
    "gn:dem":405,
    "gn:feature_class":"P",
    "gn:feature_code":"PPL",
    "gn:name":"Chwegh",
    "gn:population":0,
    "gn:timezone":"Africa/Juba",
    "iso:country":"SS",
    "name:und_x_variant":[
        "Chweg"
    ],
    "wof:name":"Chwegh",
    "wof:placetype":"locality"
},
  "geometry": {"coordinates":[30.69629,9.13631],"type":"Point"}
}