{
  "type": "Feature",
  "properties": {
    "gn:admin1_code":"10",
    "gn:asciiname":"Jabel Manbolo",
    "gn:country_code":"SS",
    "gn:dem":498,
    "gn:feature_class":"P",
    "gn:feature_code":"PPL",
    "gn:name":"Jabel Manbolo",
    "gn:population":0,
    "gn:timezone":"Africa/Juba",
    "iso:country":"SS",
    "wof:name":"Jabel Manbolo",
    "wof:placetype":"locality"
},
  "geometry": {"coordinates":[30.06803,6.00384],"type":"Point"}
}