{
  "type": "Feature",
  "properties": {
    "gn:admin1_code":"08",
    "gn:asciiname":"Rorayai",
    "gn:country_code":"SS",
    "gn:dem":418,
    "gn:feature_class":"P",
    "gn:feature_code":"PPL",
    "gn:name":"Rorayai",
    "gn:population":0,
    "gn:timezone":"Africa/Juba",
    "iso:country":"SS",
    "name:und_x_variant":[
        "Roarei",
        "Rorayai"
    ],
    "wof:name":"Rorayai",
    "wof:placetype":"locality"
},
  "geometry": {"coordinates":[27.65408,8.83257],"type":"Point"}
}