{
  "type": "Feature",
  "properties": {
    "gn:admin1_code":"01",
    "gn:asciiname":"Lujulu",
    "gn:country_code":"SS",
    "gn:dem":1195,
    "gn:feature_class":"P",
    "gn:feature_code":"PPL",
    "gn:name":"Lujulu",
    "gn:population":0,
    "gn:timezone":"Africa/Juba",
    "iso:country":"SS",
    "wof:name":"Lujulu",
    "wof:placetype":"locality"
},
  "geometry": {"coordinates":[30.66755,3.68402],"type":"Point"}
}