{
  "type": "Feature",
  "properties": {
    "gn:admin1_code":"03",
    "gn:asciiname":"Manbitshei",
    "gn:country_code":"SS",
    "gn:dem":422,
    "gn:feature_class":"P",
    "gn:feature_code":"PPL",
    "gn:name":"Manbitshei",
    "gn:population":0,
    "gn:timezone":"Africa/Juba",
    "iso:country":"SS",
    "wof:name":"Manbitshei",
    "wof:placetype":"locality"
},
  "geometry": {"coordinates":[33.09145,6.71019],"type":"Point"}
}