{
  "type": "Feature",
  "properties": {
    "gn:admin1_code":"06",
    "gn:asciiname":"Yidit",
    "gn:country_code":"SS",
    "gn:dem":399,
    "gn:feature_class":"P",
    "gn:feature_code":"PPL",
    "gn:name":"Yidit",
    "gn:population":0,
    "gn:timezone":"Africa/Juba",
    "iso:country":"SS",
    "wof:name":"Yidit",
    "wof:placetype":"locality"
},
  "geometry": {"coordinates":[30.29481,9.59099],"type":"Point"}
}