{
  "type": "Feature",
  "properties": {
    "gn:admin1_code":"28",
    "gn:asciiname":"Rimenze",
    "gn:country_code":"SS",
    "gn:dem":672,
    "gn:feature_class":"P",
    "gn:feature_code":"PPL",
    "gn:name":"Rimenze",
    "gn:population":0,
    "gn:timezone":"Africa/Juba",
    "iso:country":"SS",
    "wof:name":"Rimenze",
    "wof:placetype":"locality"
},
  "geometry": {"coordinates":[28.5895,4.71082],"type":"Point"}
}