{
  "type": "Feature",
  "properties": {
    "gn:admin1_code":"02",
    "gn:asciiname":"Gharingoru",
    "gn:country_code":"SS",
    "gn:dem":798,
    "gn:feature_class":"P",
    "gn:feature_code":"PPL",
    "gn:name":"Gharingoru",
    "gn:population":0,
    "gn:timezone":"Africa/Juba",
    "iso:country":"SS",
    "name:und_x_variant":[
        "Garingoru"
    ],
    "wof:name":"Gharingoru",
    "wof:placetype":"locality"
},
  "geometry": {"coordinates":[33.2705,4.07159],"type":"Point"}
}