{
  "type": "Feature",
  "properties": {
    "gn:admin1_code":"03",
    "gn:asciiname":"Cantiere",
    "gn:country_code":"SS",
    "gn:dem":698,
    "gn:feature_class":"P",
    "gn:feature_code":"PPL",
    "gn:name":"Cantiere",
    "gn:population":0,
    "gn:timezone":"Africa/Juba",
    "iso:country":"SS",
    "name:und_x_variant":[
        "Kantiere"
    ],
    "wof:name":"Cantiere",
    "wof:placetype":"locality"
},
  "geometry": {"coordinates":[34.94172,6.44529],"type":"Point"}
}