{
  "type": "Feature",
  "properties": {
    "gn:admin1_code":"08",
    "gn:asciiname":"Abiyei",
    "gn:country_code":"SS",
    "gn:dem":410,
    "gn:feature_class":"P",
    "gn:feature_code":"PPL",
    "gn:name":"Abiyei",
    "gn:population":0,
    "gn:timezone":"Africa/Juba",
    "iso:country":"SS",
    "wof:name":"Abiyei",
    "wof:placetype":"locality"
},
  "geometry": {"coordinates":[29.24691,7.88907],"type":"Point"}
}