{
  "type": "Feature",
  "properties": {
    "gn:admin1_code":"01",
    "gn:asciiname":"Olibari",
    "gn:country_code":"SS",
    "gn:dem":946,
    "gn:feature_class":"P",
    "gn:feature_code":"PPL",
    "gn:name":"Olibari",
    "gn:population":0,
    "gn:timezone":"Africa/Juba",
    "iso:country":"SS",
    "wof:name":"Olibari",
    "wof:placetype":"locality"
},
  "geometry": {"coordinates":[31.00537000000001,4.25837],"type":"Point"}
}