{
  "type": "Feature",
  "properties": {
    "gn:admin1_code":"10",
    "gn:asciiname":"Li Rangu",
    "gn:country_code":"SS",
    "gn:dem":672,
    "gn:feature_class":"P",
    "gn:feature_code":"PPL",
    "gn:name":"Li Rangu",
    "gn:population":0,
    "gn:timezone":"Africa/Juba",
    "iso:country":"SS",
    "wof:name":"Li Rangu",
    "wof:placetype":"locality"
},
  "geometry": {"coordinates":[28.35917,4.72944],"type":"Point"}
}