{
  "type": "Feature",
  "properties": {
    "gn:admin1_code":"08",
    "gn:asciiname":"Kome",
    "gn:country_code":"SS",
    "gn:dem":434,
    "gn:feature_class":"P",
    "gn:feature_code":"PPL",
    "gn:name":"Kome",
    "gn:population":0,
    "gn:timezone":"Africa/Juba",
    "iso:country":"SS",
    "name:ceb_x_preferred":[
        "Kome"
    ],
    "name:deu_x_preferred":[
        "Kome"
    ],
    "name:ita_x_preferred":[
        "Kome"
    ],
    "name:swe_x_preferred":[
        "Kome"
    ],
    "wof:lang_x_official":[
        "eng"
    ],
    "wof:lang_x_spoken":[
        "eng"
    ],
    "wof:name":"Kome",
    "wof:placetype":"locality"
},
  "geometry": {"coordinates":[27.58142,8.51526],"type":"Point"}
}