{
  "type": "Feature",
  "properties": {
    "gn:admin1_code":"10",
    "gn:asciiname":"Jabal Afi",
    "gn:country_code":"SS",
    "gn:dem":877,
    "gn:feature_class":"P",
    "gn:feature_code":"PPL",
    "gn:name":"Jabal Afi",
    "gn:population":0,
    "gn:timezone":"Africa/Juba",
    "iso:country":"SS",
    "name:und_x_variant":[
        "Jebel Afi"
    ],
    "wof:name":"Jabal Afi",
    "wof:placetype":"locality"
},
  "geometry": {"coordinates":[29.49872,4.73199],"type":"Point"}
}