{
  "type": "Feature",
  "properties": {
    "gn:admin1_code":"09",
    "gn:asciiname":"Saidun Hamadan",
    "gn:country_code":"SS",
    "gn:dem":506,
    "gn:feature_class":"P",
    "gn:feature_code":"PPL",
    "gn:name":"Saidun Hamadan",
    "gn:population":0,
    "gn:timezone":"Africa/Juba",
    "iso:country":"SS",
    "wof:lang_x_official":[
        "eng"
    ],
    "wof:lang_x_spoken":[
        "eng"
    ],
    "wof:name":"Saidun Hamadan",
    "wof:placetype":"locality"
},
  "geometry": {"coordinates":[25.83057,8.6864],"type":"Point"}
}