{
  "type": "Feature",
  "properties": {
    "gn:admin1_code":"06",
    "gn:asciiname":"Diam",
    "gn:country_code":"SS",
    "gn:dem":393,
    "gn:feature_class":"P",
    "gn:feature_code":"PPL",
    "gn:name":"Diam",
    "gn:population":0,
    "gn:timezone":"Africa/Juba",
    "iso:country":"SS",
    "wof:name":"Diam",
    "wof:placetype":"locality"
},
  "geometry": {"coordinates":[29.55673,9.20786],"type":"Point"}
}