{
  "type": "Feature",
  "properties": {
    "gn:admin1_code":"06",
    "gn:asciiname":"Maar",
    "gn:country_code":"SS",
    "gn:dem":394,
    "gn:feature_class":"P",
    "gn:feature_code":"PPL",
    "gn:name":"Maar",
    "gn:population":0,
    "gn:timezone":"Africa/Juba",
    "iso:country":"SS",
    "name:ara_x_preferred":[
        "\u0641\u0648\u0647\u0629 \u0627\u0644\u0628\u0631\u0643\u0627\u0646"
    ],
    "name:ast_x_preferred":[
        "Maar"
    ],
    "name:aze_x_preferred":[
        "Maar"
    ],
    "name:bel_x_preferred":[
        "\u041c\u0430\u0430\u0440"
    ],
    "name:cat_x_preferred":[
        "Maar"
    ],
    "name:ces_x_preferred":[
        "Maar"
    ],
    "name:dan_x_preferred":[
        "Maar"
    ],
    "name:deu_x_preferred":[
        "Maar"
    ],
    "name:ell_x_preferred":[
        "\u039c\u03ac\u03b1\u03c1"
    ],
    "name:epo_x_preferred":[
        "Malprofunda kratero"
    ],
    "name:est_x_preferred":[
        "Maar"
    ],
    "name:eus_x_preferred":[
        "Maar"
    ],
    "name:fas_x_preferred":[
        "\u0622\u0628\u200c\u062f\u0647\u0627\u0646\u0647"
    ],
    "name:fin_x_preferred":[
        "Maari"
    ],
    "name:fra_x_preferred":[
        "Maar"
    ],
    "name:heb_x_preferred":[
        "\u05de\u05d0\u05e8"
    ],
    "name:hrv_x_preferred":[
        "Maar"
    ],
    "name:hun_x_preferred":[
        "Maar"
    ],
    "name:ind_x_preferred":[
        "Maar"
    ],
    "name:isl_x_preferred":[
        "Sprengig\u00edgur"
    ],
    "name:ita_x_preferred":[
        "Maar"
    ],
    "name:jpn_x_preferred":[
        "\u30de\u30fc\u30eb"
    ],
    "name:kat_x_preferred":[
        "\u10db\u10d0\u10d0\u10e0\u10d8"
    ],
    "name:kaz_x_preferred":[
        "\u041c\u0430\u0430\u0440"
    ],
    "name:kir_x_preferred":[
        "\u041c\u0430\u0430\u0440"
    ],
    "name:lav_x_preferred":[
        "M\u0101rs"
    ],
    "name:nld_x_preferred":[
        "Maar"
    ],
    "name:nno_x_preferred":[
        "Maar"
    ],
    "name:nor_x_preferred":[
        "Maar"
    ],
    "name:pol_x_preferred":[
        "Maar"
    ],
    "name:por_x_preferred":[
        "Maar"
    ],
    "name:ron_x_preferred":[
        "Maar"
    ],
    "name:rus_x_preferred":[
        "\u041c\u0430\u0430\u0440"
    ],
    "name:slk_x_preferred":[
        "Maar"
    ],
    "name:slv_x_preferred":[
        "Maar"
    ],
    "name:spa_x_preferred":[
        "Maar"
    ],
    "name:swe_x_preferred":[
        "Maar"
    ],
    "name:tur_x_preferred":[
        "Maar"
    ],
    "name:ukr_x_preferred":[
        "\u041c\u0430\u0430\u0440"
    ],
    "name:xmf_x_preferred":[
        "\u10db\u10d0\u10d0\u10e0\u10d8"
    ],
    "name:zho_x_preferred":[
        "\u4f4e\u5e73\u706b\u5c71\u53e3"
    ],
    "wof:lang_x_official":[
        "eng"
    ],
    "wof:lang_x_spoken":[
        "eng"
    ],
    "wof:name":"Maar",
    "wof:placetype":"locality"
},
  "geometry": {"coordinates":[29.9745,8.54016],"type":"Point"}
}