{
  "type": "Feature",
  "properties": {
    "gn:admin1_code":"01",
    "gn:asciiname":"Jabur",
    "gn:country_code":"SS",
    "gn:dem":467,
    "gn:feature_class":"P",
    "gn:feature_code":"PPL",
    "gn:name":"Jabur",
    "gn:population":0,
    "gn:timezone":"Africa/Juba",
    "iso:country":"SS",
    "name:msa_x_preferred":[
        "Jabur"
    ],
    "wof:name":"Jabur",
    "wof:placetype":"locality"
},
  "geometry": {"coordinates":[31.89379000000001,5.03888],"type":"Point"}
}