{
  "type": "Feature",
  "properties": {
    "gn:admin1_code":"04",
    "gn:asciiname":"Malwal",
    "gn:country_code":"SS",
    "gn:dem":446,
    "gn:feature_class":"P",
    "gn:feature_code":"PPL",
    "gn:name":"Malwal",
    "gn:population":0,
    "gn:timezone":"Africa/Juba",
    "iso:country":"SS",
    "wof:name":"Malwal",
    "wof:placetype":"locality"
},
  "geometry": {"coordinates":[29.76558,6.5939],"type":"Point"}
}