{
  "type": "Feature",
  "properties": {
    "gn:admin1_code":"05",
    "gn:asciiname":"Kanuk",
    "gn:country_code":"SS",
    "gn:dem":407,
    "gn:feature_class":"P",
    "gn:feature_code":"PPL",
    "gn:name":"Kanuk",
    "gn:population":0,
    "gn:timezone":"Africa/Juba",
    "iso:country":"SS",
    "wof:name":"Kanuk",
    "wof:placetype":"locality"
},
  "geometry": {"coordinates":[28.11956,9.04876],"type":"Point"}
}