{
  "type": "Feature",
  "properties": {
    "gn:admin1_code":"02",
    "gn:asciiname":"Leriok",
    "gn:country_code":"SS",
    "gn:dem":817,
    "gn:feature_class":"P",
    "gn:feature_code":"PPL",
    "gn:name":"Leriok",
    "gn:population":0,
    "gn:timezone":"Africa/Juba",
    "iso:country":"SS",
    "wof:name":"Leriok",
    "wof:placetype":"locality"
},
  "geometry": {"coordinates":[33.24089,4.07772],"type":"Point"}
}