{
  "type": "Feature",
  "properties": {
    "gn:admin1_code":"07",
    "gn:asciiname":"Malek",
    "gn:country_code":"SS",
    "gn:dem":408,
    "gn:feature_class":"P",
    "gn:feature_code":"PPL",
    "gn:name":"Malek",
    "gn:population":0,
    "gn:timezone":"Africa/Juba",
    "iso:country":"SS",
    "wof:name":"Malek",
    "wof:placetype":"locality"
},
  "geometry": {"coordinates":[33.71384,8.67645],"type":"Point"}
}