{
  "type": "Feature",
  "properties": {
    "gn:admin1_code":"04",
    "gn:asciiname":"Shambe",
    "gn:country_code":"SS",
    "gn:dem":415,
    "gn:feature_class":"P",
    "gn:feature_code":"PPL",
    "gn:name":"Shambe",
    "gn:population":0,
    "gn:timezone":"Africa/Juba",
    "iso:country":"SS",
    "name:und_x_variant":[
        "Shambi",
        "Shambe"
    ],
    "wof:name":"Shambe",
    "wof:placetype":"locality"
},
  "geometry": {"coordinates":[30.77361,7.10472],"type":"Point"}
}