{
  "type": "Feature",
  "properties": {
    "gn:admin1_code":"04",
    "gn:asciiname":"Mokwi",
    "gn:country_code":"SS",
    "gn:dem":419,
    "gn:feature_class":"P",
    "gn:feature_code":"PPL",
    "gn:name":"Mokwi",
    "gn:population":0,
    "gn:timezone":"Africa/Juba",
    "iso:country":"SS",
    "wof:name":"Mokwi",
    "wof:placetype":"locality"
},
  "geometry": {"coordinates":[29.35272,7.17994],"type":"Point"}
}