{
  "type": "Feature",
  "properties": {
    "gn:admin1_code":"07",
    "gn:asciiname":"Pabodyet",
    "gn:country_code":"SS",
    "gn:dem":398,
    "gn:feature_class":"P",
    "gn:feature_code":"PPL",
    "gn:name":"Pabodyet",
    "gn:population":0,
    "gn:timezone":"Africa/Juba",
    "iso:country":"SS",
    "wof:name":"Pabodyet",
    "wof:placetype":"locality"
},
  "geometry": {"coordinates":[32.14771,9.66547],"type":"Point"}
}