{
  "type": "Feature",
  "properties": {
    "gn:admin1_code":"06",
    "gn:asciiname":"Abiemnom",
    "gn:country_code":"SS",
    "gn:dem":398,
    "gn:feature_class":"P",
    "gn:feature_code":"PPL",
    "gn:name":"Abiemnom",
    "gn:population":0,
    "gn:timezone":"Africa/Juba",
    "iso:country":"SS",
    "name:und_x_variant":[
        "Abemnom",
        "Abiemnom"
    ],
    "wof:name":"Abiemnom",
    "wof:placetype":"locality"
},
  "geometry": {"coordinates":[28.9032,9.33943],"type":"Point"}
}