{
  "type": "Feature",
  "properties": {
    "gn:admin1_code":"02",
    "gn:asciiname":"Makorro",
    "gn:country_code":"SS",
    "gn:dem":713,
    "gn:feature_class":"P",
    "gn:feature_code":"PPL",
    "gn:name":"Makorro",
    "gn:population":0,
    "gn:timezone":"Africa/Juba",
    "iso:country":"SS",
    "wof:name":"Makorro",
    "wof:placetype":"locality"
},
  "geometry": {"coordinates":[32.5503,4.20364],"type":"Point"}
}