{
  "type": "Feature",
  "properties": {
    "gn:admin1_code":"01",
    "gn:asciiname":"Guar",
    "gn:country_code":"SS",
    "gn:dem":496,
    "gn:feature_class":"P",
    "gn:feature_code":"PPL",
    "gn:name":"Guar",
    "gn:population":0,
    "gn:timezone":"Africa/Juba",
    "iso:country":"SS",
    "name:ara_x_preferred":[
        "\u0642\u0648\u0627\u0631 \u0631\u0628\u0627\u0639\u064a"
    ],
    "name:ast_x_preferred":[
        "Cyamopsis tetragonoloba"
    ],
    "name:cat_x_preferred":[
        "Cyamopsis tetragonoloba"
    ],
    "name:ceb_x_preferred":[
        "Cyamopsis tetragonoloba"
    ],
    "name:dan_x_preferred":[
        "Guarb\u00f8nne"
    ],
    "name:deu_x_preferred":[
        "Guarbohne"
    ],
    "name:epo_x_preferred":[
        "Guaro"
    ],
    "name:fas_x_preferred":[
        "\u06af\u0648\u0622\u0631"
    ],
    "name:fra_x_preferred":[
        "Cyamopsis tetragonoloba"
    ],
    "name:hin_x_preferred":[
        "\u0917\u094d\u0935\u093e\u0930"
    ],
    "name:hun_x_preferred":[
        "Csom\u00f3sbab"
    ],
    "name:jpn_x_preferred":[
        "\u30af\u30e9\u30b9\u30bf\u30de\u30e1"
    ],
    "name:kan_x_preferred":[
        "\u0c97\u0ccb\u0cb0\u0cbf\u0c95\u0cbe\u0caf\u0cbf"
    ],
    "name:lit_x_preferred":[
        "Kampuotoji pupen\u0117"
    ],
    "name:mal_x_preferred":[
        "\u0d15\u0d4a\u0d24\u0d4d\u0d24\u0d2e\u0d30"
    ],
    "name:mar_x_preferred":[
        "\u0917\u0935\u093e\u0930"
    ],
    "name:nld_x_preferred":[
        "Guarplant"
    ],
    "name:pan_x_preferred":[
        "\u0a17\u0a41\u0a06\u0a30\u0a3e"
    ],
    "name:pnb_x_preferred":[
        "\u06af\u0648\u0627\u0631\u0627"
    ],
    "name:pol_x_preferred":[
        "Cyamopsis tetragonoloba"
    ],
    "name:rus_x_preferred":[
        "\u0413\u0443\u0430\u0440"
    ],
    "name:san_x_preferred":[
        "\u0917\u094b\u0930\u093e\u0923\u0940"
    ],
    "name:snd_x_preferred":[
        "\u06af\u0626\u0627\u0631"
    ],
    "name:spa_x_preferred":[
        "Cyamopsis tetragonoloba"
    ],
    "name:swa_x_preferred":[
        "Mgwaru"
    ],
    "name:swe_x_preferred":[
        "Cyamopsis tetragonoloba"
    ],
    "name:tam_x_preferred":[
        "\u0b95\u0bca\u0ba4\u0bcd\u0ba4\u0bb5\u0bb0\u0bc8"
    ],
    "name:tel_x_preferred":[
        "\u0c17\u0c4b\u0c30\u0c41 \u0c1a\u0c3f\u0c15\u0c4d\u0c15\u0c41\u0c21\u0c41"
    ],
    "name:ukr_x_preferred":[
        "\u0413\u0443\u0430\u0440\u043e\u0432\u0438\u0439 \u0431\u0456\u0431"
    ],
    "name:vie_x_preferred":[
        "Cyamopsis tetragonoloba"
    ],
    "name:war_x_preferred":[
        "Cyamopsis tetragonoloba"
    ],
    "wof:name":"Guar",
    "wof:placetype":"locality"
},
  "geometry": {"coordinates":[30.52273,6.0271],"type":"Point"}
}