{
  "type": "Feature",
  "properties": {
    "gn:admin1_code":"01",
    "gn:asciiname":"Guar",
    "gn:country_code":"SS",
    "gn:dem":496,
    "gn:feature_class":"P",
    "gn:feature_code":"PPL",
    "gn:name":"Guar",
    "gn:population":0,
    "gn:timezone":"Africa/Juba",
    "iso:country":"SS",
    "wof:name":"Guar",
    "wof:placetype":"locality"
},
  "geometry": {"coordinates":[30.52273,6.0271],"type":"Point"}
}