{
  "type": "Feature",
  "properties": {
    "gn:admin1_code":"05",
    "gn:asciiname":"Ankwap",
    "gn:country_code":"SS",
    "gn:dem":432,
    "gn:feature_class":"P",
    "gn:feature_code":"PPL",
    "gn:name":"Ankwap",
    "gn:population":0,
    "gn:timezone":"Africa/Juba",
    "iso:country":"SS",
    "wof:name":"Ankwap",
    "wof:placetype":"locality"
},
  "geometry": {"coordinates":[27.19043,9.11284],"type":"Point"}
}