{
  "type": "Feature",
  "properties": {
    "gn:admin1_code":"06",
    "gn:asciiname":"Pakur",
    "gn:country_code":"SS",
    "gn:dem":397,
    "gn:feature_class":"P",
    "gn:feature_code":"PPL",
    "gn:name":"Pakur",
    "gn:population":0,
    "gn:timezone":"Africa/Juba",
    "iso:country":"SS",
    "name:bih_x_preferred":[
        "\u092a\u093e\u0915\u0941\u0921\u093c"
    ],
    "name:bpy_x_preferred":[
        "\u09aa\u09be\u0995\u09c1\u09b0"
    ],
    "name:ceb_x_preferred":[
        "P\u0101kaur"
    ],
    "name:fra_x_preferred":[
        "Pakur"
    ],
    "name:hif_x_preferred":[
        "Pakaur"
    ],
    "name:hin_x_preferred":[
        "\u092a\u093e\u0915\u0941\u0921\u093c"
    ],
    "name:ita_x_preferred":[
        "Pakur"
    ],
    "name:mar_x_preferred":[
        "\u092a\u093e\u0915\u0941\u0930"
    ],
    "name:mlg_x_preferred":[
        "Pakur"
    ],
    "name:msa_x_preferred":[
        "Pakaur"
    ],
    "name:nep_x_preferred":[
        "\u092a\u093e\u0915\u0941\u0921\u093c"
    ],
    "name:ori_x_preferred":[
        "\u0b2a\u0b15\u0b4c\u0b30"
    ],
    "name:pnb_x_preferred":[
        "\u067e\u0627\u06a9\u0648\u0691"
    ],
    "name:por_x_preferred":[
        "Pakaur"
    ],
    "name:san_x_preferred":[
        "\u092a\u093e\u0915\u0941\u0921"
    ],
    "name:spa_x_preferred":[
        "Pakur"
    ],
    "name:swe_x_preferred":[
        "Pakaur"
    ],
    "name:urd_x_preferred":[
        "\u067e\u0627\u06a9\u0691"
    ],
    "name:vie_x_preferred":[
        "Pakaur"
    ],
    "name:zho_x_preferred":[
        "\u5e15\u8003\u5c14"
    ],
    "wof:name":"Pakur",
    "wof:placetype":"locality"
},
  "geometry": {"coordinates":[29.78032,9.23704],"type":"Point"}
}