{
  "type": "Feature",
  "properties": {
    "gn:admin1_code":"04",
    "gn:asciiname":"Runchol",
    "gn:country_code":"SS",
    "gn:dem":444,
    "gn:feature_class":"P",
    "gn:feature_code":"PPL",
    "gn:name":"Runchol",
    "gn:population":0,
    "gn:timezone":"Africa/Juba",
    "iso:country":"SS",
    "wof:name":"Runchol",
    "wof:placetype":"locality"
},
  "geometry": {"coordinates":[29.89401,6.54334],"type":"Point"}
}