{
  "type": "Feature",
  "properties": {
    "gn:admin1_code":"02",
    "gn:asciiname":"Palataka",
    "gn:country_code":"SS",
    "gn:dem":959,
    "gn:feature_class":"P",
    "gn:feature_code":"PPL",
    "gn:name":"Palataka",
    "gn:population":0,
    "gn:timezone":"Africa/Juba",
    "iso:country":"SS",
    "wof:name":"Palataka",
    "wof:placetype":"locality"
},
  "geometry": {"coordinates":[32.45132,4.04776],"type":"Point"}
}