{
  "type": "Feature",
  "properties": {
    "gn:admin1_code":"02",
    "gn:asciiname":"Langera",
    "gn:country_code":"SS",
    "gn:dem":1473,
    "gn:feature_class":"P",
    "gn:feature_code":"PPL",
    "gn:name":"Langera",
    "gn:population":0,
    "gn:timezone":"Africa/Juba",
    "iso:country":"SS",
    "wof:name":"Langera",
    "wof:placetype":"locality"
},
  "geometry": {"coordinates":[33.49009,3.85124],"type":"Point"}
}