{
  "type": "Feature",
  "properties": {
    "gn:admin1_code":"05",
    "gn:asciiname":"Mashar",
    "gn:country_code":"SS",
    "gn:dem":429,
    "gn:feature_class":"P",
    "gn:feature_code":"PPL",
    "gn:name":"Mashar",
    "gn:population":0,
    "gn:timezone":"Africa/Juba",
    "iso:country":"SS",
    "wof:name":"Mashar",
    "wof:placetype":"locality"
},
  "geometry": {"coordinates":[27.29157,9.06982],"type":"Point"}
}