{
  "type": "Feature",
  "properties": {
    "gn:admin1_code":"08",
    "gn:asciiname":"Molau",
    "gn:country_code":"SS",
    "gn:dem":411,
    "gn:feature_class":"P",
    "gn:feature_code":"PPL",
    "gn:name":"Molau",
    "gn:population":0,
    "gn:timezone":"Africa/Juba",
    "iso:country":"SS",
    "wof:name":"Molau",
    "wof:placetype":"locality"
},
  "geometry": {"coordinates":[28.44515,7.89612],"type":"Point"}
}