{
  "type": "Feature",
  "properties": {
    "gn:admin1_code":"08",
    "gn:asciiname":"Molau",
    "gn:country_code":"SS",
    "gn:dem":411,
    "gn:feature_class":"P",
    "gn:feature_code":"PPL",
    "gn:name":"Molau",
    "gn:population":0,
    "gn:timezone":"Africa/Juba",
    "iso:country":"SS",
    "name:bak_x_preferred":[
        "\u041c\u043e\u043b\u0430\u0443"
    ],
    "name:ceb_x_preferred":[
        "Molau"
    ],
    "name:deu_x_preferred":[
        "Molau"
    ],
    "name:epo_x_preferred":[
        "Molau"
    ],
    "name:fas_x_preferred":[
        "\u0645\u0648\u0644\u0627\u0648"
    ],
    "name:ita_x_preferred":[
        "Molau"
    ],
    "name:kaz_x_preferred":[
        "\u041c\u043e\u043b\u0430\u0443"
    ],
    "name:kir_x_preferred":[
        "\u041c\u043e\u043b\u0430\u0443"
    ],
    "name:mkd_x_preferred":[
        "\u041c\u043e\u043b\u0430\u0443"
    ],
    "name:nld_x_preferred":[
        "Molau"
    ],
    "name:ron_x_preferred":[
        "Molau"
    ],
    "name:rus_x_preferred":[
        "\u041c\u043e\u043b\u0430\u0443"
    ],
    "name:uzb_x_preferred":[
        "Molau"
    ],
    "name:vie_x_preferred":[
        "Molau"
    ],
    "name:vol_x_preferred":[
        "Molau"
    ],
    "wof:lang_x_official":[
        "eng"
    ],
    "wof:lang_x_spoken":[
        "eng"
    ],
    "wof:name":"Molau",
    "wof:placetype":"locality"
},
  "geometry": {"coordinates":[28.44515,7.89612],"type":"Point"}
}