{
  "type": "Feature",
  "properties": {
    "gn:admin1_code":"04",
    "gn:asciiname":"Majeir",
    "gn:country_code":"SS",
    "gn:dem":445,
    "gn:feature_class":"P",
    "gn:feature_code":"PPL",
    "gn:name":"Majeir",
    "gn:population":0,
    "gn:timezone":"Africa/Juba",
    "iso:country":"SS",
    "wof:name":"Majeir",
    "wof:placetype":"locality"
},
  "geometry": {"coordinates":[30.34117,6.33167],"type":"Point"}
}