{
  "type": "Feature",
  "properties": {
    "gn:admin1_code":"08",
    "gn:asciiname":"N'Gab Kaich",
    "gn:country_code":"SS",
    "gn:dem":409,
    "gn:feature_class":"P",
    "gn:feature_code":"PPL",
    "gn:name":"N\u2019Gab Kaich",
    "gn:population":0,
    "gn:timezone":"Africa/Juba",
    "iso:country":"SS",
    "wof:name":"N'Gab Kaich",
    "wof:placetype":"locality"
},
  "geometry": {"coordinates":[28.01652,8.83747],"type":"Point"}
}