{
  "type": "Feature",
  "properties": {
    "gn:admin1_code":"07",
    "gn:asciiname":"Ryagdo",
    "gn:country_code":"SS",
    "gn:dem":395,
    "gn:feature_class":"P",
    "gn:feature_code":"PPL",
    "gn:name":"Ryagdo",
    "gn:population":0,
    "gn:timezone":"Africa/Juba",
    "iso:country":"SS",
    "wof:name":"Ryagdo",
    "wof:placetype":"locality"
},
  "geometry": {"coordinates":[32.14876,9.61699],"type":"Point"}
}