{
  "type": "Feature",
  "properties": {
    "gn:admin1_code":"04",
    "gn:asciiname":"Pagak",
    "gn:country_code":"SS",
    "gn:dem":424,
    "gn:feature_class":"P",
    "gn:feature_code":"PPL",
    "gn:name":"Pagak",
    "gn:population":0,
    "gn:timezone":"Africa/Juba",
    "iso:country":"SS",
    "wof:name":"Pagak",
    "wof:placetype":"locality"
},
  "geometry": {"coordinates":[31.3532,6.38877],"type":"Point"}
}