{
  "type": "Feature",
  "properties": {
    "gn:admin1_code":"03",
    "gn:asciiname":"Mangong",
    "gn:country_code":"SS",
    "gn:dem":413,
    "gn:feature_class":"P",
    "gn:feature_code":"PPL",
    "gn:name":"Mangong",
    "gn:population":0,
    "gn:timezone":"Africa/Juba",
    "iso:country":"SS",
    "name:kor_x_preferred":[
        "\ub9cc\uacf5"
    ],
    "name:pol_x_preferred":[
        "Mangong W\u014flmy\u014fn"
    ],
    "name:rus_x_preferred":[
        "\u041c\u0430\u043d\u0433\u043e\u043d"
    ],
    "wof:lang_x_official":[
        "eng"
    ],
    "wof:lang_x_spoken":[
        "eng"
    ],
    "wof:name":"Mangong",
    "wof:placetype":"locality"
},
  "geometry": {"coordinates":[32.87260999999999,7.69691],"type":"Point"}
}