{
  "type": "Feature",
  "properties": {
    "gn:admin1_code":"04",
    "gn:asciiname":"Aroping",
    "gn:country_code":"SS",
    "gn:dem":430,
    "gn:feature_class":"P",
    "gn:feature_code":"PPL",
    "gn:name":"Aroping",
    "gn:population":0,
    "gn:timezone":"Africa/Juba",
    "iso:country":"SS",
    "wof:name":"Aroping",
    "wof:placetype":"locality"
},
  "geometry": {"coordinates":[29.96482,6.76352],"type":"Point"}
}