{
  "type": "Feature",
  "properties": {
    "gn:admin1_code":"08",
    "gn:asciiname":"Nyet",
    "gn:country_code":"SS",
    "gn:dem":408,
    "gn:feature_class":"P",
    "gn:feature_code":"PPL",
    "gn:name":"Nyet",
    "gn:population":0,
    "gn:timezone":"Africa/Juba",
    "iso:country":"SS",
    "wof:name":"Nyet",
    "wof:placetype":"locality"
},
  "geometry": {"coordinates":[28.298,8.88434],"type":"Point"}
}