{
  "type": "Feature",
  "properties": {
    "gn:admin1_code":"01",
    "gn:asciiname":"Perisak",
    "gn:country_code":"SS",
    "gn:dem":669,
    "gn:feature_class":"P",
    "gn:feature_code":"PPL",
    "gn:name":"Perisak",
    "gn:population":0,
    "gn:timezone":"Africa/Juba",
    "iso:country":"SS",
    "wof:name":"Perisak",
    "wof:placetype":"locality"
},
  "geometry": {"coordinates":[31.27143,4.4988],"type":"Point"}
}