{
  "type": "Feature",
  "properties": {
    "gn:admin1_code":"01",
    "gn:asciiname":"Aiyon",
    "gn:country_code":"SS",
    "gn:dem":486,
    "gn:feature_class":"P",
    "gn:feature_code":"PPL",
    "gn:name":"Aiyon",
    "gn:population":0,
    "gn:timezone":"Africa/Juba",
    "iso:country":"SS",
    "wof:name":"Aiyon",
    "wof:placetype":"locality"
},
  "geometry": {"coordinates":[30.3609,6.08323],"type":"Point"}
}