{
  "type": "Feature",
  "properties": {
    "gn:admin1_code":"08",
    "gn:asciiname":"Malwal",
    "gn:country_code":"SS",
    "gn:dem":419,
    "gn:feature_class":"P",
    "gn:feature_code":"PPL",
    "gn:name":"Malwal",
    "gn:population":0,
    "gn:timezone":"Africa/Juba",
    "iso:country":"SS",
    "wof:name":"Malwal",
    "wof:placetype":"locality"
},
  "geometry": {"coordinates":[27.93588,8.37661],"type":"Point"}
}