{
  "type": "Feature",
  "properties": {
    "gn:admin1_code":"08",
    "gn:asciiname":"Gul",
    "gn:country_code":"SS",
    "gn:dem":415,
    "gn:feature_class":"P",
    "gn:feature_code":"PPL",
    "gn:name":"Gul",
    "gn:population":0,
    "gn:timezone":"Africa/Juba",
    "iso:country":"SS",
    "wof:name":"Gul",
    "wof:placetype":"locality"
},
  "geometry": {"coordinates":[27.95901,8.64467],"type":"Point"}
}