{
  "type": "Feature",
  "properties": {
    "gn:admin1_code":"10",
    "gn:asciiname":"Logo",
    "gn:country_code":"SS",
    "gn:dem":565,
    "gn:feature_class":"P",
    "gn:feature_code":"PPL",
    "gn:name":"Logo",
    "gn:population":0,
    "gn:timezone":"Africa/Juba",
    "iso:country":"SS",
    "wof:name":"Logo",
    "wof:placetype":"locality"
},
  "geometry": {"coordinates":[30.31271,5.35114],"type":"Point"}
}