{
  "type": "Feature",
  "properties": {
    "gn:admin1_code":"05",
    "gn:asciiname":"Kira",
    "gn:country_code":"SS",
    "gn:dem":563,
    "gn:feature_class":"P",
    "gn:feature_code":"PPL",
    "gn:name":"Kira",
    "gn:population":0,
    "gn:timezone":"Africa/Juba",
    "iso:country":"SS",
    "wof:name":"Kira",
    "wof:placetype":"locality"
},
  "geometry": {"coordinates":[26.35631,8.52958],"type":"Point"}
}