{
  "type": "Feature",
  "properties": {
    "gn:admin1_code":"01",
    "gn:asciiname":"Tikasu",
    "gn:country_code":"SS",
    "gn:dem":856,
    "gn:feature_class":"P",
    "gn:feature_code":"PPL",
    "gn:name":"Tikasu",
    "gn:population":0,
    "gn:timezone":"Africa/Juba",
    "iso:country":"SS",
    "wof:name":"Tikasu",
    "wof:placetype":"locality"
},
  "geometry": {"coordinates":[30.75035,4.12958],"type":"Point"}
}