{
  "type": "Feature",
  "properties": {
    "gn:admin1_code":"02",
    "gn:asciiname":"Logirim",
    "gn:country_code":"SS",
    "gn:dem":612,
    "gn:feature_class":"P",
    "gn:feature_code":"PPL",
    "gn:name":"Logirim",
    "gn:population":0,
    "gn:timezone":"Africa/Juba",
    "iso:country":"SS",
    "wof:name":"Logirim",
    "wof:placetype":"locality"
},
  "geometry": {"coordinates":[33.24121,4.72276],"type":"Point"}
}