{
  "type": "Feature",
  "properties": {
    "gn:admin1_code":"05",
    "gn:asciiname":"Mayom",
    "gn:country_code":"SS",
    "gn:dem":443,
    "gn:feature_class":"P",
    "gn:feature_code":"PPL",
    "gn:name":"Mayom",
    "gn:population":0,
    "gn:timezone":"Africa/Juba",
    "iso:country":"SS",
    "wof:name":"Mayom",
    "wof:placetype":"locality"
},
  "geometry": {"coordinates":[26.93335,9.17976],"type":"Point"}
}