{
  "type": "Feature",
  "properties": {
    "gn:admin1_code":"08",
    "gn:asciiname":"Duk Yoak",
    "gn:country_code":"SS",
    "gn:dem":436,
    "gn:feature_class":"P",
    "gn:feature_code":"PPL",
    "gn:name":"Duk Yoak",
    "gn:population":0,
    "gn:timezone":"Africa/Juba",
    "iso:country":"SS",
    "wof:name":"Duk Yoak",
    "wof:placetype":"locality"
},
  "geometry": {"coordinates":[28.44932,7.44647],"type":"Point"}
}