{
  "type": "Feature",
  "properties": {
    "gn:admin1_code":"03",
    "gn:asciiname":"Pieri",
    "gn:country_code":"SS",
    "gn:dem":411,
    "gn:feature_class":"P",
    "gn:feature_code":"PPL",
    "gn:name":"Pieri",
    "gn:population":0,
    "gn:timezone":"Africa/Juba",
    "iso:country":"SS",
    "name:deu_x_preferred":[
        "Pieri"
    ],
    "name:fra_x_preferred":[
        "Pieri"
    ],
    "name:ita_x_preferred":[
        "Pieri"
    ],
    "name:rus_x_preferred":[
        "\u041f\u044c\u0435\u0440\u0438"
    ],
    "name:spa_x_preferred":[
        "Pieri"
    ],
    "wof:name":"Pieri",
    "wof:placetype":"locality"
},
  "geometry": {"coordinates":[32.03333,8.03333],"type":"Point"}
}