{
  "type": "Feature",
  "properties": {
    "gn:admin1_code":"07",
    "gn:asciiname":"Teday",
    "gn:country_code":"SS",
    "gn:dem":391,
    "gn:feature_class":"P",
    "gn:feature_code":"PPL",
    "gn:name":"Teday",
    "gn:population":0,
    "gn:timezone":"Africa/Juba",
    "iso:country":"SS",
    "name:und_x_variant":[
        "Tedau"
    ],
    "wof:name":"Teday",
    "wof:placetype":"locality"
},
  "geometry": {"coordinates":[32.49926,10.34344],"type":"Point"}
}