{
  "type": "Feature",
  "properties": {
    "gn:admin1_code":"10",
    "gn:asciiname":"Dimo",
    "gn:country_code":"SS",
    "gn:dem":678,
    "gn:feature_class":"P",
    "gn:feature_code":"PPL",
    "gn:name":"Dimo",
    "gn:population":0,
    "gn:timezone":"Africa/Juba",
    "iso:country":"SS",
    "name:ceb_x_preferred":[
        "Dimo"
    ],
    "name:deu_x_preferred":[
        "Dimo"
    ],
    "name:fra_x_preferred":[
        "Dimo"
    ],
    "name:ita_x_preferred":[
        "Dimo"
    ],
    "name:swe_x_preferred":[
        "Dimo"
    ],
    "wof:lang_x_official":[
        "eng"
    ],
    "wof:lang_x_spoken":[
        "eng"
    ],
    "wof:name":"Dimo",
    "wof:placetype":"locality"
},
  "geometry": {"coordinates":[29.14111,5.21694],"type":"Point"}
}