{
  "type": "Feature",
  "properties": {
    "gn:admin1_code":"08",
    "gn:asciiname":"Ajak",
    "gn:country_code":"SS",
    "gn:dem":415,
    "gn:feature_class":"P",
    "gn:feature_code":"PPL",
    "gn:name":"Ajak",
    "gn:population":0,
    "gn:timezone":"Africa/Juba",
    "iso:country":"SS",
    "name:fas_x_preferred":[
        "\u0627\u062c\u06a9"
    ],
    "name:fra_x_preferred":[
        "Ajak"
    ],
    "name:hun_x_preferred":[
        "Ajak"
    ],
    "name:ita_x_preferred":[
        "Ajak"
    ],
    "name:und_x_variant":[
        "Ajako"
    ],
    "name:vie_x_preferred":[
        "Ajak"
    ],
    "wof:name":"Ajak",
    "wof:placetype":"locality"
},
  "geometry": {"coordinates":[28.70291,7.65436],"type":"Point"}
}