{
  "type": "Feature",
  "properties": {
    "gn:admin1_code":"08",
    "gn:asciiname":"Adir",
    "gn:country_code":"SS",
    "gn:dem":418,
    "gn:feature_class":"P",
    "gn:feature_code":"PPL",
    "gn:name":"Adir",
    "gn:population":0,
    "gn:timezone":"Africa/Juba",
    "iso:country":"SS",
    "name:heb_x_preferred":[
        "\u05d0\u05d3\u05d9\u05e8"
    ],
    "wof:name":"Adir",
    "wof:placetype":"locality"
},
  "geometry": {"coordinates":[27.91881,8.51273],"type":"Point"}
}