{
  "type": "Feature",
  "properties": {
    "gn:admin1_code":"03",
    "gn:asciiname":"Kongettit",
    "gn:country_code":"SS",
    "gn:dem":417,
    "gn:feature_class":"P",
    "gn:feature_code":"PPL",
    "gn:name":"Kongettit",
    "gn:population":0,
    "gn:timezone":"Africa/Juba",
    "iso:country":"SS",
    "wof:name":"Kongettit",
    "wof:placetype":"locality"
},
  "geometry": {"coordinates":[32.81488,7.45813],"type":"Point"}
}