{
  "type": "Feature",
  "properties": {
    "gn:admin1_code":"04",
    "gn:asciiname":"Achwer",
    "gn:country_code":"SS",
    "gn:dem":416,
    "gn:feature_class":"P",
    "gn:feature_code":"PPL",
    "gn:name":"Achwer",
    "gn:population":0,
    "gn:timezone":"Africa/Juba",
    "iso:country":"SS",
    "wof:name":"Achwer",
    "wof:placetype":"locality"
},
  "geometry": {"coordinates":[30.22026,7.00563],"type":"Point"}
}