{
  "type": "Feature",
  "properties": {
    "gn:admin1_code":"04",
    "gn:asciiname":"Pul Akot",
    "gn:country_code":"SS",
    "gn:dem":417,
    "gn:feature_class":"P",
    "gn:feature_code":"PPL",
    "gn:name":"Pul Akot",
    "gn:population":0,
    "gn:timezone":"Africa/Juba",
    "iso:country":"SS",
    "wof:name":"Pul Akot",
    "wof:placetype":"locality"
},
  "geometry": {"coordinates":[30.41176,7.02424],"type":"Point"}
}