{
  "type": "Feature",
  "properties": {
    "gn:admin1_code":"04",
    "gn:asciiname":"Gel Riwer",
    "gn:country_code":"SS",
    "gn:dem":427,
    "gn:feature_class":"P",
    "gn:feature_code":"PPL",
    "gn:name":"Gel Riwer",
    "gn:population":0,
    "gn:timezone":"Africa/Juba",
    "iso:country":"SS",
    "wof:name":"Gel Riwer",
    "wof:placetype":"locality"
},
  "geometry": {"coordinates":[29.12007,7.03731],"type":"Point"}
}