{
  "type": "Feature",
  "properties": {
    "gn:admin1_code":"10",
    "gn:asciiname":"Sheikh Mulai",
    "gn:country_code":"SS",
    "gn:dem":731,
    "gn:feature_class":"P",
    "gn:feature_code":"PPL",
    "gn:name":"Sheikh Mulai",
    "gn:population":0,
    "gn:timezone":"Africa/Juba",
    "iso:country":"SS",
    "name:und_x_variant":[
        "Shaykh Mawl\u0101\u2019\u012b",
        "Shaykh Mulai"
    ],
    "wof:name":"Sheikh Mulai",
    "wof:placetype":"locality"
},
  "geometry": {"coordinates":[30.71938,4.9475],"type":"Point"}
}