{
  "type": "Feature",
  "properties": {
    "gn:admin1_code":"01",
    "gn:asciiname":"Moggi",
    "gn:country_code":"SS",
    "gn:dem":458,
    "gn:feature_class":"P",
    "gn:feature_code":"PPL",
    "gn:name":"Moggi",
    "gn:population":0,
    "gn:timezone":"Africa/Juba",
    "iso:country":"SS",
    "wof:name":"Moggi",
    "wof:placetype":"locality"
},
  "geometry": {"coordinates":[31.14576,5.77249],"type":"Point"}
}