{
  "type": "Feature",
  "properties": {
    "gn:admin1_code":"10",
    "gn:asciiname":"Manum",
    "gn:country_code":"SS",
    "gn:dem":714,
    "gn:feature_class":"P",
    "gn:feature_code":"PPL",
    "gn:name":"Manum",
    "gn:population":0,
    "gn:timezone":"Africa/Juba",
    "iso:country":"SS",
    "wof:name":"Manum",
    "wof:placetype":"locality"
},
  "geometry": {"coordinates":[29.78359,4.80753],"type":"Point"}
}