{
  "type": "Feature",
  "properties": {
    "gn:admin1_code":"07",
    "gn:asciiname":"Khanfariyya",
    "gn:country_code":"SS",
    "gn:dem":388,
    "gn:feature_class":"P",
    "gn:feature_code":"PPL",
    "gn:name":"Khanfariyya",
    "gn:population":0,
    "gn:timezone":"Africa/Juba",
    "iso:country":"SS",
    "wof:name":"Khanfariyya",
    "wof:placetype":"locality"
},
  "geometry": {"coordinates":[32.8597,12.0609],"type":"Point"}
}