{
  "type": "Feature",
  "properties": {
    "gn:admin1_code":"03",
    "gn:asciiname":"Kan",
    "gn:country_code":"SS",
    "gn:dem":398,
    "gn:feature_class":"P",
    "gn:feature_code":"PPL",
    "gn:name":"Kan",
    "gn:population":0,
    "gn:timezone":"Africa/Juba",
    "iso:country":"SS",
    "wof:name":"Kan",
    "wof:placetype":"locality"
},
  "geometry": {"coordinates":[31.76304,9.0137],"type":"Point"}
}