{
  "type": "Feature",
  "properties": {
    "gn:admin1_code":"05",
    "gn:asciiname":"Akwanalan",
    "gn:country_code":"SS",
    "gn:dem":437,
    "gn:feature_class":"P",
    "gn:feature_code":"PPL",
    "gn:name":"Akwanalan",
    "gn:population":0,
    "gn:timezone":"Africa/Juba",
    "iso:country":"SS",
    "wof:name":"Akwanalan",
    "wof:placetype":"locality"
},
  "geometry": {"coordinates":[27.05434,9.15195],"type":"Point"}
}