{
  "type": "Feature",
  "properties": {
    "gn:admin1_code":"11550580",
    "gn:asciiname":"Ayod",
    "gn:country_code":"SS",
    "gn:dem":411,
    "gn:feature_class":"P",
    "gn:feature_code":"PPLA",
    "gn:name":"Ayod",
    "gn:population":0,
    "gn:timezone":"Africa/Juba",
    "iso:country":"SS",
    "name:fra_x_preferred":[
        "Ayod"
    ],
    "name:por_x_preferred":[
        "Ayod"
    ],
    "name:und_x_variant":[
        "Duk Ayod",
        "Duk Yod",
        "Ayod"
    ],
    "wof:name":"Ayod",
    "wof:placetype":"locality"
},
  "geometry": {"coordinates":[31.40904,8.12193],"type":"Point"}
}