{
  "type": "Feature",
  "properties": {
    "gn:admin1_code":"09",
    "gn:asciiname":"Abu Kirsh",
    "gn:country_code":"SS",
    "gn:dem":471,
    "gn:feature_class":"P",
    "gn:feature_code":"PPL",
    "gn:name":"Abu Kirsh",
    "gn:population":0,
    "gn:timezone":"Africa/Juba",
    "iso:country":"SS",
    "name:und_x_variant":[
        "Ab\u016b Kirsh"
    ],
    "wof:name":"Abu Kirsh",
    "wof:placetype":"locality"
},
  "geometry": {"coordinates":[27.4435,8.17257],"type":"Point"}
}