{
  "type": "Feature",
  "properties": {
    "gn:admin1_code":"08",
    "gn:asciiname":"Win",
    "gn:country_code":"SS",
    "gn:dem":411,
    "gn:feature_class":"P",
    "gn:feature_code":"PPL",
    "gn:name":"Win",
    "gn:population":0,
    "gn:timezone":"Africa/Juba",
    "iso:country":"SS",
    "name:fra_x_preferred":[
        "Win"
    ],
    "name:pol_x_preferred":[
        "Win"
    ],
    "wof:name":"Win",
    "wof:placetype":"locality"
},
  "geometry": {"coordinates":[28.11431,8.92933],"type":"Point"}
}