{
  "type": "Feature",
  "properties": {
    "gn:admin1_code":"01",
    "gn:asciiname":"Singi",
    "gn:country_code":"SS",
    "gn:dem":485,
    "gn:feature_class":"P",
    "gn:feature_code":"PPL",
    "gn:name":"Singi",
    "gn:population":0,
    "gn:timezone":"Africa/Juba",
    "iso:country":"SS",
    "name:deu_x_preferred":[
        "Singi"
    ],
    "name:nor_x_preferred":[
        "Singi"
    ],
    "name:swe_x_preferred":[
        "Singi"
    ],
    "wof:lang_x_official":[
        "eng"
    ],
    "wof:lang_x_spoken":[
        "eng"
    ],
    "wof:name":"Singi",
    "wof:placetype":"locality"
},
  "geometry": {"coordinates":[31.76936,4.86278],"type":"Point"}
}