{
  "type": "Feature",
  "properties": {
    "gn:admin1_code":"07",
    "gn:asciiname":"Panomdojop",
    "gn:country_code":"SS",
    "gn:dem":408,
    "gn:feature_class":"P",
    "gn:feature_code":"PPL",
    "gn:name":"Panomdojop",
    "gn:population":0,
    "gn:timezone":"Africa/Juba",
    "iso:country":"SS",
    "wof:name":"Panomdojop",
    "wof:placetype":"locality"
},
  "geometry": {"coordinates":[33.59802,8.68683],"type":"Point"}
}