{
  "type": "Feature",
  "properties": {
    "gn:admin1_code":"10",
    "gn:asciiname":"Naguga",
    "gn:country_code":"SS",
    "gn:dem":702,
    "gn:feature_class":"P",
    "gn:feature_code":"PPL",
    "gn:name":"Naguga",
    "gn:population":0,
    "gn:timezone":"Africa/Juba",
    "iso:country":"SS",
    "wof:name":"Naguga",
    "wof:placetype":"locality"
},
  "geometry": {"coordinates":[29.27056,4.85556],"type":"Point"}
}