{
  "type": "Feature",
  "properties": {
    "gn:admin1_code":"03",
    "gn:asciiname":"Lil",
    "gn:country_code":"SS",
    "gn:dem":400,
    "gn:feature_class":"P",
    "gn:feature_code":"PPL",
    "gn:name":"Lil",
    "gn:population":0,
    "gn:timezone":"Africa/Juba",
    "iso:country":"SS",
    "wof:name":"Lil",
    "wof:placetype":"locality"
},
  "geometry": {"coordinates":[30.68242,9.06066],"type":"Point"}
}