{
  "type": "Feature",
  "properties": {
    "gn:admin1_code":"04",
    "gn:asciiname":"Wantok",
    "gn:country_code":"SS",
    "gn:dem":422,
    "gn:feature_class":"P",
    "gn:feature_code":"PPL",
    "gn:name":"Wantok",
    "gn:population":0,
    "gn:timezone":"Africa/Juba",
    "iso:country":"SS",
    "wof:name":"Wantok",
    "wof:placetype":"locality"
},
  "geometry": {"coordinates":[29.68449,6.82186],"type":"Point"}
}