{
  "type": "Feature",
  "properties": {
    "gn:admin1_code":"06",
    "gn:asciiname":"Fanial",
    "gn:country_code":"SS",
    "gn:dem":408,
    "gn:feature_class":"P",
    "gn:feature_code":"PPL",
    "gn:name":"Fanial",
    "gn:population":0,
    "gn:timezone":"Africa/Juba",
    "iso:country":"SS",
    "name:und_x_variant":[
        "Panial",
        "Fanial"
    ],
    "wof:name":"Fanial",
    "wof:placetype":"locality"
},
  "geometry": {"coordinates":[30.41799,7.39192],"type":"Point"}
}