{
  "type": "Feature",
  "properties": {
    "gn:admin1_code":"05",
    "gn:asciiname":"Fan Fort",
    "gn:country_code":"SS",
    "gn:dem":423,
    "gn:feature_class":"P",
    "gn:feature_code":"PPL",
    "gn:name":"Fan Fort",
    "gn:population":0,
    "gn:timezone":"Africa/Juba",
    "iso:country":"SS",
    "wof:name":"Fan Fort",
    "wof:placetype":"locality"
},
  "geometry": {"coordinates":[27.53469,9.00559],"type":"Point"}
}