{
  "type": "Feature",
  "properties": {
    "gn:admin1_code":"02",
    "gn:asciiname":"Issore",
    "gn:country_code":"SS",
    "gn:dem":1569,
    "gn:feature_class":"P",
    "gn:feature_code":"PPL",
    "gn:name":"Issore",
    "gn:population":0,
    "gn:timezone":"Africa/Juba",
    "iso:country":"SS",
    "wof:name":"Issore",
    "wof:placetype":"locality"
},
  "geometry": {"coordinates":[32.79544,3.91044],"type":"Point"}
}