{
  "type": "Feature",
  "properties": {
    "gn:admin1_code":"06",
    "gn:asciiname":"Bol",
    "gn:country_code":"SS",
    "gn:dem":411,
    "gn:feature_class":"P",
    "gn:feature_code":"PPL",
    "gn:name":"Bol",
    "gn:population":0,
    "gn:timezone":"Africa/Juba",
    "iso:country":"SS",
    "name:bel_x_preferred":[
        "\u0411\u043e\u043b"
    ],
    "name:bos_x_preferred":[
        "Bol"
    ],
    "name:ceb_x_preferred":[
        "Bol"
    ],
    "name:dan_x_preferred":[
        "B\u00f8l"
    ],
    "name:deu_x_preferred":[
        "Bol"
    ],
    "name:fin_x_preferred":[
        "Bol"
    ],
    "name:fra_x_preferred":[
        "Bol"
    ],
    "name:hrv_x_preferred":[
        "Bol"
    ],
    "name:hye_x_preferred":[
        "\u0532\u0578\u056c"
    ],
    "name:nld_x_preferred":[
        "Bol"
    ],
    "name:nor_x_preferred":[
        "Bol"
    ],
    "name:oss_x_preferred":[
        "\u0411\u043e\u043b"
    ],
    "name:pol_x_preferred":[
        "Bol"
    ],
    "name:rus_x_preferred":[
        "\u0411\u043e\u043b"
    ],
    "name:slk_x_preferred":[
        "Bol"
    ],
    "name:swe_x_preferred":[
        "Bol"
    ],
    "name:ukr_x_preferred":[
        "\u0411\u043e\u043b"
    ],
    "wof:lang_x_official":[
        "eng"
    ],
    "wof:lang_x_spoken":[
        "eng"
    ],
    "wof:name":"Bol",
    "wof:placetype":"locality"
},
  "geometry": {"coordinates":[30.51667,7.33333],"type":"Point"}
}