{
  "type": "Feature",
  "properties": {
    "gn:admin1_code":"02",
    "gn:asciiname":"Sultan Saroor",
    "gn:country_code":"SS",
    "gn:dem":656,
    "gn:feature_class":"P",
    "gn:feature_code":"PPL",
    "gn:name":"Sultan Saroor",
    "gn:population":0,
    "gn:timezone":"Africa/Juba",
    "iso:country":"SS",
    "name:und_x_variant":[
        "Sul\u0163\u0101n Sar\u016br"
    ],
    "wof:name":"Sultan Saroor",
    "wof:placetype":"locality"
},
  "geometry": {"coordinates":[32.08174,3.59574],"type":"Point"}
}