{
  "type": "Feature",
  "properties": {
    "gn:admin1_code":"09",
    "gn:asciiname":"Goin",
    "gn:country_code":"SS",
    "gn:dem":481,
    "gn:feature_class":"P",
    "gn:feature_code":"PPL",
    "gn:name":"Goin",
    "gn:population":0,
    "gn:timezone":"Africa/Juba",
    "iso:country":"SS",
    "name:deu_x_preferred":[
        "Goin"
    ],
    "name:fra_x_preferred":[
        "Goin"
    ],
    "name:pol_x_preferred":[
        "Goin"
    ],
    "name:swe_x_preferred":[
        "Goin"
    ],
    "name:ukr_x_preferred":[
        "\u0413\u0443\u0435\u043d"
    ],
    "wof:lang_x_official":[
        "eng"
    ],
    "wof:lang_x_spoken":[
        "eng"
    ],
    "wof:name":"Goin",
    "wof:placetype":"locality"
},
  "geometry": {"coordinates":[27.50681,8.2583],"type":"Point"}
}