{
  "type": "Feature",
  "properties": {
    "gn:admin1_code":"02",
    "gn:asciiname":"Ayum",
    "gn:country_code":"SS",
    "gn:dem":785,
    "gn:feature_class":"P",
    "gn:feature_code":"PPL",
    "gn:name":"Ayum",
    "gn:population":0,
    "gn:timezone":"Africa/Juba",
    "iso:country":"SS",
    "wof:name":"Ayum",
    "wof:placetype":"locality"
},
  "geometry": {"coordinates":[32.12884,4.03113],"type":"Point"}
}