{
  "type": "Feature",
  "properties": {
    "gn:admin1_code":"07",
    "gn:asciiname":"El Watish",
    "gn:country_code":"SS",
    "gn:dem":476,
    "gn:feature_class":"P",
    "gn:feature_code":"PPL",
    "gn:name":"El Watish",
    "gn:population":0,
    "gn:timezone":"Africa/Juba",
    "iso:country":"SS",
    "wof:name":"El Watish",
    "wof:placetype":"locality"
},
  "geometry": {"coordinates":[33.70826,10.28716],"type":"Point"}
}