{
  "type": "Feature",
  "properties": {
    "gn:admin1_code":"10",
    "gn:asciiname":"Dali",
    "gn:country_code":"SS",
    "gn:dem":574,
    "gn:feature_class":"P",
    "gn:feature_code":"PPL",
    "gn:name":"Dali",
    "gn:population":0,
    "gn:timezone":"Africa/Juba",
    "iso:country":"SS",
    "wof:name":"Dali",
    "wof:placetype":"locality"
},
  "geometry": {"coordinates":[29.37639,5.46083],"type":"Point"}
}