{
  "type": "Feature",
  "properties": {
    "gn:admin1_code":"04",
    "gn:asciiname":"Ubori",
    "gn:country_code":"SS",
    "gn:dem":471,
    "gn:feature_class":"P",
    "gn:feature_code":"PPL",
    "gn:name":"Ubori",
    "gn:population":0,
    "gn:timezone":"Africa/Juba",
    "iso:country":"SS",
    "wof:name":"Ubori",
    "wof:placetype":"locality"
},
  "geometry": {"coordinates":[29.3276,6.6679],"type":"Point"}
}