{
  "type": "Feature",
  "properties": {
    "gn:admin1_code":"03",
    "gn:asciiname":"List",
    "gn:country_code":"SS",
    "gn:dem":401,
    "gn:feature_class":"P",
    "gn:feature_code":"PPL",
    "gn:name":"List",
    "gn:population":0,
    "gn:timezone":"Africa/Juba",
    "iso:country":"SS",
    "wof:name":"List",
    "wof:placetype":"locality"
},
  "geometry": {"coordinates":[30.67998,8.80243],"type":"Point"}
}