{
  "type": "Feature",
  "properties": {
    "gn:admin1_code":"05",
    "gn:asciiname":"Wun Riang",
    "gn:country_code":"SS",
    "gn:dem":405,
    "gn:feature_class":"P",
    "gn:feature_code":"PPL",
    "gn:name":"Wun Riang",
    "gn:population":0,
    "gn:timezone":"Africa/Juba",
    "iso:country":"SS",
    "wof:name":"Wun Riang",
    "wof:placetype":"locality"
},
  "geometry": {"coordinates":[28.46888,9.13773],"type":"Point"}
}