{
  "type": "Feature",
  "properties": {
    "gn:admin1_code":"03",
    "gn:asciiname":"Mwot Did",
    "gn:country_code":"SS",
    "gn:dem":409,
    "gn:feature_class":"P",
    "gn:feature_code":"PPL",
    "gn:name":"Mwot Did",
    "gn:population":0,
    "gn:timezone":"Africa/Juba",
    "iso:country":"SS",
    "wof:name":"Mwot Did",
    "wof:placetype":"locality"
},
  "geometry": {"coordinates":[31.83674,8.02047],"type":"Point"}
}