{
  "type": "Feature",
  "properties": {
    "gn:admin1_code":"03",
    "gn:asciiname":"Gumbiel",
    "gn:country_code":"SS",
    "gn:dem":402,
    "gn:feature_class":"P",
    "gn:feature_code":"PPL",
    "gn:name":"Gumbiel",
    "gn:population":0,
    "gn:timezone":"Africa/Juba",
    "iso:country":"SS",
    "name:und_x_variant":[
        "Jumb\u0113l",
        "Gumbiel"
    ],
    "wof:lang_x_official":[
        "eng"
    ],
    "wof:lang_x_spoken":[
        "eng"
    ],
    "wof:name":"Gumbiel",
    "wof:placetype":"locality"
},
  "geometry": {"coordinates":[30.67035,8.56748],"type":"Point"}
}