{
  "type": "Feature",
  "properties": {
    "gn:admin1_code":"05",
    "gn:asciiname":"Marol",
    "gn:country_code":"SS",
    "gn:dem":438,
    "gn:feature_class":"P",
    "gn:feature_code":"PPL",
    "gn:name":"Marol",
    "gn:population":0,
    "gn:timezone":"Africa/Juba",
    "iso:country":"SS",
    "name:mar_x_preferred":[
        "\u092e\u0930\u094b\u0933"
    ],
    "wof:name":"Marol",
    "wof:placetype":"locality"
},
  "geometry": {"coordinates":[27.07297,9.19307],"type":"Point"}
}