{
  "type": "Feature",
  "properties": {
    "gn:admin1_code":"01",
    "gn:asciiname":"Payawa",
    "gn:country_code":"SS",
    "gn:dem":903,
    "gn:feature_class":"P",
    "gn:feature_code":"PPL",
    "gn:name":"Payawa",
    "gn:population":0,
    "gn:timezone":"Africa/Juba",
    "iso:country":"SS",
    "wof:name":"Payawa",
    "wof:placetype":"locality"
},
  "geometry": {"coordinates":[30.74868,3.95848],"type":"Point"}
}