{
  "type": "Feature",
  "properties": {
    "gn:admin1_code":"03",
    "gn:asciiname":"Dongashup",
    "gn:country_code":"SS",
    "gn:dem":402,
    "gn:feature_class":"P",
    "gn:feature_code":"PPL",
    "gn:name":"Dongashup",
    "gn:population":0,
    "gn:timezone":"Africa/Juba",
    "iso:country":"SS",
    "wof:name":"Dongashup",
    "wof:placetype":"locality"
},
  "geometry": {"coordinates":[31.09753,8.66914],"type":"Point"}
}