{
  "type": "Feature",
  "properties": {
    "gn:admin1_code":"07",
    "gn:asciiname":"Jaai",
    "gn:country_code":"SS",
    "gn:dem":406,
    "gn:feature_class":"P",
    "gn:feature_code":"PPL",
    "gn:name":"Jaai",
    "gn:population":0,
    "gn:timezone":"Africa/Juba",
    "iso:country":"SS",
    "wof:name":"Jaai",
    "wof:placetype":"locality"
},
  "geometry": {"coordinates":[33.49219,8.92563],"type":"Point"}
}