{
  "type": "Feature",
  "properties": {
    "gn:admin1_code":"08",
    "gn:asciiname":"Bongo",
    "gn:country_code":"SS",
    "gn:dem":435,
    "gn:feature_class":"P",
    "gn:feature_code":"PPL",
    "gn:name":"Bongo",
    "gn:population":0,
    "gn:timezone":"Africa/Juba",
    "iso:country":"SS",
    "wof:name":"Bongo",
    "wof:placetype":"locality"
},
  "geometry": {"coordinates":[28.69551,7.24626],"type":"Point"}
}