{
  "type": "Feature",
  "properties": {
    "gn:admin1_code":"08",
    "gn:asciiname":"Bongo",
    "gn:country_code":"SS",
    "gn:dem":435,
    "gn:feature_class":"P",
    "gn:feature_code":"PPL",
    "gn:name":"Bongo",
    "gn:population":0,
    "gn:timezone":"Africa/Juba",
    "iso:country":"SS",
    "name:ceb_x_preferred":[
        "Bongo"
    ],
    "name:ces_x_preferred":[
        "Bongo"
    ],
    "name:dan_x_preferred":[
        "Bongo"
    ],
    "name:deu_x_preferred":[
        "Bongo"
    ],
    "name:fra_x_preferred":[
        "Bongo"
    ],
    "name:heb_x_preferred":[
        "\u05d1\u05d5\u05e0\u05d2\u05d5"
    ],
    "name:ind_x_preferred":[
        "Bongo"
    ],
    "name:ita_x_preferred":[
        "Bongo"
    ],
    "name:jpn_x_preferred":[
        "\u30dc\u30f3\u30b4"
    ],
    "name:nds_x_preferred":[
        "Bongo"
    ],
    "name:nld_x_preferred":[
        "Bongo"
    ],
    "name:por_x_preferred":[
        "Bongo"
    ],
    "name:rus_x_preferred":[
        "\u0411\u043e\u043d\u0433\u043e"
    ],
    "name:slk_x_preferred":[
        "Bongo"
    ],
    "name:spa_x_preferred":[
        "Bongo"
    ],
    "name:swe_x_preferred":[
        "Bongo"
    ],
    "name:ukr_x_preferred":[
        "\u0411\u043e\u043d\u0433\u043e"
    ],
    "wof:name":"Bongo",
    "wof:placetype":"locality"
},
  "geometry": {"coordinates":[28.69551,7.24626],"type":"Point"}
}