{
  "type": "Feature",
  "properties": {
    "gn:admin1_code":"05",
    "gn:asciiname":"Toge",
    "gn:country_code":"SS",
    "gn:dem":437,
    "gn:feature_class":"P",
    "gn:feature_code":"PPL",
    "gn:name":"Toge",
    "gn:population":0,
    "gn:timezone":"Africa/Juba",
    "iso:country":"SS",
    "wof:name":"Toge",
    "wof:placetype":"locality"
},
  "geometry": {"coordinates":[27.01698,9.21076],"type":"Point"}
}