{
  "type": "Feature",
  "properties": {
    "gn:admin1_code":"08",
    "gn:asciiname":"Wen",
    "gn:country_code":"SS",
    "gn:dem":470,
    "gn:feature_class":"P",
    "gn:feature_code":"PPL",
    "gn:name":"Wen",
    "gn:population":0,
    "gn:timezone":"Africa/Juba",
    "iso:country":"SS",
    "name:nld_x_preferred":[
        "Wen"
    ],
    "name:nor_x_preferred":[
        "Wen"
    ],
    "name:rus_x_preferred":[
        "\u0412\u044d\u043d\u044c"
    ],
    "name:swe_x_preferred":[
        "Wen"
    ],
    "name:tgl_x_preferred":[
        "Wen"
    ],
    "wof:lang_x_official":[
        "eng"
    ],
    "wof:lang_x_spoken":[
        "eng"
    ],
    "wof:name":"Wen",
    "wof:placetype":"locality"
},
  "geometry": {"coordinates":[27.63474,8.28474],"type":"Point"}
}