{
  "type": "Feature",
  "properties": {
    "gn:admin1_code":"04",
    "gn:asciiname":"Burich",
    "gn:country_code":"SS",
    "gn:dem":469,
    "gn:feature_class":"P",
    "gn:feature_code":"PPL",
    "gn:name":"Burich",
    "gn:population":0,
    "gn:timezone":"Africa/Juba",
    "iso:country":"SS",
    "wof:name":"Burich",
    "wof:placetype":"locality"
},
  "geometry": {"coordinates":[29.05545,6.84167],"type":"Point"}
}