{
  "type": "Feature",
  "properties": {
    "gn:admin1_code":"01",
    "gn:asciiname":"Mngali",
    "gn:country_code":"SS",
    "gn:dem":888,
    "gn:feature_class":"P",
    "gn:feature_code":"PPL",
    "gn:name":"Mngali",
    "gn:population":0,
    "gn:timezone":"Africa/Juba",
    "iso:country":"SS",
    "wof:name":"Mngali",
    "wof:placetype":"locality"
},
  "geometry": {"coordinates":[30.96722,4.23083],"type":"Point"}
}