{
  "type": "Feature",
  "properties": {
    "gn:admin1_code":"08",
    "gn:asciiname":"Achor",
    "gn:country_code":"SS",
    "gn:dem":473,
    "gn:feature_class":"P",
    "gn:feature_code":"PPL",
    "gn:name":"Achor",
    "gn:population":0,
    "gn:timezone":"Africa/Juba",
    "iso:country":"SS",
    "name:ind_x_preferred":[
        "Akhor"
    ],
    "name:pol_x_preferred":[
        "Akor"
    ],
    "name:rus_x_preferred":[
        "\u0410\u0445\u043e\u0440"
    ],
    "wof:lang_x_official":[
        "eng"
    ],
    "wof:lang_x_spoken":[
        "eng"
    ],
    "wof:name":"Achor",
    "wof:placetype":"locality"
},
  "geometry": {"coordinates":[27.86681,7.83698],"type":"Point"}
}